<?xml version="1.0"?>
<dolfin xmlns:dolfin="http://fenicsproject.org">
  <function_data size="1089">
    <dof index="0" value="0" cell_index="1985" cell_dof_index="1" />
    <dof index="1" value="0" cell_index="1921" cell_dof_index="1" />
    <dof index="2" value="0" cell_index="1984" cell_dof_index="2" />
    <dof index="3" value="0" cell_index="1857" cell_dof_index="1" />
    <dof index="4" value="0.0071562198298531906" cell_index="1920" cell_dof_index="2" />
    <dof index="5" value="0.0078669141298791361" cell_index="1986" cell_dof_index="2" />
    <dof index="6" value="0.0086536381908073941" cell_index="1793" cell_dof_index="1" />
    <dof index="7" value="0.0094508018137149184" cell_index="1856" cell_dof_index="2" />
    <dof index="8" value="0.01019132246042617" cell_index="1922" cell_dof_index="2" />
    <dof index="9" value="0.010812236965289322" cell_index="1988" cell_dof_index="2" />
    <dof index="10" value="0.011260026694324637" cell_index="1729" cell_dof_index="1" />
    <dof index="11" value="0.011495206420525437" cell_index="1792" cell_dof_index="2" />
    <dof index="12" value="0.0071562198298532028" cell_index="1858" cell_dof_index="2" />
    <dof index="13" value="0.0078669141298791483" cell_index="1924" cell_dof_index="2" />
    <dof index="14" value="0.0086536381908074028" cell_index="1990" cell_dof_index="2" />
    <dof index="15" value="0.0094508018137149305" cell_index="1665" cell_dof_index="1" />
    <dof index="16" value="0.010191322460426181" cell_index="1728" cell_dof_index="2" />
    <dof index="17" value="0.010812236965289337" cell_index="1794" cell_dof_index="2" />
    <dof index="18" value="0.011260026694324653" cell_index="1860" cell_dof_index="2" />
    <dof index="19" value="0.011495206420525454" cell_index="1926" cell_dof_index="2" />
    <dof index="20" value="0.021236625891172173" cell_index="1992" cell_dof_index="2" />
    <dof index="21" value="0.023345665206828452" cell_index="1601" cell_dof_index="1" />
    <dof index="22" value="0.025680328612754016" cell_index="1664" cell_dof_index="2" />
    <dof index="23" value="0.028045972211783295" cell_index="1730" cell_dof_index="2" />
    <dof index="24" value="0.030243523476669226" cell_index="1796" cell_dof_index="2" />
    <dof index="25" value="0.03208613443101322" cell_index="1862" cell_dof_index="2" />
    <dof index="26" value="0.033414984463506901" cell_index="1928" cell_dof_index="2" />
    <dof index="27" value="0.034112898163932891" cell_index="1994" cell_dof_index="2" />
    <dof index="28" value="0.071098131101757153" cell_index="1537" cell_dof_index="1" />
    <dof index="29" value="0.078158986933173469" cell_index="1600" cell_dof_index="2" />
    <dof index="30" value="0.08597520998873763" cell_index="1666" cell_dof_index="2" />
    <dof index="31" value="0.093895151678426284" cell_index="1732" cell_dof_index="2" />
    <dof index="32" value="0.10125233679504315" cell_index="1798" cell_dof_index="2" />
    <dof index="33" value="0.10742121672318376" cell_index="1864" cell_dof_index="2" />
    <dof index="34" value="0.11187007570431237" cell_index="1930" cell_dof_index="2" />
    <dof index="35" value="0.11420662200996756" cell_index="1996" cell_dof_index="2" />
    <dof index="36" value="0.021236625891172159" cell_index="1473" cell_dof_index="1" />
    <dof index="37" value="0.023345665206828424" cell_index="1536" cell_dof_index="2" />
    <dof index="38" value="0.025680328612753996" cell_index="1602" cell_dof_index="2" />
    <dof index="39" value="0.028045972211783267" cell_index="1668" cell_dof_index="2" />
    <dof index="40" value="0.030243523476669198" cell_index="1734" cell_dof_index="2" />
    <dof index="41" value="0.032086134431013193" cell_index="1800" cell_dof_index="2" />
    <dof index="42" value="0.033414984463506867" cell_index="1866" cell_dof_index="2" />
    <dof index="43" value="0.034112898163932863" cell_index="1932" cell_dof_index="2" />
    <dof index="44" value="0.034566800739645485" cell_index="1998" cell_dof_index="2" />
    <dof index="45" value="0.0379996785494238" cell_index="1409" cell_dof_index="1" />
    <dof index="46" value="0.04179980410422382" cell_index="1472" cell_dof_index="2" />
    <dof index="47" value="0.045650356038778296" cell_index="1538" cell_dof_index="2" />
    <dof index="48" value="0.049227304518152541" cell_index="1604" cell_dof_index="2" />
    <dof index="49" value="0.052226517577039326" cell_index="1670" cell_dof_index="2" />
    <dof index="50" value="0.054389483319406851" cell_index="1736" cell_dof_index="2" />
    <dof index="51" value="0.055525475634745525" cell_index="1802" cell_dof_index="2" />
    <dof index="52" value="0.15388095047705747" cell_index="1868" cell_dof_index="2" />
    <dof index="53" value="0.16916308503787669" cell_index="1934" cell_dof_index="2" />
    <dof index="54" value="0.18608009557377223" cell_index="2000" cell_dof_index="2" />
    <dof index="55" value="0.20322158911300311" cell_index="1345" cell_dof_index="1" />
    <dof index="56" value="0.2191450827553372" cell_index="1408" cell_dof_index="2" />
    <dof index="57" value="0.23249667290279832" cell_index="1474" cell_dof_index="2" />
    <dof index="58" value="0.24212554271900569" cell_index="1540" cell_dof_index="2" />
    <dof index="59" value="0.24718263719921477" cell_index="1606" cell_dof_index="2" />
    <dof index="60" value="0.15388095047705738" cell_index="1672" cell_dof_index="2" />
    <dof index="61" value="0.16916308503787653" cell_index="1738" cell_dof_index="2" />
    <dof index="62" value="0.186080095573772" cell_index="1804" cell_dof_index="2" />
    <dof index="63" value="0.20322158911300281" cell_index="1870" cell_dof_index="2" />
    <dof index="64" value="0.21914508275533692" cell_index="1936" cell_dof_index="2" />
    <dof index="65" value="0.23249667290279805" cell_index="2002" cell_dof_index="2" />
    <dof index="66" value="0.24212554271900544" cell_index="1281" cell_dof_index="1" />
    <dof index="67" value="0.24718263719921449" cell_index="1344" cell_dof_index="2" />
    <dof index="68" value="0.034566800739645506" cell_index="1410" cell_dof_index="2" />
    <dof index="69" value="0.037999678549423821" cell_index="1476" cell_dof_index="2" />
    <dof index="70" value="0.041799804104223841" cell_index="1542" cell_dof_index="2" />
    <dof index="71" value="0.045650356038778324" cell_index="1608" cell_dof_index="2" />
    <dof index="72" value="0.049227304518152569" cell_index="1674" cell_dof_index="2" />
    <dof index="73" value="0.052226517577039354" cell_index="1740" cell_dof_index="2" />
    <dof index="74" value="0.054389483319406878" cell_index="1806" cell_dof_index="2" />
    <dof index="75" value="0.055525475634745552" cell_index="1872" cell_dof_index="2" />
    <dof index="76" value="0.046604961349647124" cell_index="1938" cell_dof_index="2" />
    <dof index="77" value="0.051233365894453153" cell_index="2004" cell_dof_index="2" />
    <dof index="78" value="0.056356915103973622" cell_index="1217" cell_dof_index="1" />
    <dof index="79" value="0.061548452077162426" cell_index="1280" cell_dof_index="2" />
    <dof index="80" value="0.066371101036969693" cell_index="1346" cell_dof_index="2" />
    <dof index="81" value="0.070414813665788722" cell_index="1412" cell_dof_index="2" />
    <dof index="82" value="0.073331049263722831" cell_index="1478" cell_dof_index="2" />
    <dof index="83" value="0.074862659850094895" cell_index="1544" cell_dof_index="2" />
    <dof index="84" value="0.23103474129770349" cell_index="1610" cell_dof_index="2" />
    <dof index="85" value="0.25397912781071741" cell_index="1676" cell_dof_index="2" />
    <dof index="86" value="0.2793780946131344" cell_index="1742" cell_dof_index="2" />
    <dof index="87" value="0.30511409710736709" cell_index="1808" cell_dof_index="2" />
    <dof index="88" value="0.32902141131882162" cell_index="1874" cell_dof_index="2" />
    <dof index="89" value="0.34906730501826011" cell_index="1940" cell_dof_index="2" />
    <dof index="90" value="0.36352395764537276" cell_index="2006" cell_dof_index="2" />
    <dof index="91" value="0.37111660970094568" cell_index="1153" cell_dof_index="1" />
    <dof index="92" value="0.31567037662807967" cell_index="1216" cell_dof_index="2" />
    <dof index="93" value="0.3470200476402433" cell_index="1282" cell_dof_index="2" />
    <dof index="94" value="0.3817234925483477" cell_index="1348" cell_dof_index="2" />
    <dof index="95" value="0.41688744042312742" cell_index="1414" cell_dof_index="2" />
    <dof index="96" value="0.44955279126562725" cell_index="1480" cell_dof_index="2" />
    <dof index="97" value="0.47694215607892299" cell_index="1546" cell_dof_index="2" />
    <dof index="98" value="0.4966947567222243" cell_index="1612" cell_dof_index="2" />
    <dof index="99" value="0.50706884730499191" cell_index="1678" cell_dof_index="2" />
    <dof index="100" value="0.2310347412977031" cell_index="1744" cell_dof_index="2" />
    <dof index="101" value="0.25397912781071702" cell_index="1810" cell_dof_index="2" />
    <dof index="102" value="0.2793780946131339" cell_index="1876" cell_dof_index="2" />
    <dof index="103" value="0.30511409710736653" cell_index="1942" cell_dof_index="2" />
    <dof index="104" value="0.32902141131882107" cell_index="2008" cell_dof_index="2" />
    <dof index="105" value="0.34906730501825955" cell_index="1089" cell_dof_index="1" />
    <dof index="106" value="0.3635239576453721" cell_index="1152" cell_dof_index="2" />
    <dof index="107" value="0.37111660970094501" cell_index="1218" cell_dof_index="2" />
    <dof index="108" value="0.046604961349647048" cell_index="1284" cell_dof_index="2" />
    <dof index="109" value="0.051233365894453077" cell_index="1350" cell_dof_index="2" />
    <dof index="110" value="0.056356915103973546" cell_index="1416" cell_dof_index="2" />
    <dof index="111" value="0.061548452077162349" cell_index="1482" cell_dof_index="2" />
    <dof index="112" value="0.066371101036969596" cell_index="1548" cell_dof_index="2" />
    <dof index="113" value="0.070414813665788625" cell_index="1614" cell_dof_index="2" />
    <dof index="114" value="0.07333104926372272" cell_index="1680" cell_dof_index="2" />
    <dof index="115" value="0.074862659850094784" cell_index="1746" cell_dof_index="2" />
    <dof index="116" value="0.056874373775029519" cell_index="1812" cell_dof_index="2" />
    <dof index="117" value="0.062522648174152845" cell_index="1878" cell_dof_index="2" />
    <dof index="118" value="0.068775172462518741" cell_index="1944" cell_dof_index="2" />
    <dof index="119" value="0.075110665631686696" cell_index="2010" cell_dof_index="2" />
    <dof index="120" value="0.080995986240967946" cell_index="1025" cell_dof_index="1" />
    <dof index="121" value="0.08593073174509662" cell_index="1088" cell_dof_index="2" />
    <dof index="122" value="0.089489560432210347" cell_index="1154" cell_dof_index="2" />
    <dof index="123" value="0.09135866171337205" cell_index="1220" cell_dof_index="2" />
    <dof index="124" value="0.29947958730714813" cell_index="1286" cell_dof_index="2" />
    <dof index="125" value="0.32922132816108679" cell_index="1352" cell_dof_index="2" />
    <dof index="126" value="0.36214482725603175" cell_index="1418" cell_dof_index="2" />
    <dof index="127" value="0.39550521003923" cell_index="1484" cell_dof_index="2" />
    <dof index="128" value="0.42649514927284027" cell_index="1550" cell_dof_index="2" />
    <dof index="129" value="0.45247970873169285" cell_index="1616" cell_dof_index="2" />
    <dof index="130" value="0.47121919500242504" cell_index="1682" cell_dof_index="2" />
    <dof index="131" value="0.48106119664857466" cell_index="1748" cell_dof_index="2" />
    <dof index="132" value="0.46574703077020563" cell_index="1814" cell_dof_index="2" />
    <dof index="133" value="0.51200102630029865" cell_index="1880" cell_dof_index="2" />
    <dof index="134" value="0.56320325375064384" cell_index="1946" cell_dof_index="2" />
    <dof index="135" value="0.6150849174270957" cell_index="2012" cell_dof_index="2" />
    <dof index="136" value="0.66328009597527526" cell_index="961" cell_dof_index="1" />
    <dof index="137" value="0.70369096845794743" cell_index="1024" cell_dof_index="2" />
    <dof index="138" value="0.73283439077674872" cell_index="1090" cell_dof_index="2" />
    <dof index="139" value="0.74814055265825419" cell_index="1156" cell_dof_index="2" />
    <dof index="140" value="0.46574703077020535" cell_index="1222" cell_dof_index="2" />
    <dof index="141" value="0.51200102630029831" cell_index="1288" cell_dof_index="2" />
    <dof index="142" value="0.56320325375064351" cell_index="1354" cell_dof_index="2" />
    <dof index="143" value="0.61508491742709537" cell_index="1420" cell_dof_index="2" />
    <dof index="144" value="0.66328009597527493" cell_index="1486" cell_dof_index="2" />
    <dof index="145" value="0.70369096845794699" cell_index="1552" cell_dof_index="2" />
    <dof index="146" value="0.73283439077674828" cell_index="1618" cell_dof_index="2" />
    <dof index="147" value="0.74814055265825374" cell_index="1684" cell_dof_index="2" />
    <dof index="148" value="0.29947958730714813" cell_index="1750" cell_dof_index="2" />
    <dof index="149" value="0.32922132816108701" cell_index="1816" cell_dof_index="2" />
    <dof index="150" value="0.36214482725603198" cell_index="1882" cell_dof_index="2" />
    <dof index="151" value="0.39550521003923012" cell_index="1948" cell_dof_index="2" />
    <dof index="152" value="0.42649514927284049" cell_index="2014" cell_dof_index="2" />
    <dof index="153" value="0.45247970873169308" cell_index="897" cell_dof_index="1" />
    <dof index="154" value="0.47121919500242526" cell_index="960" cell_dof_index="2" />
    <dof index="155" value="0.48106119664857488" cell_index="1026" cell_dof_index="2" />
    <dof index="156" value="0.05687437377502947" cell_index="1092" cell_dof_index="2" />
    <dof index="157" value="0.062522648174152776" cell_index="1158" cell_dof_index="2" />
    <dof index="158" value="0.068775172462518658" cell_index="1224" cell_dof_index="2" />
    <dof index="159" value="0.075110665631686627" cell_index="1290" cell_dof_index="2" />
    <dof index="160" value="0.080995986240967863" cell_index="1356" cell_dof_index="2" />
    <dof index="161" value="0.085930731745096536" cell_index="1422" cell_dof_index="2" />
    <dof index="162" value="0.089489560432210249" cell_index="1488" cell_dof_index="2" />
    <dof index="163" value="0.091358661713371966" cell_index="1554" cell_dof_index="2" />
    <dof index="164" value="0.064973439857008153" cell_index="1620" cell_dof_index="2" />
    <dof index="165" value="0.071426043949300466" cell_index="1686" cell_dof_index="2" />
    <dof index="166" value="0.078568944764552812" cell_index="1752" cell_dof_index="2" />
    <dof index="167" value="0.085806629455722969" cell_index="1818" cell_dof_index="2" />
    <dof index="168" value="0.092530035785591588" cell_index="1884" cell_dof_index="2" />
    <dof index="169" value="0.098167502520441416" cell_index="1950" cell_dof_index="2" />
    <dof index="170" value="0.10223311812753756" cell_index="2016" cell_dof_index="2" />
    <dof index="171" value="0.10436838453343399" cell_index="833" cell_dof_index="1" />
    <dof index="172" value="0.35652567769434801" cell_index="896" cell_dof_index="2" />
    <dof index="173" value="0.39193274636672809" cell_index="962" cell_dof_index="2" />
    <dof index="174" value="0.43112764753658933" cell_index="1028" cell_dof_index="2" />
    <dof index="175" value="0.47084265177734325" cell_index="1094" cell_dof_index="2" />
    <dof index="176" value="0.50773568073573416" cell_index="1160" cell_dof_index="2" />
    <dof index="177" value="0.53866988481273892" cell_index="1226" cell_dof_index="2" />
    <dof index="178" value="0.56097894468019682" cell_index="1292" cell_dof_index="2" />
    <dof index="179" value="0.57269569084748595" cell_index="1358" cell_dof_index="2" />
    <dof index="180" value="0.59819469957341198" cell_index="1424" cell_dof_index="2" />
    <dof index="181" value="0.6576022601850986" cell_index="1490" cell_dof_index="2" />
    <dof index="182" value="0.72336521527361042" cell_index="1556" cell_dof_index="2" />
    <dof index="183" value="0.79000082251512271" cell_index="1622" cell_dof_index="2" />
    <dof index="184" value="0.85190159363724649" cell_index="1688" cell_dof_index="2" />
    <dof index="185" value="0.90380438233413996" cell_index="1754" cell_dof_index="2" />
    <dof index="186" value="0.94123551899583102" cell_index="1820" cell_dof_index="2" />
    <dof index="187" value="0.96089439882419592" cell_index="1886" cell_dof_index="2" />
    <dof index="188" value="0.68301534657183216" cell_index="1952" cell_dof_index="2" />
    <dof index="189" value="0.75084656545276485" cell_index="2018" cell_dof_index="2" />
    <dof index="190" value="0.82593433803483451" cell_index="769" cell_dof_index="1" />
    <dof index="191" value="0.9020184999415557" cell_index="832" cell_dof_index="2" />
    <dof index="192" value="0.97269645257335169" cell_index="898" cell_dof_index="2" />
    <dof index="193" value="1.0319587650531075" cell_index="964" cell_dof_index="2" />
    <dof index="194" value="1.0746974265587916" cell_index="1030" cell_dof_index="2" />
    <dof index="195" value="1.0971438250788053" cell_index="1096" cell_dof_index="2" />
    <dof index="196" value="0.59819469957341087" cell_index="1162" cell_dof_index="2" />
    <dof index="197" value="0.65760226018509682" cell_index="1228" cell_dof_index="2" />
    <dof index="198" value="0.72336521527360886" cell_index="1294" cell_dof_index="2" />
    <dof index="199" value="0.79000082251512094" cell_index="1360" cell_dof_index="2" />
    <dof index="200" value="0.85190159363724427" cell_index="1426" cell_dof_index="2" />
    <dof index="201" value="0.90380438233413762" cell_index="1492" cell_dof_index="2" />
    <dof index="202" value="0.9412355189958288" cell_index="1558" cell_dof_index="2" />
    <dof index="203" value="0.96089439882419347" cell_index="1624" cell_dof_index="2" />
    <dof index="204" value="0.35652567769434779" cell_index="1690" cell_dof_index="2" />
    <dof index="205" value="0.39193274636672787" cell_index="1756" cell_dof_index="2" />
    <dof index="206" value="0.431127647536589" cell_index="1822" cell_dof_index="2" />
    <dof index="207" value="0.47084265177734286" cell_index="1888" cell_dof_index="2" />
    <dof index="208" value="0.50773568073573383" cell_index="1954" cell_dof_index="2" />
    <dof index="209" value="0.53866988481273859" cell_index="2020" cell_dof_index="2" />
    <dof index="210" value="0.56097894468019638" cell_index="705" cell_dof_index="1" />
    <dof index="211" value="0.57269569084748562" cell_index="768" cell_dof_index="2" />
    <dof index="212" value="0.06497343985700825" cell_index="834" cell_dof_index="2" />
    <dof index="213" value="0.071426043949300563" cell_index="900" cell_dof_index="2" />
    <dof index="214" value="0.078568944764552909" cell_index="966" cell_dof_index="2" />
    <dof index="215" value="0.085806629455723052" cell_index="1032" cell_dof_index="2" />
    <dof index="216" value="0.092530035785591713" cell_index="1098" cell_dof_index="2" />
    <dof index="217" value="0.098167502520441555" cell_index="1164" cell_dof_index="2" />
    <dof index="218" value="0.10223311812753769" cell_index="1230" cell_dof_index="2" />
    <dof index="219" value="0.10436838453343411" cell_index="1296" cell_dof_index="2" />
    <dof index="220" value="0.070587763167650711" cell_index="1362" cell_dof_index="2" />
    <dof index="221" value="0.077597933638596073" cell_index="1428" cell_dof_index="2" />
    <dof index="222" value="0.085358049036313763" cell_index="1494" cell_dof_index="2" />
    <dof index="223" value="0.093221138538528897" cell_index="1560" cell_dof_index="2" />
    <dof index="224" value="0.10052551113657998" cell_index="1626" cell_dof_index="2" />
    <dof index="225" value="0.1066501086278142" cell_index="1692" cell_dof_index="2" />
    <dof index="226" value="0.11106703210048227" cell_index="1758" cell_dof_index="2" />
    <dof index="227" value="0.11338680583711937" cell_index="1824" cell_dof_index="2" />
    <dof index="228" value="0.39995080396012106" cell_index="1890" cell_dof_index="2" />
    <dof index="229" value="0.43967048326336056" cell_index="1956" cell_dof_index="2" />
    <dof index="230" value="0.48363935623599014" cell_index="2022" cell_dof_index="2" />
    <dof index="231" value="0.52819168126932659" cell_index="641" cell_dof_index="1" />
    <dof index="232" value="0.56957831206645648" cell_index="704" cell_dof_index="2" />
    <dof index="233" value="0.60428032811891941" cell_index="770" cell_dof_index="2" />
    <dof index="234" value="0.6293066501703527" cell_index="836" cell_dof_index="2" />
    <dof index="235" value="0.64245050583794205" cell_index="902" cell_dof_index="2" />
    <dof index="236" value="0.70783730154983893" cell_index="968" cell_dof_index="2" />
    <dof index="237" value="0.77813362384260132" cell_index="1034" cell_dof_index="2" />
    <dof index="238" value="0.85595021550580241" cell_index="1100" cell_dof_index="2" />
    <dof index="239" value="0.93479940699914565" cell_index="1166" cell_dof_index="2" />
    <dof index="240" value="1.0080459182540671" cell_index="1232" cell_dof_index="2" />
    <dof index="241" value="1.0694619253171853" cell_index="1298" cell_dof_index="2" />
    <dof index="242" value="1.1137537834487419" cell_index="1364" cell_dof_index="2" />
    <dof index="243" value="1.1370159227808452" cell_index="1430" cell_dof_index="2" />
    <dof index="244" value="0.8743420822021265" cell_index="1496" cell_dof_index="2" />
    <dof index="245" value="0.9611742294625627" cell_index="1562" cell_dof_index="2" />
    <dof index="246" value="1.0572956413120136" cell_index="1628" cell_dof_index="2" />
    <dof index="247" value="1.154692551759223" cell_index="1694" cell_dof_index="2" />
    <dof index="248" value="1.2451688618158501" cell_index="1760" cell_dof_index="2" />
    <dof index="249" value="1.3210317746328659" cell_index="1826" cell_dof_index="2" />
    <dof index="250" value="1.3757424198313513" cell_index="1892" cell_dof_index="2" />
    <dof index="251" value="1.4044765191725046" cell_index="1958" cell_dof_index="2" />
    <dof index="252" value="0.87434208220212606" cell_index="2024" cell_dof_index="2" />
    <dof index="253" value="0.96117422946256248" cell_index="577" cell_dof_index="1" />
    <dof index="254" value="1.0572956413120129" cell_index="640" cell_dof_index="2" />
    <dof index="255" value="1.1546925517592221" cell_index="706" cell_dof_index="2" />
    <dof index="256" value="1.2451688618158492" cell_index="772" cell_dof_index="2" />
    <dof index="257" value="1.321031774632865" cell_index="838" cell_dof_index="2" />
    <dof index="258" value="1.3757424198313504" cell_index="904" cell_dof_index="2" />
    <dof index="259" value="1.4044765191725037" cell_index="970" cell_dof_index="2" />
    <dof index="260" value="0.70783730154983904" cell_index="1036" cell_dof_index="2" />
    <dof index="261" value="0.77813362384260143" cell_index="1102" cell_dof_index="2" />
    <dof index="262" value="0.85595021550580253" cell_index="1168" cell_dof_index="2" />
    <dof index="263" value="0.93479940699914588" cell_index="1234" cell_dof_index="2" />
    <dof index="264" value="1.0080459182540673" cell_index="1300" cell_dof_index="2" />
    <dof index="265" value="1.0694619253171855" cell_index="1366" cell_dof_index="2" />
    <dof index="266" value="1.1137537834487421" cell_index="1432" cell_dof_index="2" />
    <dof index="267" value="1.1370159227808452" cell_index="1498" cell_dof_index="2" />
    <dof index="268" value="0.399950803960122" cell_index="1564" cell_dof_index="2" />
    <dof index="269" value="0.4396704832633615" cell_index="1630" cell_dof_index="2" />
    <dof index="270" value="0.4836393562359913" cell_index="1696" cell_dof_index="2" />
    <dof index="271" value="0.5281916812693277" cell_index="1762" cell_dof_index="2" />
    <dof index="272" value="0.5695783120664577" cell_index="1828" cell_dof_index="2" />
    <dof index="273" value="0.60428032811892085" cell_index="1894" cell_dof_index="2" />
    <dof index="274" value="0.62930665017035403" cell_index="1960" cell_dof_index="2" />
    <dof index="275" value="0.64245050583794339" cell_index="2026" cell_dof_index="2" />
    <dof index="276" value="0.070587763167650822" cell_index="513" cell_dof_index="1" />
    <dof index="277" value="0.077597933638596156" cell_index="576" cell_dof_index="2" />
    <dof index="278" value="0.085358049036313874" cell_index="642" cell_dof_index="2" />
    <dof index="279" value="0.09322113853852905" cell_index="708" cell_dof_index="2" />
    <dof index="280" value="0.10052551113658012" cell_index="774" cell_dof_index="2" />
    <dof index="281" value="0.10665010862781435" cell_index="840" cell_dof_index="2" />
    <dof index="282" value="0.11106703210048242" cell_index="906" cell_dof_index="2" />
    <dof index="283" value="0.11338680583711952" cell_index="972" cell_dof_index="2" />
    <dof index="284" value="0.073500742409314007" cell_index="1038" cell_dof_index="2" />
    <dof index="285" value="0.08080020496356119" cell_index="1104" cell_dof_index="2" />
    <dof index="286" value="0.088880560783301796" cell_index="1170" cell_dof_index="2" />
    <dof index="287" value="0.097068140189537508" cell_index="1236" cell_dof_index="2" />
    <dof index="288" value="0.10467394585185726" cell_index="1302" cell_dof_index="2" />
    <dof index="289" value="0.11105129005944704" cell_index="1368" cell_dof_index="2" />
    <dof index="290" value="0.11565048884175114" cell_index="1434" cell_dof_index="2" />
    <dof index="291" value="0.11806599379916838" cell_index="1500" cell_dof_index="2" />
    <dof index="292" value="0.4280736723595529" cell_index="1566" cell_dof_index="2" />
    <dof index="293" value="0.47058627344930304" cell_index="1632" cell_dof_index="2" />
    <dof index="294" value="0.51764685374202557" cell_index="1698" cell_dof_index="2" />
    <dof index="295" value="0.56533191200503752" cell_index="1764" cell_dof_index="2" />
    <dof index="296" value="0.60962867764845108" cell_index="1830" cell_dof_index="2" />
    <dof index="297" value="0.64677079438573648" cell_index="1896" cell_dof_index="2" />
    <dof index="298" value="0.67355686277248272" cell_index="1962" cell_dof_index="2" />
    <dof index="299" value="0.6876249394181041" cell_index="2028" cell_dof_index="2" />
    <dof index="300" value="0.79041622456161531" cell_index="449" cell_dof_index="1" />
    <dof index="301" value="0.86891357634789945" cell_index="512" cell_dof_index="2" />
    <dof index="302" value="0.95580854000128013" cell_index="578" cell_dof_index="2" />
    <dof index="303" value="1.0438565704080471" cell_index="644" cell_dof_index="2" />
    <dof index="304" value="1.1256482911349157" cell_index="710" cell_dof_index="2" />
    <dof index="305" value="1.1942293172043104" cell_index="776" cell_dof_index="2" />
    <dof index="306" value="1.2436884276616289" cell_index="842" cell_dof_index="2" />
    <dof index="307" value="1.2696644143832223" cell_index="908" cell_dof_index="2" />
    <dof index="308" value="1.032282718161655" cell_index="974" cell_dof_index="2" />
    <dof index="309" value="1.1348001730827997" cell_index="1040" cell_dof_index="2" />
    <dof index="310" value="1.2482848998473848" cell_index="1106" cell_dof_index="2" />
    <dof index="311" value="1.3632755305211008" cell_index="1172" cell_dof_index="2" />
    <dof index="312" value="1.4700954276479334" cell_index="1238" cell_dof_index="2" />
    <dof index="313" value="1.5596621721115795" cell_index="1304" cell_dof_index="2" />
    <dof index="314" value="1.624255715860071" cell_index="1370" cell_dof_index="2" />
    <dof index="315" value="1.6581803258903998" cell_index="1436" cell_dof_index="2" />
    <dof index="316" value="1.1171760961579822" cell_index="1502" cell_dof_index="2" />
    <dof index="317" value="1.2281244323665135" cell_index="1568" cell_dof_index="2" />
    <dof index="318" value="1.3509419723580729" cell_index="1634" cell_dof_index="2" />
    <dof index="319" value="1.47538925953109" cell_index="1700" cell_dof_index="2" />
    <dof index="320" value="1.5909938643206321" cell_index="1766" cell_dof_index="2" />
    <dof index="321" value="1.6879264431239187" cell_index="1832" cell_dof_index="2" />
    <dof index="322" value="1.7578320627495769" cell_index="1898" cell_dof_index="2" />
    <dof index="323" value="1.7945465816798742" cell_index="1964" cell_dof_index="2" />
    <dof index="324" value="1.0322827181616556" cell_index="2030" cell_dof_index="2" />
    <dof index="325" value="1.1348001730828003" cell_index="385" cell_dof_index="1" />
    <dof index="326" value="1.2482848998473861" cell_index="448" cell_dof_index="2" />
    <dof index="327" value="1.3632755305211017" cell_index="514" cell_dof_index="2" />
    <dof index="328" value="1.4700954276479343" cell_index="580" cell_dof_index="2" />
    <dof index="329" value="1.5596621721115809" cell_index="646" cell_dof_index="2" />
    <dof index="330" value="1.6242557158600721" cell_index="712" cell_dof_index="2" />
    <dof index="331" value="1.6581803258904009" cell_index="778" cell_dof_index="2" />
    <dof index="332" value="0.79041622456161398" cell_index="844" cell_dof_index="2" />
    <dof index="333" value="0.86891357634789745" cell_index="910" cell_dof_index="2" />
    <dof index="334" value="0.95580854000127791" cell_index="976" cell_dof_index="2" />
    <dof index="335" value="1.0438565704080451" cell_index="1042" cell_dof_index="2" />
    <dof index="336" value="1.1256482911349137" cell_index="1108" cell_dof_index="2" />
    <dof index="337" value="1.1942293172043081" cell_index="1174" cell_dof_index="2" />
    <dof index="338" value="1.2436884276616267" cell_index="1240" cell_dof_index="2" />
    <dof index="339" value="1.2696644143832201" cell_index="1306" cell_dof_index="2" />
    <dof index="340" value="0.42807367235955363" cell_index="1372" cell_dof_index="2" />
    <dof index="341" value="0.47058627344930387" cell_index="1438" cell_dof_index="2" />
    <dof index="342" value="0.51764685374202657" cell_index="1504" cell_dof_index="2" />
    <dof index="343" value="0.56533191200503852" cell_index="1570" cell_dof_index="2" />
    <dof index="344" value="0.60962867764845208" cell_index="1636" cell_dof_index="2" />
    <dof index="345" value="0.64677079438573759" cell_index="1702" cell_dof_index="2" />
    <dof index="346" value="0.67355686277248383" cell_index="1768" cell_dof_index="2" />
    <dof index="347" value="0.68762493941810521" cell_index="1834" cell_dof_index="2" />
    <dof index="348" value="0.073500742409314035" cell_index="1900" cell_dof_index="2" />
    <dof index="349" value="0.080800204963561217" cell_index="1966" cell_dof_index="2" />
    <dof index="350" value="0.08888056078330181" cell_index="2032" cell_dof_index="2" />
    <dof index="351" value="0.097068140189537522" cell_index="321" cell_dof_index="1" />
    <dof index="352" value="0.10467394585185726" cell_index="384" cell_dof_index="2" />
    <dof index="353" value="0.11105129005944706" cell_index="450" cell_dof_index="2" />
    <dof index="354" value="0.11565048884175115" cell_index="516" cell_dof_index="2" />
    <dof index="355" value="0.11806599379916839" cell_index="582" cell_dof_index="2" />
    <dof index="356" value="0.073601114987818475" cell_index="648" cell_dof_index="2" />
    <dof index="357" value="0.080910545684621082" cell_index="714" cell_dof_index="2" />
    <dof index="358" value="0.08900193603438511" cell_index="780" cell_dof_index="2" />
    <dof index="359" value="0.097200696395122424" cell_index="846" cell_dof_index="2" />
    <dof index="360" value="0.10481688854199876" cell_index="912" cell_dof_index="2" />
    <dof index="361" value="0.11120294164777302" cell_index="978" cell_dof_index="2" />
    <dof index="362" value="0.11580842109372352" cell_index="1044" cell_dof_index="2" />
    <dof index="363" value="0.11822722466354955" cell_index="1110" cell_dof_index="2" />
    <dof index="364" value="0.43981242405143106" cell_index="1176" cell_dof_index="2" />
    <dof index="365" value="0.48349081715361142" cell_index="1242" cell_dof_index="2" />
    <dof index="366" value="0.53184190537102582" cell_index="1308" cell_dof_index="2" />
    <dof index="367" value="0.58083459616204802" cell_index="1374" cell_dof_index="2" />
    <dof index="368" value="0.62634607965945899" cell_index="1440" cell_dof_index="2" />
    <dof index="369" value="0.6645067175388798" cell_index="1506" cell_dof_index="2" />
    <dof index="370" value="0.69202732071693984" cell_index="1572" cell_dof_index="2" />
    <dof index="371" value="0.70648117595439819" cell_index="1638" cell_dof_index="2" />
    <dof index="372" value="0.84274049465875023" cell_index="1704" cell_dof_index="2" />
    <dof index="373" value="0.92643424362052651" cell_index="1770" cell_dof_index="2" />
    <dof index="374" value="1.0190815127137429" cell_index="1836" cell_dof_index="2" />
    <dof index="375" value="1.1129581797063541" cell_index="1902" cell_dof_index="2" />
    <dof index="376" value="1.2001643794811394" cell_index="1968" cell_dof_index="2" />
    <dof index="377" value="1.2732853580718575" cell_index="2034" cell_dof_index="2" />
    <dof index="378" value="1.3260185812990246" cell_index="257" cell_dof_index="1" />
    <dof index="379" value="1.3537141361456451" cell_index="320" cell_dof_index="2" />
    <dof index="380" value="1.1507190762737256" cell_index="386" cell_dof_index="2" />
    <dof index="381" value="1.2649986132196487" cell_index="452" cell_dof_index="2" />
    <dof index="382" value="1.3915037243255284" cell_index="518" cell_dof_index="2" />
    <dof index="383" value="1.5196875154332952" cell_index="584" cell_dof_index="2" />
    <dof index="384" value="1.6387631244567082" cell_index="650" cell_dof_index="2" />
    <dof index="385" value="1.7386060837940465" cell_index="716" cell_dof_index="2" />
    <dof index="386" value="1.8106106051211885" cell_index="782" cell_dof_index="2" />
    <dof index="387" value="1.8484274698523608" cell_index="848" cell_dof_index="2" />
    <dof index="388" value="1.3172792782927281" cell_index="914" cell_dof_index="2" />
    <dof index="389" value="1.448100144180541" cell_index="980" cell_dof_index="2" />
    <dof index="390" value="1.5929161682596051" cell_index="1046" cell_dof_index="2" />
    <dof index="391" value="1.7396538519573936" cell_index="1112" cell_dof_index="2" />
    <dof index="392" value="1.8759649947469623" cell_index="1178" cell_dof_index="2" />
    <dof index="393" value="1.9902596685125111" cell_index="1244" cell_dof_index="2" />
    <dof index="394" value="2.0726864448155298" cell_index="1310" cell_dof_index="2" />
    <dof index="395" value="2.115977090905873" cell_index="1376" cell_dof_index="2" />
    <dof index="396" value="1.3172792782927261" cell_index="1442" cell_dof_index="2" />
    <dof index="397" value="1.4481001441805392" cell_index="1508" cell_dof_index="2" />
    <dof index="398" value="1.5929161682596031" cell_index="1574" cell_dof_index="2" />
    <dof index="399" value="1.7396538519573916" cell_index="1640" cell_dof_index="2" />
    <dof index="400" value="1.8759649947469601" cell_index="1706" cell_dof_index="2" />
    <dof index="401" value="1.9902596685125089" cell_index="1772" cell_dof_index="2" />
    <dof index="402" value="2.0726864448155271" cell_index="1838" cell_dof_index="2" />
    <dof index="403" value="2.1159770909058704" cell_index="1904" cell_dof_index="2" />
    <dof index="404" value="1.1507190762737238" cell_index="1970" cell_dof_index="2" />
    <dof index="405" value="1.2649986132196465" cell_index="2036" cell_dof_index="2" />
    <dof index="406" value="1.3915037243255257" cell_index="193" cell_dof_index="1" />
    <dof index="407" value="1.5196875154332934" cell_index="256" cell_dof_index="2" />
    <dof index="408" value="1.6387631244567056" cell_index="322" cell_dof_index="2" />
    <dof index="409" value="1.7386060837940438" cell_index="388" cell_dof_index="2" />
    <dof index="410" value="1.8106106051211857" cell_index="454" cell_dof_index="2" />
    <dof index="411" value="1.848427469852358" cell_index="520" cell_dof_index="2" />
    <dof index="412" value="0.84274049465875189" cell_index="586" cell_dof_index="2" />
    <dof index="413" value="0.92643424362052818" cell_index="652" cell_dof_index="2" />
    <dof index="414" value="1.0190815127137449" cell_index="718" cell_dof_index="2" />
    <dof index="415" value="1.1129581797063564" cell_index="784" cell_dof_index="2" />
    <dof index="416" value="1.2001643794811416" cell_index="850" cell_dof_index="2" />
    <dof index="417" value="1.2732853580718599" cell_index="916" cell_dof_index="2" />
    <dof index="418" value="1.3260185812990273" cell_index="982" cell_dof_index="2" />
    <dof index="419" value="1.3537141361456477" cell_index="1048" cell_dof_index="2" />
    <dof index="420" value="0.43981242405143151" cell_index="1114" cell_dof_index="2" />
    <dof index="421" value="0.4834908171536117" cell_index="1180" cell_dof_index="2" />
    <dof index="422" value="0.53184190537102605" cell_index="1246" cell_dof_index="2" />
    <dof index="423" value="0.58083459616204836" cell_index="1312" cell_dof_index="2" />
    <dof index="424" value="0.62634607965945932" cell_index="1378" cell_dof_index="2" />
    <dof index="425" value="0.66450671753888013" cell_index="1444" cell_dof_index="2" />
    <dof index="426" value="0.69202732071694029" cell_index="1510" cell_dof_index="2" />
    <dof index="427" value="0.70648117595439863" cell_index="1576" cell_dof_index="2" />
    <dof index="428" value="0.073601114987818586" cell_index="1642" cell_dof_index="2" />
    <dof index="429" value="0.080910545684621235" cell_index="1708" cell_dof_index="2" />
    <dof index="430" value="0.089001936034385262" cell_index="1774" cell_dof_index="2" />
    <dof index="431" value="0.097200696395122591" cell_index="1840" cell_dof_index="2" />
    <dof index="432" value="0.10481688854199894" cell_index="1906" cell_dof_index="2" />
    <dof index="433" value="0.11120294164777322" cell_index="1972" cell_dof_index="2" />
    <dof index="434" value="0.11580842109372372" cell_index="2038" cell_dof_index="2" />
    <dof index="435" value="0.11822722466354975" cell_index="129" cell_dof_index="1" />
    <dof index="436" value="0.070886738927405463" cell_index="192" cell_dof_index="2" />
    <dof index="437" value="0.077926601103378859" cell_index="258" cell_dof_index="2" />
    <dof index="438" value="0.085719584611555127" cell_index="324" cell_dof_index="2" />
    <dof index="439" value="0.093615978372928649" cell_index="390" cell_dof_index="2" />
    <dof index="440" value="0.10095128877448888" cell_index="456" cell_dof_index="2" />
    <dof index="441" value="0.10710182711022595" cell_index="522" cell_dof_index="2" />
    <dof index="442" value="0.11153745854291088" cell_index="588" cell_dof_index="2" />
    <dof index="443" value="0.1138670577235661" cell_index="654" cell_dof_index="2" />
    <dof index="444" value="0.43472261902381198" cell_index="720" cell_dof_index="2" />
    <dof index="445" value="0.47789553639894933" cell_index="786" cell_dof_index="2" />
    <dof index="446" value="0.52568707332030717" cell_index="852" cell_dof_index="2" />
    <dof index="447" value="0.57411278775898422" cell_index="918" cell_dof_index="2" />
    <dof index="448" value="0.6190975817750346" cell_index="984" cell_dof_index="2" />
    <dof index="449" value="0.65681659910006862" cell_index="1050" cell_dof_index="2" />
    <dof index="450" value="0.68401871535789027" cell_index="1116" cell_dof_index="2" />
    <dof index="451" value="0.69830530086617981" cell_index="1182" cell_dof_index="2" />
    <dof index="452" value="0.86280121746698735" cell_index="1248" cell_dof_index="2" />
    <dof index="453" value="0.94848722514819794" cell_index="1314" cell_dof_index="2" />
    <dof index="454" value="1.0433398839147463" cell_index="1380" cell_dof_index="2" />
    <dof index="455" value="1.1394512053551211" cell_index="1446" cell_dof_index="2" />
    <dof index="456" value="1.2287332747622899" cell_index="1512" cell_dof_index="2" />
    <dof index="457" value="1.3035948362397596" cell_index="1578" cell_dof_index="2" />
    <dof index="458" value="1.3575833291266257" cell_index="1644" cell_dof_index="2" />
    <dof index="459" value="1.3859381531697779" cell_index="1710" cell_dof_index="2" />
    <dof index="460" value="1.2250836018106019" cell_index="1776" cell_dof_index="2" />
    <dof index="461" value="1.3467483848333319" cell_index="1842" cell_dof_index="2" />
    <dof index="462" value="1.4814288123646957" cell_index="1908" cell_dof_index="2" />
    <dof index="463" value="1.617896403579536" cell_index="1974" cell_dof_index="2" />
    <dof index="464" value="1.7446672019420486" cell_index="2040" cell_dof_index="2" />
    <dof index="465" value="1.8509624522445822" cell_index="65" cell_dof_index="1" />
    <dof index="466" value="1.9276202222884675" cell_index="128" cell_dof_index="2" />
    <dof index="467" value="1.9678809790702807" cell_index="194" cell_dof_index="2" />
    <dof index="468" value="1.4669181703422425" cell_index="260" cell_dof_index="2" />
    <dof index="469" value="1.6125998859761943" cell_index="326" cell_dof_index="2" />
    <dof index="470" value="1.7738665669139113" cell_index="392" cell_dof_index="2" />
    <dof index="471" value="1.937273202118253" cell_index="458" cell_dof_index="2" />
    <dof index="472" value="2.0890688732968741" cell_index="524" cell_dof_index="2" />
    <dof index="473" value="2.2163470719923866" cell_index="590" cell_dof_index="2" />
    <dof index="474" value="2.3081372776641436" cell_index="656" cell_dof_index="2" />
    <dof index="475" value="2.3563456085794257" cell_index="722" cell_dof_index="2" />
    <dof index="476" value="1.5518015160373106" cell_index="788" cell_dof_index="2" />
    <dof index="477" value="1.7059131166366388" cell_index="854" cell_dof_index="2" />
    <dof index="478" value="1.8765115078932346" cell_index="920" cell_dof_index="2" />
    <dof index="479" value="2.0493736820535644" cell_index="986" cell_dof_index="2" />
    <dof index="480" value="2.2099530227593438" cell_index="1052" cell_dof_index="2" />
    <dof index="481" value="2.3445961853347406" cell_index="1118" cell_dof_index="2" />
    <dof index="482" value="2.4416978391274511" cell_index="1184" cell_dof_index="2" />
    <dof index="483" value="2.4926957492443527" cell_index="1250" cell_dof_index="2" />
    <dof index="484" value="1.46691817034224" cell_index="1316" cell_dof_index="2" />
    <dof index="485" value="1.6125998859761912" cell_index="1382" cell_dof_index="2" />
    <dof index="486" value="1.773866566913908" cell_index="1448" cell_dof_index="2" />
    <dof index="487" value="1.9372732021182497" cell_index="1514" cell_dof_index="2" />
    <dof index="488" value="2.0890688732968701" cell_index="1580" cell_dof_index="2" />
    <dof index="489" value="2.2163470719923826" cell_index="1646" cell_dof_index="2" />
    <dof index="490" value="2.3081372776641391" cell_index="1712" cell_dof_index="2" />
    <dof index="491" value="2.3563456085794212" cell_index="1778" cell_dof_index="2" />
    <dof index="492" value="1.2250836018105977" cell_index="1844" cell_dof_index="2" />
    <dof index="493" value="1.3467483848333279" cell_index="1910" cell_dof_index="2" />
    <dof index="494" value="1.4814288123646915" cell_index="1976" cell_dof_index="2" />
    <dof index="495" value="1.6178964035795311" cell_index="2042" cell_dof_index="2" />
    <dof index="496" value="1.7446672019420431" cell_index="1" cell_dof_index="1" />
    <dof index="497" value="1.8509624522445765" cell_index="64" cell_dof_index="2" />
    <dof index="498" value="1.9276202222884615" cell_index="130" cell_dof_index="2" />
    <dof index="499" value="1.9678809790702745" cell_index="196" cell_dof_index="2" />
    <dof index="500" value="0.86280121746698757" cell_index="262" cell_dof_index="2" />
    <dof index="501" value="0.94848722514819805" cell_index="328" cell_dof_index="2" />
    <dof index="502" value="1.0433398839147465" cell_index="394" cell_dof_index="2" />
    <dof index="503" value="1.1394512053551216" cell_index="460" cell_dof_index="2" />
    <dof index="504" value="1.2287332747622903" cell_index="526" cell_dof_index="2" />
    <dof index="505" value="1.3035948362397598" cell_index="592" cell_dof_index="2" />
    <dof index="506" value="1.3575833291266259" cell_index="658" cell_dof_index="2" />
    <dof index="507" value="1.3859381531697783" cell_index="724" cell_dof_index="2" />
    <dof index="508" value="0.43472261902381293" cell_index="790" cell_dof_index="2" />
    <dof index="509" value="0.47789553639895055" cell_index="856" cell_dof_index="2" />
    <dof index="510" value="0.52568707332030828" cell_index="922" cell_dof_index="2" />
    <dof index="511" value="0.57411278775898544" cell_index="988" cell_dof_index="2" />
    <dof index="512" value="0.61909758177503604" cell_index="1054" cell_dof_index="2" />
    <dof index="513" value="0.65681659910007018" cell_index="1120" cell_dof_index="2" />
    <dof index="514" value="0.68401871535789183" cell_index="1186" cell_dof_index="2" />
    <dof index="515" value="0.69830530086618137" cell_index="1252" cell_dof_index="2" />
    <dof index="516" value="0.070886738927405629" cell_index="1318" cell_dof_index="2" />
    <dof index="517" value="0.077926601103379026" cell_index="1384" cell_dof_index="2" />
    <dof index="518" value="0.08571958461155528" cell_index="1450" cell_dof_index="2" />
    <dof index="519" value="0.093615978372928815" cell_index="1516" cell_dof_index="2" />
    <dof index="520" value="0.1009512887744891" cell_index="1582" cell_dof_index="2" />
    <dof index="521" value="0.10710182711022614" cell_index="1648" cell_dof_index="2" />
    <dof index="522" value="0.11153745854291107" cell_index="1714" cell_dof_index="2" />
    <dof index="523" value="0.11386705772356633" cell_index="1780" cell_dof_index="2" />
    <dof index="524" value="0.065464302938695998" cell_index="1846" cell_dof_index="2" />
    <dof index="525" value="0.071965655337013462" cell_index="1912" cell_dof_index="2" />
    <dof index="526" value="0.079162519530441303" cell_index="1978" cell_dof_index="2" />
    <dof index="527" value="0.086454883675548461" cell_index="2044" cell_dof_index="2" />
    <dof index="528" value="0.093229084175431534" cell_index="0" cell_dof_index="0" />
    <dof index="529" value="0.09890914099479084" cell_index="0" cell_dof_index="2" />
    <dof index="530" value="0.10300547162344423" cell_index="66" cell_dof_index="2" />
    <dof index="531" value="0.1051568695971094" cell_index="132" cell_dof_index="2" />
    <dof index="532" value="0.41301180258902948" cell_index="198" cell_dof_index="2" />
    <dof index="533" value="0.45402858811579327" cell_index="264" cell_dof_index="2" />
    <dof index="534" value="0.49943333116025163" cell_index="330" cell_dof_index="2" />
    <dof index="535" value="0.54544057977522209" cell_index="396" cell_dof_index="2" />
    <dof index="536" value="0.58817875361900718" cell_index="462" cell_dof_index="2" />
    <dof index="537" value="0.62401401650981581" cell_index="528" cell_dof_index="2" />
    <dof index="538" value="0.64985761097266537" cell_index="594" cell_dof_index="2" />
    <dof index="539" value="0.6634306991337342" cell_index="660" cell_dof_index="2" />
    <dof index="540" value="0.84984322210894636" cell_index="726" cell_dof_index="2" />
    <dof index="541" value="0.93424235296696279" cell_index="792" cell_dof_index="2" />
    <dof index="542" value="1.0276704653987216" cell_index="858" cell_dof_index="2" />
    <dof index="543" value="1.1223383372566589" cell_index="924" cell_dof_index="2" />
    <dof index="544" value="1.2102795223239433" cell_index="990" cell_dof_index="2" />
    <dof index="545" value="1.2840167741151465" cell_index="1056" cell_dof_index="2" />
    <dof index="546" value="1.3371944398658739" cell_index="1122" cell_dof_index="2" />
    <dof index="547" value="1.3651234164821904" cell_index="1188" cell_dof_index="2" />
    <dof index="548" value="1.2525269881433698" cell_index="1254" cell_dof_index="2" />
    <dof index="549" value="1.376917212628749" cell_index="1320" cell_dof_index="2" />
    <dof index="550" value="1.5146146481412357" cell_index="1386" cell_dof_index="2" />
    <dof index="551" value="1.6541392820118388" cell_index="1452" cell_dof_index="2" />
    <dof index="552" value="1.7837499028893493" cell_index="1518" cell_dof_index="2" />
    <dof index="553" value="1.8924262981317703" cell_index="1584" cell_dof_index="2" />
    <dof index="554" value="1.9708012969391568" cell_index="1650" cell_dof_index="2" />
    <dof index="555" value="2.0119639444170661" cell_index="1716" cell_dof_index="2" />
    <dof index="556" value="1.5603329580570207" cell_index="1782" cell_dof_index="2" />
    <dof index="557" value="1.7152918282146603" cell_index="1848" cell_dof_index="2" />
    <dof index="558" value="1.8868281295510045" cell_index="1914" cell_dof_index="2" />
    <dof index="559" value="2.0606406595403555" cell_index="1980" cell_dof_index="2" />
    <dof index="560" value="2.2221028279277917" cell_index="2046" cell_dof_index="2" />
    <dof index="561" value="2.3574862271397627" cell_index="0" cell_dof_index="1" />
    <dof index="562" value="2.4551217231286491" cell_index="2" cell_dof_index="2" />
    <dof index="563" value="2.5064000078352082" cell_index="68" cell_dof_index="2" />
    <dof index="564" value="1.7268032663194264" cell_index="134" cell_dof_index="2" />
    <dof index="565" value="1.8982945379430061" cell_index="200" cell_dof_index="2" />
    <dof index="566" value="2.0881318697191698" cell_index="266" cell_dof_index="2" />
    <dof index="567" value="2.280488278627304" cell_index="332" cell_dof_index="2" />
    <dof index="568" value="2.4591766786375362" cell_index="398" cell_dof_index="2" />
    <dof index="569" value="2.6090039925819712" cell_index="464" cell_dof_index="2" />
    <dof index="570" value="2.717056118579662" cell_index="530" cell_dof_index="2" />
    <dof index="571" value="2.7738052304056442" cell_index="596" cell_dof_index="2" />
    <dof index="572" value="1.7268032663194264" cell_index="662" cell_dof_index="2" />
    <dof index="573" value="1.8982945379430061" cell_index="728" cell_dof_index="2" />
    <dof index="574" value="2.0881318697191698" cell_index="794" cell_dof_index="2" />
    <dof index="575" value="2.280488278627304" cell_index="860" cell_dof_index="2" />
    <dof index="576" value="2.4591766786375362" cell_index="926" cell_dof_index="2" />
    <dof index="577" value="2.6090039925819712" cell_index="992" cell_dof_index="2" />
    <dof index="578" value="2.717056118579662" cell_index="1058" cell_dof_index="2" />
    <dof index="579" value="2.7738052304056442" cell_index="1124" cell_dof_index="2" />
    <dof index="580" value="1.5603329580570178" cell_index="1190" cell_dof_index="2" />
    <dof index="581" value="1.715291828214657" cell_index="1256" cell_dof_index="2" />
    <dof index="582" value="1.886828129551001" cell_index="1322" cell_dof_index="2" />
    <dof index="583" value="2.0606406595403515" cell_index="1388" cell_dof_index="2" />
    <dof index="584" value="2.2221028279277872" cell_index="1454" cell_dof_index="2" />
    <dof index="585" value="2.3574862271397579" cell_index="1520" cell_dof_index="2" />
    <dof index="586" value="2.4551217231286446" cell_index="1586" cell_dof_index="2" />
    <dof index="587" value="2.5064000078352033" cell_index="1652" cell_dof_index="2" />
    <dof index="588" value="1.2525269881433692" cell_index="1718" cell_dof_index="2" />
    <dof index="589" value="1.3769172126287474" cell_index="1784" cell_dof_index="2" />
    <dof index="590" value="1.5146146481412341" cell_index="1850" cell_dof_index="2" />
    <dof index="591" value="1.6541392820118379" cell_index="1916" cell_dof_index="2" />
    <dof index="592" value="1.7837499028893478" cell_index="1982" cell_dof_index="2" />
    <dof index="593" value="1.8924262981317692" cell_index="2" cell_dof_index="1" />
    <dof index="594" value="1.9708012969391555" cell_index="4" cell_dof_index="2" />
    <dof index="595" value="2.0119639444170647" cell_index="70" cell_dof_index="2" />
    <dof index="596" value="0.84984322210894747" cell_index="136" cell_dof_index="2" />
    <dof index="597" value="0.93424235296696412" cell_index="202" cell_dof_index="2" />
    <dof index="598" value="1.027670465398723" cell_index="268" cell_dof_index="2" />
    <dof index="599" value="1.1223383372566602" cell_index="334" cell_dof_index="2" />
    <dof index="600" value="1.2102795223239446" cell_index="400" cell_dof_index="2" />
    <dof index="601" value="1.284016774115148" cell_index="466" cell_dof_index="2" />
    <dof index="602" value="1.3371944398658757" cell_index="532" cell_dof_index="2" />
    <dof index="603" value="1.3651234164821922" cell_index="598" cell_dof_index="2" />
    <dof index="604" value="0.4130118025890302" cell_index="664" cell_dof_index="2" />
    <dof index="605" value="0.45402858811579411" cell_index="730" cell_dof_index="2" />
    <dof index="606" value="0.49943333116025257" cell_index="796" cell_dof_index="2" />
    <dof index="607" value="0.5454405797752232" cell_index="862" cell_dof_index="2" />
    <dof index="608" value="0.58817875361900818" cell_index="928" cell_dof_index="2" />
    <dof index="609" value="0.62401401650981692" cell_index="994" cell_dof_index="2" />
    <dof index="610" value="0.64985761097266648" cell_index="1060" cell_dof_index="2" />
    <dof index="611" value="0.66343069913373542" cell_index="1126" cell_dof_index="2" />
    <dof index="612" value="0.065464302938696095" cell_index="1192" cell_dof_index="2" />
    <dof index="613" value="0.071965655337013559" cell_index="1258" cell_dof_index="2" />
    <dof index="614" value="0.079162519530441414" cell_index="1324" cell_dof_index="2" />
    <dof index="615" value="0.086454883675548613" cell_index="1390" cell_dof_index="2" />
    <dof index="616" value="0.093229084175431659" cell_index="1456" cell_dof_index="2" />
    <dof index="617" value="0.098909140994790992" cell_index="1522" cell_dof_index="2" />
    <dof index="618" value="0.10300547162344439" cell_index="1588" cell_dof_index="2" />
    <dof index="619" value="0.10515686959710957" cell_index="1654" cell_dof_index="2" />
    <dof index="620" value="0.057544910116443491" cell_index="1720" cell_dof_index="2" />
    <dof index="621" value="0.063259776426817946" cell_index="1786" cell_dof_index="2" />
    <dof index="622" value="0.069586016599555739" cell_index="1852" cell_dof_index="2" />
    <dof index="623" value="0.075996203837928072" cell_index="1918" cell_dof_index="2" />
    <dof index="624" value="0.081950911081073732" cell_index="4" cell_dof_index="1" />
    <dof index="625" value="0.08694383614792138" cell_index="6" cell_dof_index="2" />
    <dof index="626" value="0.090544622641498457" cell_index="72" cell_dof_index="2" />
    <dof index="627" value="0.092435760215134513" cell_index="138" cell_dof_index="2" />
    <dof index="628" value="0.37552949635864141" cell_index="204" cell_dof_index="2" />
    <dof index="629" value="0.41282386110696073" cell_index="270" cell_dof_index="2" />
    <dof index="630" value="0.45410796044962654" cell_index="336" cell_dof_index="2" />
    <dof index="631" value="0.49593988581573606" cell_index="402" cell_dof_index="2" />
    <dof index="632" value="0.53479941670138187" cell_index="468" cell_dof_index="2" />
    <dof index="633" value="0.56738250062514939" cell_index="534" cell_dof_index="2" />
    <dof index="634" value="0.59088069595974602" cell_index="600" cell_dof_index="2" />
    <dof index="635" value="0.60322197756285201" cell_index="666" cell_dof_index="2" />
    <dof index="636" value="0.80438977070339668" cell_index="732" cell_dof_index="2" />
    <dof index="637" value="0.88427485509575365" cell_index="798" cell_dof_index="2" />
    <dof index="638" value="0.97270601037370852" cell_index="864" cell_dof_index="2" />
    <dof index="639" value="1.0623106171479009" cell_index="930" cell_dof_index="2" />
    <dof index="640" value="1.1455483107028532" cell_index="996" cell_dof_index="2" />
    <dof index="641" value="1.2153417614447839" cell_index="1062" cell_dof_index="2" />
    <dof index="642" value="1.2656752456062734" cell_index="1128" cell_dof_index="2" />
    <dof index="643" value="1.2921104544917765" cell_index="1194" cell_dof_index="2" />
    <dof index="644" value="1.232021428733785" cell_index="1260" cell_dof_index="2" />
    <dof index="645" value="1.3543752171484822" cell_index="1326" cell_dof_index="2" />
    <dof index="646" value="1.4898183595629544" cell_index="1392" cell_dof_index="2" />
    <dof index="647" value="1.6270587866292197" cell_index="1458" cell_dof_index="2" />
    <dof index="648" value="1.7545475064924803" cell_index="1524" cell_dof_index="2" />
    <dof index="649" value="1.8614447222839532" cell_index="1590" cell_dof_index="2" />
    <dof index="650" value="1.9385366164480988" cell_index="1656" cell_dof_index="2" />
    <dof index="651" value="1.9790253757612783" cell_index="1722" cell_dof_index="2" />
    <dof index="652" value="1.5939521544275477" cell_index="1788" cell_dof_index="2" />
    <dof index="653" value="1.7522497944665034" cell_index="1854" cell_dof_index="2" />
    <dof index="654" value="1.9274820458047504" cell_index="6" cell_dof_index="1" />
    <dof index="655" value="2.1050395698014364" cell_index="8" cell_dof_index="2" />
    <dof index="656" value="2.269980629227736" cell_index="74" cell_dof_index="2" />
    <dof index="657" value="2.4082810219313293" cell_index="140" cell_dof_index="2" />
    <dof index="658" value="2.5080201887395983" cell_index="206" cell_dof_index="2" />
    <dof index="659" value="2.5604033239937225" cell_index="272" cell_dof_index="2" />
    <dof index="660" value="1.8355605139917703" cell_index="338" cell_dof_index="2" />
    <dof index="661" value="2.0178526215098547" cell_index="404" cell_dof_index="2" />
    <dof index="662" value="2.2196462578124985" cell_index="470" cell_dof_index="2" />
    <dof index="663" value="2.4241176273609244" cell_index="536" cell_dof_index="2" />
    <dof index="664" value="2.6140601516568416" cell_index="602" cell_dof_index="2" />
    <dof index="665" value="2.7733238655714176" cell_index="668" cell_dof_index="2" />
    <dof index="666" value="2.8881813133204983" cell_index="734" cell_dof_index="2" />
    <dof index="667" value="2.94850458864873" cell_index="800" cell_dof_index="2" />
    <dof index="668" value="1.9203657963442078" cell_index="866" cell_dof_index="2" />
    <dof index="669" value="2.1110800362468423" cell_index="932" cell_dof_index="2" />
    <dof index="670" value="2.3221968009198806" cell_index="998" cell_dof_index="2" />
    <dof index="671" value="2.5361150135962576" cell_index="1064" cell_dof_index="2" />
    <dof index="672" value="2.7348331294789761" cell_index="1130" cell_dof_index="2" />
    <dof index="673" value="2.9014550340519754" cell_index="1196" cell_dof_index="2" />
    <dof index="674" value="3.0216190452253575" cell_index="1262" cell_dof_index="2" />
    <dof index="675" value="3.0847293343064126" cell_index="1328" cell_dof_index="2" />
    <dof index="676" value="1.8355605139917677" cell_index="1394" cell_dof_index="2" />
    <dof index="677" value="2.017852621509852" cell_index="1460" cell_dof_index="2" />
    <dof index="678" value="2.2196462578124949" cell_index="1526" cell_dof_index="2" />
    <dof index="679" value="2.4241176273609195" cell_index="1592" cell_dof_index="2" />
    <dof index="680" value="2.6140601516568367" cell_index="1658" cell_dof_index="2" />
    <dof index="681" value="2.7733238655714136" cell_index="1724" cell_dof_index="2" />
    <dof index="682" value="2.8881813133204943" cell_index="1790" cell_dof_index="2" />
    <dof index="683" value="2.9485045886487256" cell_index="8" cell_dof_index="1" />
    <dof index="684" value="1.5939521544275495" cell_index="10" cell_dof_index="2" />
    <dof index="685" value="1.7522497944665048" cell_index="76" cell_dof_index="2" />
    <dof index="686" value="1.9274820458047515" cell_index="142" cell_dof_index="2" />
    <dof index="687" value="2.1050395698014377" cell_index="208" cell_dof_index="2" />
    <dof index="688" value="2.2699806292277374" cell_index="274" cell_dof_index="2" />
    <dof index="689" value="2.4082810219313311" cell_index="340" cell_dof_index="2" />
    <dof index="690" value="2.5080201887396001" cell_index="406" cell_dof_index="2" />
    <dof index="691" value="2.5604033239937243" cell_index="472" cell_dof_index="2" />
    <dof index="692" value="1.2320214287337858" cell_index="538" cell_dof_index="2" />
    <dof index="693" value="1.3543752171484829" cell_index="604" cell_dof_index="2" />
    <dof index="694" value="1.4898183595629553" cell_index="670" cell_dof_index="2" />
    <dof index="695" value="1.6270587866292203" cell_index="736" cell_dof_index="2" />
    <dof index="696" value="1.7545475064924807" cell_index="802" cell_dof_index="2" />
    <dof index="697" value="1.8614447222839541" cell_index="868" cell_dof_index="2" />
    <dof index="698" value="1.9385366164480997" cell_index="934" cell_dof_index="2" />
    <dof index="699" value="1.9790253757612792" cell_index="1000" cell_dof_index="2" />
    <dof index="700" value="0.8043897707033939" cell_index="1066" cell_dof_index="2" />
    <dof index="701" value="0.88427485509575043" cell_index="1132" cell_dof_index="2" />
    <dof index="702" value="0.97270601037370519" cell_index="1198" cell_dof_index="2" />
    <dof index="703" value="1.0623106171478969" cell_index="1264" cell_dof_index="2" />
    <dof index="704" value="1.1455483107028492" cell_index="1330" cell_dof_index="2" />
    <dof index="705" value="1.2153417614447795" cell_index="1396" cell_dof_index="2" />
    <dof index="706" value="1.2656752456062688" cell_index="1462" cell_dof_index="2" />
    <dof index="707" value="1.2921104544917721" cell_index="1528" cell_dof_index="2" />
    <dof index="708" value="0.37552949635864236" cell_index="1594" cell_dof_index="2" />
    <dof index="709" value="0.41282386110696179" cell_index="1660" cell_dof_index="2" />
    <dof index="710" value="0.45410796044962765" cell_index="1726" cell_dof_index="2" />
    <dof index="711" value="0.49593988581573739" cell_index="10" cell_dof_index="1" />
    <dof index="712" value="0.53479941670138331" cell_index="12" cell_dof_index="2" />
    <dof index="713" value="0.56738250062515094" cell_index="78" cell_dof_index="2" />
    <dof index="714" value="0.59088069595974757" cell_index="144" cell_dof_index="2" />
    <dof index="715" value="0.60322197756285367" cell_index="210" cell_dof_index="2" />
    <dof index="716" value="0.057544910116443554" cell_index="276" cell_dof_index="2" />
    <dof index="717" value="0.063259776426818029" cell_index="342" cell_dof_index="2" />
    <dof index="718" value="0.069586016599555808" cell_index="408" cell_dof_index="2" />
    <dof index="719" value="0.075996203837928142" cell_index="474" cell_dof_index="2" />
    <dof index="720" value="0.081950911081073843" cell_index="540" cell_dof_index="2" />
    <dof index="721" value="0.086943836147921477" cell_index="606" cell_dof_index="2" />
    <dof index="722" value="0.090544622641498568" cell_index="672" cell_dof_index="2" />
    <dof index="723" value="0.092435760215134624" cell_index="738" cell_dof_index="2" />
    <dof index="724" value="0.047435681816530503" cell_index="804" cell_dof_index="2" />
    <dof index="725" value="0.052146586384360726" cell_index="870" cell_dof_index="2" />
    <dof index="726" value="0.057361461432765597" cell_index="936" cell_dof_index="2" />
    <dof index="727" value="0.062645536107806668" cell_index="1002" cell_dof_index="2" />
    <dof index="728" value="0.067554147443281379" cell_index="1068" cell_dof_index="2" />
    <dof index="729" value="0.071669938124429497" cell_index="1134" cell_dof_index="2" />
    <dof index="730" value="0.074638154810370144" cell_index="1200" cell_dof_index="2" />
    <dof index="731" value="0.076197065929229493" cell_index="1266" cell_dof_index="2" />
    <dof index="732" value="0.32373275815124014" cell_index="1332" cell_dof_index="2" />
    <dof index="733" value="0.35588311566121666" cell_index="1398" cell_dof_index="2" />
    <dof index="734" value="0.39147290415342856" cell_index="1464" cell_dof_index="2" />
    <dof index="735" value="0.42753495709164607" cell_index="1530" cell_dof_index="2" />
    <dof index="736" value="0.46103459756212228" cell_index="1596" cell_dof_index="2" />
    <dof index="737" value="0.48912350064429377" cell_index="1662" cell_dof_index="2" />
    <dof index="738" value="0.50938059272629765" cell_index="12" cell_dof_index="1" />
    <dof index="739" value="0.52001964284415869" cell_index="14" cell_dof_index="2" />
    <dof index="740" value="0.72821872369409291" cell_index="80" cell_dof_index="2" />
    <dof index="741" value="0.80053915381036234" cell_index="146" cell_dof_index="2" />
    <dof index="742" value="0.88059639145399182" cell_index="212" cell_dof_index="2" />
    <dof index="743" value="0.96171596154145556" cell_index="278" cell_dof_index="2" />
    <dof index="744" value="1.0370715281728198" cell_index="344" cell_dof_index="2" />
    <dof index="745" value="1.100255943828742" cell_index="410" cell_dof_index="2" />
    <dof index="746" value="1.1458231389002367" cell_index="476" cell_dof_index="2" />
    <dof index="747" value="1.1697550867895719" cell_index="542" cell_dof_index="2" />
    <dof index="748" value="1.1643946862584793" cell_index="608" cell_dof_index="2" />
    <dof index="749" value="1.2800323673498633" cell_index="674" cell_dof_index="2" />
    <dof index="750" value="1.4080409162593164" cell_index="740" cell_dof_index="2" />
    <dof index="751" value="1.5377480952813891" cell_index="806" cell_dof_index="2" />
    <dof index="752" value="1.6582388469067435" cell_index="872" cell_dof_index="2" />
    <dof index="753" value="1.7592683802739852" cell_index="938" cell_dof_index="2" />
    <dof index="754" value="1.8321286323968635" cell_index="1004" cell_dof_index="2" />
    <dof index="755" value="1.8703949280131" cell_index="1070" cell_dof_index="2" />
    <dof index="756" value="1.5665236638922597" cell_index="1136" cell_dof_index="2" />
    <dof index="757" value="1.7220973417912555" cell_index="1202" cell_dof_index="2" />
    <dof index="758" value="1.8943142227283536" cell_index="1268" cell_dof_index="2" />
    <dof index="759" value="2.0688163633793826" cell_index="1334" cell_dof_index="2" />
    <dof index="760" value="2.2309191416974392" cell_index="1400" cell_dof_index="2" />
    <dof index="761" value="2.3668396819056112" cell_index="1466" cell_dof_index="2" />
    <dof index="762" value="2.4648625520325775" cell_index="1532" cell_dof_index="2" />
    <dof index="763" value="2.5163442861213436" cell_index="1598" cell_dof_index="2" />
    <dof index="764" value="1.8739244981098844" cell_index="14" cell_dof_index="1" />
    <dof index="765" value="2.0600265870828833" cell_index="16" cell_dof_index="2" />
    <dof index="766" value="2.2660377949661092" cell_index="82" cell_dof_index="2" />
    <dof index="767" value="2.4747827018423263" cell_index="148" cell_dof_index="2" />
    <dof index="768" value="2.6686951045104901" cell_index="214" cell_dof_index="2" />
    <dof index="769" value="2.8312874968013095" cell_index="280" cell_dof_index="2" />
    <dof index="770" value="2.9485455133508758" cell_index="346" cell_dof_index="2" />
    <dof index="771" value="3.0101295704179845" cell_index="412" cell_dof_index="2" />
    <dof index="772" value="2.040180836083588" cell_index="478" cell_dof_index="2" />
    <dof index="773" value="2.2427940768309043" cell_index="544" cell_dof_index="2" />
    <dof index="774" value="2.467082792179748" cell_index="610" cell_dof_index="2" />
    <dof index="775" value="2.6943477428586387" cell_index="676" cell_dof_index="2" />
    <dof index="776" value="2.9054642356530631" cell_index="742" cell_dof_index="2" />
    <dof index="777" value="3.0824819773920185" cell_index="808" cell_dof_index="2" />
    <dof index="778" value="3.2101432350803045" cell_index="874" cell_dof_index="2" />
    <dof index="779" value="3.2771910874155084" cell_index="940" cell_dof_index="2" />
    <dof index="780" value="2.0401808360835845" cell_index="1006" cell_dof_index="2" />
    <dof index="781" value="2.2427940768309012" cell_index="1072" cell_dof_index="2" />
    <dof index="782" value="2.4670827921797436" cell_index="1138" cell_dof_index="2" />
    <dof index="783" value="2.6943477428586355" cell_index="1204" cell_dof_index="2" />
    <dof index="784" value="2.9054642356530591" cell_index="1270" cell_dof_index="2" />
    <dof index="785" value="3.0824819773920136" cell_index="1336" cell_dof_index="2" />
    <dof index="786" value="3.2101432350802996" cell_index="1402" cell_dof_index="2" />
    <dof index="787" value="3.2771910874155039" cell_index="1468" cell_dof_index="2" />
    <dof index="788" value="1.873924498109875" cell_index="1534" cell_dof_index="2" />
    <dof index="789" value="2.0600265870828722" cell_index="16" cell_dof_index="1" />
    <dof index="790" value="2.2660377949660973" cell_index="18" cell_dof_index="2" />
    <dof index="791" value="2.4747827018423139" cell_index="84" cell_dof_index="2" />
    <dof index="792" value="2.6686951045104768" cell_index="150" cell_dof_index="2" />
    <dof index="793" value="2.831287496801294" cell_index="216" cell_dof_index="2" />
    <dof index="794" value="2.9485455133508607" cell_index="282" cell_dof_index="2" />
    <dof index="795" value="3.0101295704179694" cell_index="348" cell_dof_index="2" />
    <dof index="796" value="1.5665236638922604" cell_index="414" cell_dof_index="2" />
    <dof index="797" value="1.7220973417912564" cell_index="480" cell_dof_index="2" />
    <dof index="798" value="1.8943142227283549" cell_index="546" cell_dof_index="2" />
    <dof index="799" value="2.0688163633793835" cell_index="612" cell_dof_index="2" />
    <dof index="800" value="2.2309191416974405" cell_index="678" cell_dof_index="2" />
    <dof index="801" value="2.3668396819056126" cell_index="744" cell_dof_index="2" />
    <dof index="802" value="2.4648625520325793" cell_index="810" cell_dof_index="2" />
    <dof index="803" value="2.516344286121345" cell_index="876" cell_dof_index="2" />
    <dof index="804" value="1.1643946862584829" cell_index="942" cell_dof_index="2" />
    <dof index="805" value="1.2800323673498666" cell_index="1008" cell_dof_index="2" />
    <dof index="806" value="1.4080409162593199" cell_index="1074" cell_dof_index="2" />
    <dof index="807" value="1.5377480952813929" cell_index="1140" cell_dof_index="2" />
    <dof index="808" value="1.6582388469067475" cell_index="1206" cell_dof_index="2" />
    <dof index="809" value="1.7592683802739899" cell_index="1272" cell_dof_index="2" />
    <dof index="810" value="1.8321286323968684" cell_index="1338" cell_dof_index="2" />
    <dof index="811" value="1.8703949280131049" cell_index="1404" cell_dof_index="2" />
    <dof index="812" value="0.72821872369409246" cell_index="1470" cell_dof_index="2" />
    <dof index="813" value="0.80053915381036211" cell_index="18" cell_dof_index="1" />
    <dof index="814" value="0.88059639145399127" cell_index="20" cell_dof_index="2" />
    <dof index="815" value="0.961715961541455" cell_index="86" cell_dof_index="2" />
    <dof index="816" value="1.0370715281728193" cell_index="152" cell_dof_index="2" />
    <dof index="817" value="1.1002559438287414" cell_index="218" cell_dof_index="2" />
    <dof index="818" value="1.1458231389002362" cell_index="284" cell_dof_index="2" />
    <dof index="819" value="1.1697550867895712" cell_index="350" cell_dof_index="2" />
    <dof index="820" value="0.32373275815124097" cell_index="416" cell_dof_index="2" />
    <dof index="821" value="0.35588311566121766" cell_index="482" cell_dof_index="2" />
    <dof index="822" value="0.39147290415342972" cell_index="548" cell_dof_index="2" />
    <dof index="823" value="0.42753495709164724" cell_index="614" cell_dof_index="2" />
    <dof index="824" value="0.46103459756212356" cell_index="680" cell_dof_index="2" />
    <dof index="825" value="0.48912350064429527" cell_index="746" cell_dof_index="2" />
    <dof index="826" value="0.50938059272629921" cell_index="812" cell_dof_index="2" />
    <dof index="827" value="0.52001964284416013" cell_index="878" cell_dof_index="2" />
    <dof index="828" value="0.047435681816530663" cell_index="944" cell_dof_index="2" />
    <dof index="829" value="0.052146586384360899" cell_index="1010" cell_dof_index="2" />
    <dof index="830" value="0.057361461432765777" cell_index="1076" cell_dof_index="2" />
    <dof index="831" value="0.062645536107806862" cell_index="1142" cell_dof_index="2" />
    <dof index="832" value="0.067554147443281587" cell_index="1208" cell_dof_index="2" />
    <dof index="833" value="0.071669938124429747" cell_index="1274" cell_dof_index="2" />
    <dof index="834" value="0.074638154810370394" cell_index="1340" cell_dof_index="2" />
    <dof index="835" value="0.076197065929229743" cell_index="1406" cell_dof_index="2" />
    <dof index="836" value="0.035527700718211083" cell_index="20" cell_dof_index="1" />
    <dof index="837" value="0.039056006862207539" cell_index="22" cell_dof_index="2" />
    <dof index="838" value="0.042961769632081544" cell_index="88" cell_dof_index="2" />
    <dof index="839" value="0.046919360551795436" cell_index="154" cell_dof_index="2" />
    <dof index="840" value="0.050595742292091024" cell_index="220" cell_dof_index="2" />
    <dof index="841" value="0.053678328521254814" cell_index="286" cell_dof_index="2" />
    <dof index="842" value="0.055901421139439779" cell_index="352" cell_dof_index="2" />
    <dof index="843" value="0.057068992165220343" cell_index="418" cell_dof_index="2" />
    <dof index="844" value="0.25962856166074627" cell_index="484" cell_dof_index="2" />
    <dof index="845" value="0.2854126408650336" cell_index="550" cell_dof_index="2" />
    <dof index="846" value="0.31395508942294714" cell_index="616" cell_dof_index="2" />
    <dof index="847" value="0.34287628661149078" cell_index="682" cell_dof_index="2" />
    <dof index="848" value="0.36974246945060463" cell_index="748" cell_dof_index="2" />
    <dof index="849" value="0.39226932631704914" cell_index="814" cell_dof_index="2" />
    <dof index="850" value="0.40851519439266398" cell_index="880" cell_dof_index="2" />
    <dof index="851" value="0.41704754464140342" cell_index="946" cell_dof_index="2" />
    <dof index="852" value="0.62429081069388703" cell_index="1012" cell_dof_index="2" />
    <dof index="853" value="0.68629001296375702" cell_index="1078" cell_dof_index="2" />
    <dof index="854" value="0.75492186238520864" cell_index="1144" cell_dof_index="2" />
    <dof index="855" value="0.82446443321632634" cell_index="1210" cell_dof_index="2" />
    <dof index="856" value="0.88906561175228704" cell_index="1276" cell_dof_index="2" />
    <dof index="857" value="0.94323264809674834" cell_index="1342" cell_dof_index="2" />
    <dof index="858" value="0.98229670979503003" cell_index="22" cell_dof_index="1" />
    <dof index="859" value="1.002813203896592" cell_index="24" cell_dof_index="2" />
    <dof index="860" value="1.0522932349224166" cell_index="90" cell_dof_index="2" />
    <dof index="861" value="1.1567979625295015" cell_index="156" cell_dof_index="2" />
    <dof index="862" value="1.2724825595302725" cell_index="222" cell_dof_index="2" />
    <dof index="863" value="1.3897022519735447" cell_index="288" cell_dof_index="2" />
    <dof index="864" value="1.4985928234459149" cell_index="354" cell_dof_index="2" />
    <dof index="865" value="1.5898957946328833" cell_index="420" cell_dof_index="2" />
    <dof index="866" value="1.6557414664729098" cell_index="486" cell_dof_index="2" />
    <dof index="867" value="1.6903236957442378" cell_index="552" cell_dof_index="2" />
    <dof index="868" value="1.4791568534809145" cell_index="618" cell_dof_index="2" />
    <dof index="869" value="1.6260540100254699" cell_index="684" cell_dof_index="2" />
    <dof index="870" value="1.788666159203151" cell_index="750" cell_dof_index="2" />
    <dof index="871" value="1.9534361165555556" cell_index="816" cell_dof_index="2" />
    <dof index="872" value="2.1064982381462971" cell_index="882" cell_dof_index="2" />
    <dof index="873" value="2.2348383348916041" cell_index="948" cell_dof_index="2" />
    <dof index="874" value="2.327394357815586" cell_index="1014" cell_dof_index="2" />
    <dof index="875" value="2.3760048969103327" cell_index="1080" cell_dof_index="2" />
    <dof index="876" value="1.8404753061937944" cell_index="1146" cell_dof_index="2" />
    <dof index="877" value="2.0232555086679924" cell_index="1212" cell_dof_index="2" />
    <dof index="878" value="2.2255894561086014" cell_index="1278" cell_dof_index="2" />
    <dof index="879" value="2.4306083065408943" cell_index="24" cell_dof_index="1" />
    <dof index="880" value="2.6210594101128026" cell_index="26" cell_dof_index="2" />
    <dof index="881" value="2.7807495594694402" cell_index="92" cell_dof_index="2" />
    <dof index="882" value="2.8959145429735331" cell_index="158" cell_dof_index="2" />
    <dof index="883" value="2.9563993364652483" cell_index="224" cell_dof_index="2" />
    <dof index="884" value="2.0816883290043893" cell_index="290" cell_dof_index="2" />
    <dof index="885" value="2.2884237375062693" cell_index="356" cell_dof_index="2" />
    <dof index="886" value="2.5172756082871706" cell_index="422" cell_dof_index="2" />
    <dof index="887" value="2.749164265926058" cell_index="488" cell_dof_index="2" />
    <dof index="888" value="2.9645759251955042" cell_index="554" cell_dof_index="2" />
    <dof index="889" value="3.1451950940884319" cell_index="620" cell_dof_index="2" />
    <dof index="890" value="3.2754536209285687" cell_index="686" cell_dof_index="2" />
    <dof index="891" value="3.3438655622734026" cell_index="752" cell_dof_index="2" />
    <dof index="892" value="2.1663569291634635" cell_index="818" cell_dof_index="2" />
    <dof index="893" value="2.381500895948196" cell_index="884" cell_dof_index="2" />
    <dof index="894" value="2.6196608688464167" cell_index="950" cell_dof_index="2" />
    <dof index="895" value="2.8609811439668915" cell_index="1016" cell_dof_index="2" />
    <dof index="896" value="3.0851542510449104" cell_index="1082" cell_dof_index="2" />
    <dof index="897" value="3.2731197512685104" cell_index="1148" cell_dof_index="2" />
    <dof index="898" value="3.4086762888495792" cell_index="1214" cell_dof_index="2" />
    <dof index="899" value="3.4798707520672245" cell_index="26" cell_dof_index="1" />
    <dof index="900" value="2.0816883290043906" cell_index="28" cell_dof_index="2" />
    <dof index="901" value="2.2884237375062697" cell_index="94" cell_dof_index="2" />
    <dof index="902" value="2.5172756082871723" cell_index="160" cell_dof_index="2" />
    <dof index="903" value="2.7491642659260593" cell_index="226" cell_dof_index="2" />
    <dof index="904" value="2.9645759251955068" cell_index="292" cell_dof_index="2" />
    <dof index="905" value="3.1451950940884346" cell_index="358" cell_dof_index="2" />
    <dof index="906" value="3.275453620928571" cell_index="424" cell_dof_index="2" />
    <dof index="907" value="3.3438655622734053" cell_index="490" cell_dof_index="2" />
    <dof index="908" value="1.8404753061937926" cell_index="556" cell_dof_index="2" />
    <dof index="909" value="2.0232555086679898" cell_index="622" cell_dof_index="2" />
    <dof index="910" value="2.2255894561085983" cell_index="688" cell_dof_index="2" />
    <dof index="911" value="2.4306083065408908" cell_index="754" cell_dof_index="2" />
    <dof index="912" value="2.6210594101127991" cell_index="820" cell_dof_index="2" />
    <dof index="913" value="2.7807495594694358" cell_index="886" cell_dof_index="2" />
    <dof index="914" value="2.8959145429735287" cell_index="952" cell_dof_index="2" />
    <dof index="915" value="2.9563993364652443" cell_index="1018" cell_dof_index="2" />
    <dof index="916" value="1.479156853480915" cell_index="1084" cell_dof_index="2" />
    <dof index="917" value="1.6260540100254701" cell_index="1150" cell_dof_index="2" />
    <dof index="918" value="1.7886661592031514" cell_index="28" cell_dof_index="1" />
    <dof index="919" value="1.9534361165555558" cell_index="30" cell_dof_index="2" />
    <dof index="920" value="2.1064982381462976" cell_index="96" cell_dof_index="2" />
    <dof index="921" value="2.2348383348916041" cell_index="162" cell_dof_index="2" />
    <dof index="922" value="2.3273943578155865" cell_index="228" cell_dof_index="2" />
    <dof index="923" value="2.3760048969103331" cell_index="294" cell_dof_index="2" />
    <dof index="924" value="1.0522932349224186" cell_index="360" cell_dof_index="2" />
    <dof index="925" value="1.1567979625295028" cell_index="426" cell_dof_index="2" />
    <dof index="926" value="1.272482559530274" cell_index="492" cell_dof_index="2" />
    <dof index="927" value="1.389702251973546" cell_index="558" cell_dof_index="2" />
    <dof index="928" value="1.498592823445916" cell_index="624" cell_dof_index="2" />
    <dof index="929" value="1.5898957946328851" cell_index="690" cell_dof_index="2" />
    <dof index="930" value="1.6557414664729118" cell_index="756" cell_dof_index="2" />
    <dof index="931" value="1.69032369574424" cell_index="822" cell_dof_index="2" />
    <dof index="932" value="0.62429081069388925" cell_index="888" cell_dof_index="2" />
    <dof index="933" value="0.68629001296375935" cell_index="954" cell_dof_index="2" />
    <dof index="934" value="0.7549218623852112" cell_index="1020" cell_dof_index="2" />
    <dof index="935" value="0.82446443321632878" cell_index="1086" cell_dof_index="2" />
    <dof index="936" value="0.88906561175228971" cell_index="30" cell_dof_index="1" />
    <dof index="937" value="0.94323264809675122" cell_index="32" cell_dof_index="2" />
    <dof index="938" value="0.98229670979503314" cell_index="98" cell_dof_index="2" />
    <dof index="939" value="1.0028132038965951" cell_index="164" cell_dof_index="2" />
    <dof index="940" value="0.25962856166074733" cell_index="230" cell_dof_index="2" />
    <dof index="941" value="0.28541264086503459" cell_index="296" cell_dof_index="2" />
    <dof index="942" value="0.3139550894229482" cell_index="362" cell_dof_index="2" />
    <dof index="943" value="0.34287628661149194" cell_index="428" cell_dof_index="2" />
    <dof index="944" value="0.36974246945060585" cell_index="494" cell_dof_index="2" />
    <dof index="945" value="0.39226932631705053" cell_index="560" cell_dof_index="2" />
    <dof index="946" value="0.40851519439266543" cell_index="626" cell_dof_index="2" />
    <dof index="947" value="0.41704754464140487" cell_index="692" cell_dof_index="2" />
    <dof index="948" value="0.03552770071821125" cell_index="758" cell_dof_index="2" />
    <dof index="949" value="0.039056006862207698" cell_index="824" cell_dof_index="2" />
    <dof index="950" value="0.042961769632081752" cell_index="890" cell_dof_index="2" />
    <dof index="951" value="0.046919360551795644" cell_index="956" cell_dof_index="2" />
    <dof index="952" value="0.050595742292091253" cell_index="1022" cell_dof_index="2" />
    <dof index="953" value="0.053678328521255057" cell_index="32" cell_dof_index="1" />
    <dof index="954" value="0.055901421139440043" cell_index="34" cell_dof_index="2" />
    <dof index="955" value="0.0570689921652206" cell_index="100" cell_dof_index="2" />
    <dof index="956" value="0.022280761666197517" cell_index="166" cell_dof_index="2" />
    <dof index="957" value="0.024493495580595444" cell_index="232" cell_dof_index="2" />
    <dof index="958" value="0.026942946787429752" cell_index="298" cell_dof_index="2" />
    <dof index="959" value="0.029424901382629695" cell_index="364" cell_dof_index="2" />
    <dof index="960" value="0.031730499090716083" cell_index="430" cell_dof_index="2" />
    <dof index="961" value="0.033663705228435412" cell_index="496" cell_dof_index="2" />
    <dof index="962" value="0.035057890491943688" cell_index="562" cell_dof_index="2" />
    <dof index="963" value="0.035790118337480553" cell_index="628" cell_dof_index="2" />
    <dof index="964" value="0.18569521805117792" cell_index="694" cell_dof_index="2" />
    <dof index="965" value="0.20413687246493764" cell_index="760" cell_dof_index="2" />
    <dof index="966" value="0.22455140688585373" cell_index="826" cell_dof_index="2" />
    <dof index="967" value="0.2452368352681337" cell_index="892" cell_dof_index="2" />
    <dof index="968" value="0.26445244717384925" cell_index="958" cell_dof_index="2" />
    <dof index="969" value="0.28056442488178784" cell_index="34" cell_dof_index="1" />
    <dof index="970" value="0.29218402480344041" cell_index="36" cell_dof_index="2" />
    <dof index="971" value="0.29828665322688414" cell_index="102" cell_dof_index="2" />
    <dof index="972" value="0.49663270973504992" cell_index="168" cell_dof_index="2" />
    <dof index="973" value="0.5459540056715918" cell_index="234" cell_dof_index="2" />
    <dof index="974" value="0.6005516719649957" cell_index="300" cell_dof_index="2" />
    <dof index="975" value="0.65587383080858375" cell_index="366" cell_dof_index="2" />
    <dof index="976" value="0.70726503791722628" cell_index="432" cell_dof_index="2" />
    <dof index="977" value="0.75035572830904329" cell_index="498" cell_dof_index="2" />
    <dof index="978" value="0.78143177569297251" cell_index="564" cell_dof_index="2" />
    <dof index="979" value="0.79775295467780627" cell_index="630" cell_dof_index="2" />
    <dof index="980" value="0.90007574886131514" cell_index="696" cell_dof_index="2" />
    <dof index="981" value="0.98946354290850314" cell_index="762" cell_dof_index="2" />
    <dof index="982" value="1.0884140035040857" cell_index="828" cell_dof_index="2" />
    <dof index="983" value="1.1886775032166437" cell_index="894" cell_dof_index="2" />
    <dof index="984" value="1.2818167151865436" cell_index="36" cell_dof_index="1" />
    <dof index="985" value="1.3599124278995807" cell_index="38" cell_dof_index="2" />
    <dof index="986" value="1.4162333187157778" cell_index="104" cell_dof_index="2" />
    <dof index="987" value="1.4458131210709448" cell_index="170" cell_dof_index="2" />
    <dof index="988" value="1.3352738724069746" cell_index="236" cell_dof_index="2" />
    <dof index="989" value="1.4678818068550519" cell_index="302" cell_dof_index="2" />
    <dof index="990" value="1.6146760792960879" cell_index="368" cell_dof_index="2" />
    <dof index="991" value="1.7634182620419667" cell_index="434" cell_dof_index="2" />
    <dof index="992" value="1.9015914729048498" cell_index="500" cell_dof_index="2" />
    <dof index="993" value="2.0174474604310588" cell_index="566" cell_dof_index="2" />
    <dof index="994" value="2.1010002214877743" cell_index="632" cell_dof_index="2" />
    <dof index="995" value="2.1448822361801874" cell_index="698" cell_dof_index="2" />
    <dof index="996" value="1.7365700489624567" cell_index="764" cell_dof_index="2" />
    <dof index="997" value="1.9090312735666644" cell_index="830" cell_dof_index="2" />
    <dof index="998" value="2.0999423234629826" cell_index="38" cell_dof_index="1" />
    <dof index="999" value="2.2933866983672688" cell_index="40" cell_dof_index="2" />
    <dof index="1000" value="2.4730857582469663" cell_index="106" cell_dof_index="2" />
    <dof index="1001" value="2.6237604940360466" cell_index="172" cell_dof_index="2" />
    <dof index="1002" value="2.7324237618177043" cell_index="238" cell_dof_index="2" />
    <dof index="1003" value="2.7894938460736092" cell_index="304" cell_dof_index="2" />
    <dof index="1004" value="2.0433628593047937" cell_index="370" cell_dof_index="2" />
    <dof index="1005" value="2.2462921112730667" cell_index="436" cell_dof_index="2" />
    <dof index="1006" value="2.4709306445830781" cell_index="502" cell_dof_index="2" />
    <dof index="1007" value="2.6985500551890684" cell_index="568" cell_dof_index="2" />
    <dof index="1008" value="2.9099958215314889" cell_index="634" cell_dof_index="2" />
    <dof index="1009" value="3.0872896537790973" cell_index="700" cell_dof_index="2" />
    <dof index="1010" value="3.2151500218007558" cell_index="766" cell_dof_index="2" />
    <dof index="1011" value="3.2823024471322793" cell_index="40" cell_dof_index="1" />
    <dof index="1012" value="2.2092982498268805" cell_index="42" cell_dof_index="2" />
    <dof index="1013" value="2.4287067798246889" cell_index="108" cell_dof_index="2" />
    <dof index="1014" value="2.6715875370164577" cell_index="174" cell_dof_index="2" />
    <dof index="1015" value="2.9176912396400509" cell_index="240" cell_dof_index="2" />
    <dof index="1016" value="3.1463078846898429" cell_index="306" cell_dof_index="2" />
    <dof index="1017" value="3.337999219151607" cell_index="372" cell_dof_index="2" />
    <dof index="1018" value="3.4762427455062839" cell_index="438" cell_dof_index="2" />
    <dof index="1019" value="3.548848418591211" cell_index="504" cell_dof_index="2" />
    <dof index="1020" value="2.2092982498268809" cell_index="570" cell_dof_index="2" />
    <dof index="1021" value="2.4287067798246884" cell_index="636" cell_dof_index="2" />
    <dof index="1022" value="2.6715875370164572" cell_index="702" cell_dof_index="2" />
    <dof index="1023" value="2.9176912396400505" cell_index="42" cell_dof_index="1" />
    <dof index="1024" value="3.1463078846898425" cell_index="44" cell_dof_index="2" />
    <dof index="1025" value="3.3379992191516061" cell_index="110" cell_dof_index="2" />
    <dof index="1026" value="3.4762427455062839" cell_index="176" cell_dof_index="2" />
    <dof index="1027" value="3.5488484185912106" cell_index="242" cell_dof_index="2" />
    <dof index="1028" value="2.0433628593047919" cell_index="308" cell_dof_index="2" />
    <dof index="1029" value="2.2462921112730658" cell_index="374" cell_dof_index="2" />
    <dof index="1030" value="2.4709306445830763" cell_index="440" cell_dof_index="2" />
    <dof index="1031" value="2.6985500551890671" cell_index="506" cell_dof_index="2" />
    <dof index="1032" value="2.9099958215314881" cell_index="572" cell_dof_index="2" />
    <dof index="1033" value="3.0872896537790955" cell_index="638" cell_dof_index="2" />
    <dof index="1034" value="3.215150021800754" cell_index="44" cell_dof_index="1" />
    <dof index="1035" value="3.2823024471322775" cell_index="46" cell_dof_index="2" />
    <dof index="1036" value="1.7365700489624567" cell_index="112" cell_dof_index="2" />
    <dof index="1037" value="1.9090312735666644" cell_index="178" cell_dof_index="2" />
    <dof index="1038" value="2.0999423234629826" cell_index="244" cell_dof_index="2" />
    <dof index="1039" value="2.2933866983672688" cell_index="310" cell_dof_index="2" />
    <dof index="1040" value="2.4730857582469663" cell_index="376" cell_dof_index="2" />
    <dof index="1041" value="2.6237604940360466" cell_index="442" cell_dof_index="2" />
    <dof index="1042" value="2.7324237618177043" cell_index="508" cell_dof_index="2" />
    <dof index="1043" value="2.7894938460736092" cell_index="574" cell_dof_index="2" />
    <dof index="1044" value="1.3352738724069781" cell_index="46" cell_dof_index="1" />
    <dof index="1045" value="1.4678818068550556" cell_index="48" cell_dof_index="2" />
    <dof index="1046" value="1.6146760792960921" cell_index="114" cell_dof_index="2" />
    <dof index="1047" value="1.7634182620419705" cell_index="180" cell_dof_index="2" />
    <dof index="1048" value="1.9015914729048544" cell_index="246" cell_dof_index="2" />
    <dof index="1049" value="2.0174474604310637" cell_index="312" cell_dof_index="2" />
    <dof index="1050" value="2.1010002214877797" cell_index="378" cell_dof_index="2" />
    <dof index="1051" value="2.1448822361801927" cell_index="444" cell_dof_index="2" />
    <dof index="1052" value="0.90007574886131902" cell_index="510" cell_dof_index="2" />
    <dof index="1053" value="0.98946354290850747" cell_index="48" cell_dof_index="1" />
    <dof index="1054" value="1.0884140035040906" cell_index="50" cell_dof_index="2" />
    <dof index="1055" value="1.1886775032166494" cell_index="116" cell_dof_index="2" />
    <dof index="1056" value="1.2818167151865494" cell_index="182" cell_dof_index="2" />
    <dof index="1057" value="1.3599124278995871" cell_index="248" cell_dof_index="2" />
    <dof index="1058" value="1.4162333187157843" cell_index="314" cell_dof_index="2" />
    <dof index="1059" value="1.4458131210709515" cell_index="380" cell_dof_index="2" />
    <dof index="1060" value="0.4966327097350508" cell_index="446" cell_dof_index="2" />
    <dof index="1061" value="0.54595400567159258" cell_index="50" cell_dof_index="1" />
    <dof index="1062" value="0.60055167196499648" cell_index="52" cell_dof_index="2" />
    <dof index="1063" value="0.65587383080858475" cell_index="118" cell_dof_index="2" />
    <dof index="1064" value="0.70726503791722739" cell_index="184" cell_dof_index="2" />
    <dof index="1065" value="0.75035572830904451" cell_index="250" cell_dof_index="2" />
    <dof index="1066" value="0.78143177569297373" cell_index="316" cell_dof_index="2" />
    <dof index="1067" value="0.79775295467780749" cell_index="382" cell_dof_index="2" />
    <dof index="1068" value="0.18569521805117864" cell_index="52" cell_dof_index="1" />
    <dof index="1069" value="0.20413687246493847" cell_index="54" cell_dof_index="2" />
    <dof index="1070" value="0.22455140688585468" cell_index="120" cell_dof_index="2" />
    <dof index="1071" value="0.24523683526813472" cell_index="186" cell_dof_index="2" />
    <dof index="1072" value="0.26445244717385036" cell_index="252" cell_dof_index="2" />
    <dof index="1073" value="0.28056442488178901" cell_index="318" cell_dof_index="2" />
    <dof index="1074" value="0.29218402480344158" cell_index="54" cell_dof_index="1" />
    <dof index="1075" value="0.29828665322688536" cell_index="56" cell_dof_index="2" />
    <dof index="1076" value="0.022280761666197711" cell_index="122" cell_dof_index="2" />
    <dof index="1077" value="0.024493495580595648" cell_index="188" cell_dof_index="2" />
    <dof index="1078" value="0.026942946787429978" cell_index="254" cell_dof_index="2" />
    <dof index="1079" value="0.029424901382629948" cell_index="56" cell_dof_index="1" />
    <dof index="1080" value="0.031730499090716353" cell_index="58" cell_dof_index="2" />
    <dof index="1081" value="0.033663705228435696" cell_index="124" cell_dof_index="2" />
    <dof index="1082" value="0.035057890491943987" cell_index="190" cell_dof_index="2" />
    <dof index="1083" value="0.035790118337480858" cell_index="58" cell_dof_index="1" />
    <dof index="1084" value="0.008205524905674574" cell_index="60" cell_dof_index="2" />
    <dof index="1085" value="0.0090204271750062674" cell_index="126" cell_dof_index="2" />
    <dof index="1086" value="0.0099225073275625523" cell_index="60" cell_dof_index="1" />
    <dof index="1087" value="0.010836557778385502" cell_index="62" cell_dof_index="2" />
    <dof index="1088" value="0.01168565978394534" cell_index="62" cell_dof_index="1" />
  </function_data>
</dolfin>
