<?xml version="1.0"?>
<dolfin xmlns:dolfin="http://fenicsproject.org">
  <function_data size="1089">
    <dof index="0" value="0" cell_index="1985" cell_dof_index="1" />
    <dof index="1" value="0" cell_index="1921" cell_dof_index="1" />
    <dof index="2" value="0" cell_index="1984" cell_dof_index="2" />
    <dof index="3" value="0" cell_index="1857" cell_dof_index="1" />
    <dof index="4" value="0" cell_index="1920" cell_dof_index="2" />
    <dof index="5" value="0" cell_index="1986" cell_dof_index="2" />
    <dof index="6" value="0" cell_index="1793" cell_dof_index="1" />
    <dof index="7" value="0" cell_index="1856" cell_dof_index="2" />
    <dof index="8" value="0" cell_index="1922" cell_dof_index="2" />
    <dof index="9" value="0" cell_index="1988" cell_dof_index="2" />
    <dof index="10" value="0" cell_index="1729" cell_dof_index="1" />
    <dof index="11" value="0" cell_index="1792" cell_dof_index="2" />
    <dof index="12" value="-0.00014720368467816515" cell_index="1858" cell_dof_index="2" />
    <dof index="13" value="-0.00013808073091092229" cell_index="1924" cell_dof_index="2" />
    <dof index="14" value="-0.00012946682112851448" cell_index="1990" cell_dof_index="2" />
    <dof index="15" value="-0.00012107019879366509" cell_index="1665" cell_dof_index="1" />
    <dof index="16" value="-0.00011257892016900129" cell_index="1728" cell_dof_index="2" />
    <dof index="17" value="-0.00010368670820383566" cell_index="1794" cell_dof_index="2" />
    <dof index="18" value="-9.4118603004755472e-05" cell_index="1860" cell_dof_index="2" />
    <dof index="19" value="-8.365425496849442e-05" cell_index="1926" cell_dof_index="2" />
    <dof index="20" value="-7.2146881760061407e-05" cell_index="1992" cell_dof_index="2" />
    <dof index="21" value="-5.9536253264254235e-05" cell_index="1601" cell_dof_index="1" />
    <dof index="22" value="-4.585455242027362e-05" cell_index="1664" cell_dof_index="2" />
    <dof index="23" value="-3.1224545364482582e-05" cell_index="1730" cell_dof_index="2" />
    <dof index="24" value="-1.5850133507315553e-05" cell_index="1796" cell_dof_index="2" />
    <dof index="25" value="0" cell_index="1862" cell_dof_index="2" />
    <dof index="26" value="-0.00014720368467816529" cell_index="1928" cell_dof_index="2" />
    <dof index="27" value="-0.00013808073091092242" cell_index="1994" cell_dof_index="2" />
    <dof index="28" value="-0.00012946682112851459" cell_index="1537" cell_dof_index="1" />
    <dof index="29" value="-0.00012107019879366517" cell_index="1600" cell_dof_index="2" />
    <dof index="30" value="-0.00011257892016900136" cell_index="1666" cell_dof_index="2" />
    <dof index="31" value="-0.00010368670820383574" cell_index="1732" cell_dof_index="2" />
    <dof index="32" value="-9.411860300475554e-05" cell_index="1798" cell_dof_index="2" />
    <dof index="33" value="-8.3654254968494487e-05" cell_index="1864" cell_dof_index="2" />
    <dof index="34" value="-7.2146881760061461e-05" cell_index="1930" cell_dof_index="2" />
    <dof index="35" value="-5.9536253264254289e-05" cell_index="1996" cell_dof_index="2" />
    <dof index="36" value="-4.5854552420273661e-05" cell_index="1473" cell_dof_index="1" />
    <dof index="37" value="-3.1224545364482609e-05" cell_index="1536" cell_dof_index="2" />
    <dof index="38" value="-1.585013350731557e-05" cell_index="1602" cell_dof_index="2" />
    <dof index="39" value="0" cell_index="1668" cell_dof_index="2" />
    <dof index="40" value="-0.00043863084084741954" cell_index="1734" cell_dof_index="2" />
    <dof index="41" value="-0.00041144667836747433" cell_index="1800" cell_dof_index="2" />
    <dof index="42" value="-0.00038577934198861944" cell_index="1866" cell_dof_index="2" />
    <dof index="43" value="-0.00036075946885796048" cell_index="1932" cell_dof_index="2" />
    <dof index="44" value="-0.00033545754322240965" cell_index="1998" cell_dof_index="2" />
    <dof index="45" value="-0.00030896093466399203" cell_index="1409" cell_dof_index="1" />
    <dof index="46" value="-0.00028045033020483858" cell_index="1472" cell_dof_index="2" />
    <dof index="47" value="-0.00024926914212452378" cell_index="1538" cell_dof_index="2" />
    <dof index="48" value="-0.0002149799951008234" cell_index="1604" cell_dof_index="2" />
    <dof index="49" value="-0.00017740341817733279" cell_index="1670" cell_dof_index="2" />
    <dof index="50" value="-0.00013663530861174233" cell_index="1736" cell_dof_index="2" />
    <dof index="51" value="-9.3041479350502562e-05" cell_index="1802" cell_dof_index="2" />
    <dof index="52" value="-4.7229506537542072e-05" cell_index="1868" cell_dof_index="2" />
    <dof index="53" value="0" cell_index="1934" cell_dof_index="2" />
    <dof index="54" value="-0.0014660764204074976" cell_index="2000" cell_dof_index="2" />
    <dof index="55" value="-0.001375216280378636" cell_index="1345" cell_dof_index="1" />
    <dof index="56" value="-0.0012894259684912951" cell_index="1408" cell_dof_index="2" />
    <dof index="57" value="-0.0012057997328905796" cell_index="1474" cell_dof_index="2" />
    <dof index="58" value="-0.001121230767120823" cell_index="1540" cell_dof_index="2" />
    <dof index="59" value="-0.0010326687021433253" cell_index="1606" cell_dof_index="2" />
    <dof index="60" value="-0.00093737507242869775" cell_index="1672" cell_dof_index="2" />
    <dof index="61" value="-0.00083315530412302421" cell_index="1738" cell_dof_index="2" />
    <dof index="62" value="-0.00071854751724189151" cell_index="1804" cell_dof_index="2" />
    <dof index="63" value="-0.00059295184941168171" cell_index="1870" cell_dof_index="2" />
    <dof index="64" value="-0.00045668882690457846" cell_index="1936" cell_dof_index="2" />
    <dof index="65" value="-0.00031098114015893496" cell_index="2002" cell_dof_index="2" />
    <dof index="66" value="-0.00015785954710434614" cell_index="1281" cell_dof_index="1" />
    <dof index="67" value="0" cell_index="1344" cell_dof_index="2" />
    <dof index="68" value="-0.00043863084084741879" cell_index="1410" cell_dof_index="2" />
    <dof index="69" value="-0.00041144667836747362" cell_index="1476" cell_dof_index="2" />
    <dof index="70" value="-0.00038577934198861873" cell_index="1542" cell_dof_index="2" />
    <dof index="71" value="-0.00036075946885795977" cell_index="1608" cell_dof_index="2" />
    <dof index="72" value="-0.00033545754322240906" cell_index="1674" cell_dof_index="2" />
    <dof index="73" value="-0.00030896093466399144" cell_index="1740" cell_dof_index="2" />
    <dof index="74" value="-0.0002804503302048381" cell_index="1806" cell_dof_index="2" />
    <dof index="75" value="-0.00024926914212452335" cell_index="1872" cell_dof_index="2" />
    <dof index="76" value="-0.00021497999510082297" cell_index="1938" cell_dof_index="2" />
    <dof index="77" value="-0.00017740341817733244" cell_index="2004" cell_dof_index="2" />
    <dof index="78" value="-0.00013663530861174206" cell_index="1217" cell_dof_index="1" />
    <dof index="79" value="-9.3041479350502385e-05" cell_index="1280" cell_dof_index="2" />
    <dof index="80" value="-4.7229506537541978e-05" cell_index="1346" cell_dof_index="2" />
    <dof index="81" value="0" cell_index="1412" cell_dof_index="2" />
    <dof index="82" value="-0.00072040313861515212" cell_index="1478" cell_dof_index="2" />
    <dof index="83" value="-0.00067575612762672712" cell_index="1544" cell_dof_index="2" />
    <dof index="84" value="-0.00063360033746045824" cell_index="1610" cell_dof_index="2" />
    <dof index="85" value="-0.00059250793480072471" cell_index="1676" cell_dof_index="2" />
    <dof index="86" value="-0.00055095229177835328" cell_index="1742" cell_dof_index="2" />
    <dof index="87" value="-0.00050743451283863416" cell_index="1808" cell_dof_index="2" />
    <dof index="88" value="-0.00046060896610665241" cell_index="1874" cell_dof_index="2" />
    <dof index="89" value="-0.00040939727812910307" cell_index="1940" cell_dof_index="2" />
    <dof index="90" value="-0.00035308110781926631" cell_index="2006" cell_dof_index="2" />
    <dof index="91" value="-0.00029136569377816179" cell_index="1153" cell_dof_index="1" />
    <dof index="92" value="-0.00022440853675355089" cell_index="1216" cell_dof_index="2" />
    <dof index="93" value="-0.00015281044446396961" cell_index="1282" cell_dof_index="2" />
    <dof index="94" value="-7.7569294213686416e-05" cell_index="1348" cell_dof_index="2" />
    <dof index="95" value="0" cell_index="1414" cell_dof_index="2" />
    <dof index="96" value="-0.0031927306665254116" cell_index="1480" cell_dof_index="2" />
    <dof index="97" value="-0.0029948610661437967" cell_index="1546" cell_dof_index="2" />
    <dof index="98" value="-0.0028080322243175565" cell_index="1612" cell_dof_index="2" />
    <dof index="99" value="-0.0026259161741499456" cell_index="1678" cell_dof_index="2" />
    <dof index="100" value="-0.0024417471044541166" cell_index="1744" cell_dof_index="2" />
    <dof index="101" value="-0.0022488821099636651" cell_index="1810" cell_dof_index="2" />
    <dof index="102" value="-0.0020413575296079952" cell_index="1876" cell_dof_index="2" />
    <dof index="103" value="-0.0018143941560103145" cell_index="1942" cell_dof_index="2" />
    <dof index="104" value="-0.001564808397243186" cell_index="2008" cell_dof_index="2" />
    <dof index="105" value="-0.0012912939100837833" cell_index="1089" cell_dof_index="1" />
    <dof index="106" value="-0.00099454871684825745" cell_index="1152" cell_dof_index="2" />
    <dof index="107" value="-0.0006772355172457498" cell_index="1218" cell_dof_index="2" />
    <dof index="108" value="-0.00034377677045223224" cell_index="1284" cell_dof_index="2" />
    <dof index="109" value="0" cell_index="1350" cell_dof_index="2" />
    <dof index="110" value="-0.0031927306665254169" cell_index="1416" cell_dof_index="2" />
    <dof index="111" value="-0.0029948610661438015" cell_index="1482" cell_dof_index="2" />
    <dof index="112" value="-0.0028080322243175609" cell_index="1548" cell_dof_index="2" />
    <dof index="113" value="-0.0026259161741499495" cell_index="1614" cell_dof_index="2" />
    <dof index="114" value="-0.00244174710445412" cell_index="1680" cell_dof_index="2" />
    <dof index="115" value="-0.0022488821099636686" cell_index="1746" cell_dof_index="2" />
    <dof index="116" value="-0.0020413575296079982" cell_index="1812" cell_dof_index="2" />
    <dof index="117" value="-0.0018143941560103171" cell_index="1878" cell_dof_index="2" />
    <dof index="118" value="-0.001564808397243188" cell_index="1944" cell_dof_index="2" />
    <dof index="119" value="-0.001291293910083785" cell_index="2010" cell_dof_index="2" />
    <dof index="120" value="-0.00099454871684825875" cell_index="1025" cell_dof_index="1" />
    <dof index="121" value="-0.00067723551724575078" cell_index="1088" cell_dof_index="2" />
    <dof index="122" value="-0.00034377677045223278" cell_index="1154" cell_dof_index="2" />
    <dof index="123" value="0" cell_index="1220" cell_dof_index="2" />
    <dof index="124" value="-0.00072040313861515093" cell_index="1286" cell_dof_index="2" />
    <dof index="125" value="-0.00067575612762672615" cell_index="1352" cell_dof_index="2" />
    <dof index="126" value="-0.00063360033746045726" cell_index="1418" cell_dof_index="2" />
    <dof index="127" value="-0.00059250793480072385" cell_index="1484" cell_dof_index="2" />
    <dof index="128" value="-0.00055095229177835252" cell_index="1550" cell_dof_index="2" />
    <dof index="129" value="-0.0005074345128386334" cell_index="1616" cell_dof_index="2" />
    <dof index="130" value="-0.0004606089661066517" cell_index="1682" cell_dof_index="2" />
    <dof index="131" value="-0.00040939727812910241" cell_index="1748" cell_dof_index="2" />
    <dof index="132" value="-0.00035308110781926577" cell_index="1814" cell_dof_index="2" />
    <dof index="133" value="-0.0002913656937781613" cell_index="1880" cell_dof_index="2" />
    <dof index="134" value="-0.00022440853675355051" cell_index="1946" cell_dof_index="2" />
    <dof index="135" value="-0.00015281044446396937" cell_index="2012" cell_dof_index="2" />
    <dof index="136" value="-7.7569294213686307e-05" cell_index="961" cell_dof_index="1" />
    <dof index="137" value="0" cell_index="1024" cell_dof_index="2" />
    <dof index="138" value="-0.00098548734252234724" cell_index="1090" cell_dof_index="2" />
    <dof index="139" value="-0.00092441172825568913" cell_index="1156" cell_dof_index="2" />
    <dof index="140" value="-0.00086674402055698702" cell_index="1222" cell_dof_index="2" />
    <dof index="141" value="-0.00081053099131776763" cell_index="1288" cell_dof_index="2" />
    <dof index="142" value="-0.00075368426479232762" cell_index="1354" cell_dof_index="2" />
    <dof index="143" value="-0.00069415340211144037" cell_index="1420" cell_dof_index="2" />
    <dof index="144" value="-0.00063009762398176115" cell_index="1486" cell_dof_index="2" />
    <dof index="145" value="-0.00056004175167102214" cell_index="1552" cell_dof_index="2" />
    <dof index="146" value="-0.00048300311865456455" cell_index="1618" cell_dof_index="2" />
    <dof index="147" value="-0.00039857850122029055" cell_index="1684" cell_dof_index="2" />
    <dof index="148" value="-0.00030698335511101539" cell_index="1750" cell_dof_index="2" />
    <dof index="149" value="-0.00020903956514396109" cell_index="1816" cell_dof_index="2" />
    <dof index="150" value="-0.00010611219401810096" cell_index="1882" cell_dof_index="2" />
    <dof index="151" value="0" cell_index="1948" cell_dof_index="2" />
    <dof index="152" value="-0.0048466619040779743" cell_index="2014" cell_dof_index="2" />
    <dof index="153" value="-0.004546289854471806" cell_index="897" cell_dof_index="1" />
    <dof index="154" value="-0.0042626780109310909" cell_index="960" cell_dof_index="2" />
    <dof index="155" value="-0.0039862203279442919" cell_index="1026" cell_dof_index="2" />
    <dof index="156" value="-0.0037066460990990936" cell_index="1092" cell_dof_index="2" />
    <dof index="157" value="-0.0034138711928949472" cell_index="1158" cell_dof_index="2" />
    <dof index="158" value="-0.0030988425911043093" cell_index="1224" cell_dof_index="2" />
    <dof index="159" value="-0.002754305312100433" cell_index="1290" cell_dof_index="2" />
    <dof index="160" value="-0.0023754265668621179" cell_index="1356" cell_dof_index="2" />
    <dof index="161" value="-0.0019602232867897778" cell_index="1422" cell_dof_index="2" />
    <dof index="162" value="-0.0015097550909121495" cell_index="1488" cell_dof_index="2" />
    <dof index="163" value="-0.0010280640380779804" cell_index="1554" cell_dof_index="2" />
    <dof index="164" value="-0.00052186355533429744" cell_index="1620" cell_dof_index="2" />
    <dof index="165" value="0" cell_index="1686" cell_dof_index="2" />
    <dof index="166" value="-0.0065967848884104134" cell_index="1752" cell_dof_index="2" />
    <dof index="167" value="-0.0061879489025382381" cell_index="1818" cell_dof_index="2" />
    <dof index="168" value="-0.005801925210217258" cell_index="1884" cell_dof_index="2" />
    <dof index="169" value="-0.0054256390360408026" cell_index="1950" cell_dof_index="2" />
    <dof index="170" value="-0.0050451109355592718" cell_index="2016" cell_dof_index="2" />
    <dof index="171" value="-0.0046466154111802693" cell_index="833" cell_dof_index="1" />
    <dof index="172" value="-0.0042178304121769407" cell_index="896" cell_dof_index="2" />
    <dof index="173" value="-0.0037488811929804362" cell_index="962" cell_dof_index="2" />
    <dof index="174" value="-0.0032331898510642525" cell_index="1028" cell_dof_index="2" />
    <dof index="175" value="-0.0026680572344699206" cell_index="1094" cell_dof_index="2" />
    <dof index="176" value="-0.0020549255892081159" cell_index="1160" cell_dof_index="2" />
    <dof index="177" value="-0.0013992965560491676" cell_index="1226" cell_dof_index="2" />
    <dof index="178" value="-0.00071030777136420599" cell_index="1292" cell_dof_index="2" />
    <dof index="179" value="0" cell_index="1358" cell_dof_index="2" />
    <dof index="180" value="-0.0048466619040779544" cell_index="1424" cell_dof_index="2" />
    <dof index="181" value="-0.0045462898544717878" cell_index="1490" cell_dof_index="2" />
    <dof index="182" value="-0.0042626780109310744" cell_index="1556" cell_dof_index="2" />
    <dof index="183" value="-0.0039862203279442763" cell_index="1622" cell_dof_index="2" />
    <dof index="184" value="-0.0037066460990990797" cell_index="1688" cell_dof_index="2" />
    <dof index="185" value="-0.0034138711928949346" cell_index="1754" cell_dof_index="2" />
    <dof index="186" value="-0.0030988425911042971" cell_index="1820" cell_dof_index="2" />
    <dof index="187" value="-0.0027543053121004231" cell_index="1886" cell_dof_index="2" />
    <dof index="188" value="-0.0023754265668621097" cell_index="1952" cell_dof_index="2" />
    <dof index="189" value="-0.0019602232867897704" cell_index="2018" cell_dof_index="2" />
    <dof index="190" value="-0.0015097550909121439" cell_index="769" cell_dof_index="1" />
    <dof index="191" value="-0.0010280640380779767" cell_index="832" cell_dof_index="2" />
    <dof index="192" value="-0.00052186355533429549" cell_index="898" cell_dof_index="2" />
    <dof index="193" value="0" cell_index="964" cell_dof_index="2" />
    <dof index="194" value="-0.00098548734252233553" cell_index="1030" cell_dof_index="2" />
    <dof index="195" value="-0.00092441172825567797" cell_index="1096" cell_dof_index="2" />
    <dof index="196" value="-0.00086674402055697661" cell_index="1162" cell_dof_index="2" />
    <dof index="197" value="-0.00081053099131775787" cell_index="1228" cell_dof_index="2" />
    <dof index="198" value="-0.00075368426479231862" cell_index="1294" cell_dof_index="2" />
    <dof index="199" value="-0.00069415340211143213" cell_index="1360" cell_dof_index="2" />
    <dof index="200" value="-0.00063009762398175367" cell_index="1426" cell_dof_index="2" />
    <dof index="201" value="-0.00056004175167101542" cell_index="1492" cell_dof_index="2" />
    <dof index="202" value="-0.0004830031186545588" cell_index="1558" cell_dof_index="2" />
    <dof index="203" value="-0.00039857850122028589" cell_index="1624" cell_dof_index="2" />
    <dof index="204" value="-0.00030698335511101182" cell_index="1690" cell_dof_index="2" />
    <dof index="205" value="-0.0002090395651439586" cell_index="1756" cell_dof_index="2" />
    <dof index="206" value="-0.0001061121940180997" cell_index="1822" cell_dof_index="2" />
    <dof index="207" value="0" cell_index="1888" cell_dof_index="2" />
    <dof index="208" value="-0.0012275910508917124" cell_index="1954" cell_dof_index="2" />
    <dof index="209" value="-0.0011515110504022453" cell_index="2020" cell_dof_index="2" />
    <dof index="210" value="-0.0010796761735430733" cell_index="705" cell_dof_index="1" />
    <dof index="211" value="-0.0010096533445730349" cell_index="768" cell_dof_index="2" />
    <dof index="212" value="-0.00093884113852632338" cell_index="834" cell_dof_index="2" />
    <dof index="213" value="-0.00086468538722882422" cell_index="900" cell_dof_index="2" />
    <dof index="214" value="-0.00078489308894457083" cell_index="966" cell_dof_index="2" />
    <dof index="215" value="-0.00069762665922974611" cell_index="1032" cell_dof_index="2" />
    <dof index="216" value="-0.00060166202083887857" cell_index="1098" cell_dof_index="2" />
    <dof index="217" value="-0.00049649689048620628" cell_index="1164" cell_dof_index="2" />
    <dof index="218" value="-0.0003823996547154533" cell_index="1230" cell_dof_index="2" />
    <dof index="219" value="-0.00026039410998036509" cell_index="1296" cell_dof_index="2" />
    <dof index="220" value="-0.00013218067259362286" cell_index="1362" cell_dof_index="2" />
    <dof index="221" value="0" cell_index="1428" cell_dof_index="2" />
    <dof index="222" value="-0.0063875458789150749" cell_index="1494" cell_dof_index="2" />
    <dof index="223" value="-0.0059916774883453077" cell_index="1560" cell_dof_index="2" />
    <dof index="224" value="-0.0056178978234390879" cell_index="1626" cell_dof_index="2" />
    <dof index="225" value="-0.0052535468188495329" cell_index="1692" cell_dof_index="2" />
    <dof index="226" value="-0.0048850884347793671" cell_index="1758" cell_dof_index="2" />
    <dof index="227" value="-0.0044992325235179422" cell_index="1824" cell_dof_index="2" />
    <dof index="228" value="-0.0040840478692273138" cell_index="1890" cell_dof_index="2" />
    <dof index="229" value="-0.0036299729367914213" cell_index="1956" cell_dof_index="2" />
    <dof index="230" value="-0.0031306384637762434" cell_index="2022" cell_dof_index="2" />
    <dof index="231" value="-0.002583430910819722" cell_index="641" cell_dof_index="1" />
    <dof index="232" value="-0.0019897467782955562" cell_index="704" cell_dof_index="2" />
    <dof index="233" value="-0.0013549132041086867" cell_index="770" cell_dof_index="2" />
    <dof index="234" value="-0.00068777799405129124" cell_index="836" cell_dof_index="2" />
    <dof index="235" value="0" cell_index="902" cell_dof_index="2" />
    <dof index="236" value="-0.0098479533648201702" cell_index="968" cell_dof_index="2" />
    <dof index="237" value="-0.009237626093151376" cell_index="1034" cell_dof_index="2" />
    <dof index="238" value="-0.008661353956951898" cell_index="1100" cell_dof_index="2" />
    <dof index="239" value="-0.008099618390641921" cell_index="1166" cell_dof_index="2" />
    <dof index="240" value="-0.007531550301271687" cell_index="1232" cell_dof_index="2" />
    <dof index="241" value="-0.0069366596982646809" cell_index="1298" cell_dof_index="2" />
    <dof index="242" value="-0.0062965517145804123" cell_index="1364" cell_dof_index="2" />
    <dof index="243" value="-0.0055964849215537835" cell_index="1430" cell_dof_index="2" />
    <dof index="244" value="-0.0048266395541909186" cell_index="1496" cell_dof_index="2" />
    <dof index="245" value="-0.0039829862067947697" cell_index="1562" cell_dof_index="2" />
    <dof index="246" value="-0.0030676779238701952" cell_index="1628" cell_dof_index="2" />
    <dof index="247" value="-0.0020889277823406801" cell_index="1694" cell_dof_index="2" />
    <dof index="248" value="-0.0010603768237696181" cell_index="1760" cell_dof_index="2" />
    <dof index="249" value="0" cell_index="1826" cell_dof_index="2" />
    <dof index="250" value="-0.0098479533648201355" cell_index="1892" cell_dof_index="2" />
    <dof index="251" value="-0.0092376260931513431" cell_index="1958" cell_dof_index="2" />
    <dof index="252" value="-0.0086613539569518685" cell_index="2024" cell_dof_index="2" />
    <dof index="253" value="-0.0080996183906418932" cell_index="577" cell_dof_index="1" />
    <dof index="254" value="-0.0075315503012716627" cell_index="640" cell_dof_index="2" />
    <dof index="255" value="-0.0069366596982646583" cell_index="706" cell_dof_index="2" />
    <dof index="256" value="-0.0062965517145803914" cell_index="772" cell_dof_index="2" />
    <dof index="257" value="-0.0055964849215537644" cell_index="838" cell_dof_index="2" />
    <dof index="258" value="-0.0048266395541909021" cell_index="904" cell_dof_index="2" />
    <dof index="259" value="-0.0039829862067947558" cell_index="970" cell_dof_index="2" />
    <dof index="260" value="-0.0030676779238701843" cell_index="1036" cell_dof_index="2" />
    <dof index="261" value="-0.0020889277823406727" cell_index="1102" cell_dof_index="2" />
    <dof index="262" value="-0.0010603768237696142" cell_index="1168" cell_dof_index="2" />
    <dof index="263" value="0" cell_index="1234" cell_dof_index="2" />
    <dof index="264" value="-0.0063875458789150342" cell_index="1300" cell_dof_index="2" />
    <dof index="265" value="-0.0059916774883452687" cell_index="1366" cell_dof_index="2" />
    <dof index="266" value="-0.0056178978234390524" cell_index="1432" cell_dof_index="2" />
    <dof index="267" value="-0.0052535468188494991" cell_index="1498" cell_dof_index="2" />
    <dof index="268" value="-0.0048850884347793359" cell_index="1564" cell_dof_index="2" />
    <dof index="269" value="-0.0044992325235179128" cell_index="1630" cell_dof_index="2" />
    <dof index="270" value="-0.0040840478692272869" cell_index="1696" cell_dof_index="2" />
    <dof index="271" value="-0.003629972936791397" cell_index="1762" cell_dof_index="2" />
    <dof index="272" value="-0.0031306384637762225" cell_index="1828" cell_dof_index="2" />
    <dof index="273" value="-0.0025834309108197051" cell_index="1894" cell_dof_index="2" />
    <dof index="274" value="-0.0019897467782955436" cell_index="1960" cell_dof_index="2" />
    <dof index="275" value="-0.0013549132041086778" cell_index="2026" cell_dof_index="2" />
    <dof index="276" value="-0.0006877779940512868" cell_index="513" cell_dof_index="1" />
    <dof index="277" value="0" cell_index="576" cell_dof_index="2" />
    <dof index="278" value="-0.0012275910508916887" cell_index="642" cell_dof_index="2" />
    <dof index="279" value="-0.0011515110504022232" cell_index="708" cell_dof_index="2" />
    <dof index="280" value="-0.0010796761735430522" cell_index="774" cell_dof_index="2" />
    <dof index="281" value="-0.0010096533445730152" cell_index="840" cell_dof_index="2" />
    <dof index="282" value="-0.00093884113852630527" cell_index="906" cell_dof_index="2" />
    <dof index="283" value="-0.00086468538722880742" cell_index="972" cell_dof_index="2" />
    <dof index="284" value="-0.00078489308894455565" cell_index="1038" cell_dof_index="2" />
    <dof index="285" value="-0.00069762665922973256" cell_index="1104" cell_dof_index="2" />
    <dof index="286" value="-0.00060166202083886686" cell_index="1170" cell_dof_index="2" />
    <dof index="287" value="-0.00049649689048619663" cell_index="1236" cell_dof_index="2" />
    <dof index="288" value="-0.00038239965471544582" cell_index="1302" cell_dof_index="2" />
    <dof index="289" value="-0.00026039410998036005" cell_index="1368" cell_dof_index="2" />
    <dof index="290" value="-0.00013218067259362031" cell_index="1434" cell_dof_index="2" />
    <dof index="291" value="0" cell_index="1500" cell_dof_index="2" />
    <dof index="292" value="-0.0014412541157093029" cell_index="1566" cell_dof_index="2" />
    <dof index="293" value="-0.0013519323389262602" cell_index="1632" cell_dof_index="2" />
    <dof index="294" value="-0.0012675945524544968" cell_index="1698" cell_dof_index="2" />
    <dof index="295" value="-0.0011853842020504528" cell_index="1764" cell_dof_index="2" />
    <dof index="296" value="-0.0011022470829478463" cell_index="1830" cell_dof_index="2" />
    <dof index="297" value="-0.0010151844722491113" cell_index="1896" cell_dof_index="2" />
    <dof index="298" value="-0.00092150426969260957" cell_index="1962" cell_dof_index="2" />
    <dof index="299" value="-0.0008190490580010718" cell_index="2028" cell_dof_index="2" />
    <dof index="300" value="-0.00070638170844445356" cell_index="449" cell_dof_index="1" />
    <dof index="301" value="-0.00058291251498642437" cell_index="512" cell_dof_index="2" />
    <dof index="302" value="-0.0004489565770328182" cell_index="578" cell_dof_index="2" />
    <dof index="303" value="-0.00030571588351271494" cell_index="644" cell_dof_index="2" />
    <dof index="304" value="-0.00015518680936489463" cell_index="710" cell_dof_index="2" />
    <dof index="305" value="0" cell_index="776" cell_dof_index="2" />
    <dof index="306" value="-0.0077794359835341165" cell_index="842" cell_dof_index="2" />
    <dof index="307" value="-0.0072973051525826119" cell_index="908" cell_dof_index="2" />
    <dof index="308" value="-0.0068420763322804001" cell_index="974" cell_dof_index="2" />
    <dof index="309" value="-0.0063983307421160871" cell_index="1040" cell_dof_index="2" />
    <dof index="310" value="-0.0059495827462806138" cell_index="1106" cell_dof_index="2" />
    <dof index="311" value="-0.00547964618262554" cell_index="1172" cell_dof_index="2" />
    <dof index="312" value="-0.0049739899414607738" cell_index="1238" cell_dof_index="2" />
    <dof index="313" value="-0.0044209689635178974" cell_index="1304" cell_dof_index="2" />
    <dof index="314" value="-0.0038128260803464487" cell_index="1370" cell_dof_index="2" />
    <dof index="315" value="-0.0031463782444125241" cell_index="1436" cell_dof_index="2" />
    <dof index="316" value="-0.0024233262631097783" cell_index="1502" cell_dof_index="2" />
    <dof index="317" value="-0.0016501580942693628" cell_index="1568" cell_dof_index="2" />
    <dof index="318" value="-0.00083764954131559455" cell_index="1634" cell_dof_index="2" />
    <dof index="319" value="0" cell_index="1700" cell_dof_index="2" />
    <dof index="320" value="-0.012867758351863169" cell_index="1766" cell_dof_index="2" />
    <dof index="321" value="-0.012070278555153205" cell_index="1832" cell_dof_index="2" />
    <dof index="322" value="-0.011317296659441084" cell_index="1898" cell_dof_index="2" />
    <dof index="323" value="-0.010583308869577521" cell_index="1964" cell_dof_index="2" />
    <dof index="324" value="-0.0098410467334129215" cell_index="2030" cell_dof_index="2" />
    <dof index="325" value="-0.0090637371502223733" cell_index="385" cell_dof_index="1" />
    <dof index="326" value="-0.0082273445975756792" cell_index="448" cell_dof_index="2" />
    <dof index="327" value="-0.0073126072923594731" cell_index="514" cell_dof_index="2" />
    <dof index="328" value="-0.0063066943083566734" cell_index="580" cell_dof_index="2" />
    <dof index="329" value="-0.0052043406512186589" cell_index="646" cell_dof_index="2" />
    <dof index="330" value="-0.004008359581262882" cell_index="712" cell_dof_index="2" />
    <dof index="331" value="-0.002729482657145395" cell_index="778" cell_dof_index="2" />
    <dof index="332" value="-0.0013855338489849561" cell_index="844" cell_dof_index="2" />
    <dof index="333" value="0" cell_index="910" cell_dof_index="2" />
    <dof index="334" value="-0.014617441025536033" cell_index="976" cell_dof_index="2" />
    <dof index="335" value="-0.013711524580829368" cell_index="1042" cell_dof_index="2" />
    <dof index="336" value="-0.01285615660197122" cell_index="1108" cell_dof_index="2" />
    <dof index="337" value="-0.01202236543660941" cell_index="1174" cell_dof_index="2" />
    <dof index="338" value="-0.011179174827632563" cell_index="1240" cell_dof_index="2" />
    <dof index="339" value="-0.010296171224349428" cell_index="1306" cell_dof_index="2" />
    <dof index="340" value="-0.0093460508942811871" cell_index="1372" cell_dof_index="2" />
    <dof index="341" value="-0.0083069329494746165" cell_index="1438" cell_dof_index="2" />
    <dof index="342" value="-0.0071642417892576636" cell_index="1504" cell_dof_index="2" />
    <dof index="343" value="-0.0059119965160811016" cell_index="1570" cell_dof_index="2" />
    <dof index="344" value="-0.0045533929209798027" cell_index="1636" cell_dof_index="2" />
    <dof index="345" value="-0.0031006217773175094" cell_index="1702" cell_dof_index="2" />
    <dof index="346" value="-0.0015739306546341111" cell_index="1768" cell_dof_index="2" />
    <dof index="347" value="0" cell_index="1834" cell_dof_index="2" />
    <dof index="348" value="-0.012867758351863086" cell_index="1900" cell_dof_index="2" />
    <dof index="349" value="-0.012070278555153125" cell_index="1966" cell_dof_index="2" />
    <dof index="350" value="-0.011317296659441011" cell_index="2032" cell_dof_index="2" />
    <dof index="351" value="-0.010583308869577453" cell_index="321" cell_dof_index="1" />
    <dof index="352" value="-0.0098410467334128574" cell_index="384" cell_dof_index="2" />
    <dof index="353" value="-0.009063737150222316" cell_index="450" cell_dof_index="2" />
    <dof index="354" value="-0.0082273445975756272" cell_index="516" cell_dof_index="2" />
    <dof index="355" value="-0.0073126072923594262" cell_index="582" cell_dof_index="2" />
    <dof index="356" value="-0.0063066943083566335" cell_index="648" cell_dof_index="2" />
    <dof index="357" value="-0.0052043406512186259" cell_index="714" cell_dof_index="2" />
    <dof index="358" value="-0.004008359581262856" cell_index="780" cell_dof_index="2" />
    <dof index="359" value="-0.0027294826571453773" cell_index="846" cell_dof_index="2" />
    <dof index="360" value="-0.0013855338489849474" cell_index="912" cell_dof_index="2" />
    <dof index="361" value="0" cell_index="978" cell_dof_index="2" />
    <dof index="362" value="-0.0077794359835339708" cell_index="1044" cell_dof_index="2" />
    <dof index="363" value="-0.0072973051525824749" cell_index="1110" cell_dof_index="2" />
    <dof index="364" value="-0.0068420763322802709" cell_index="1176" cell_dof_index="2" />
    <dof index="365" value="-0.0063983307421159675" cell_index="1242" cell_dof_index="2" />
    <dof index="366" value="-0.0059495827462805019" cell_index="1308" cell_dof_index="2" />
    <dof index="367" value="-0.005479646182625436" cell_index="1374" cell_dof_index="2" />
    <dof index="368" value="-0.004973989941460681" cell_index="1440" cell_dof_index="2" />
    <dof index="369" value="-0.004420968963517815" cell_index="1506" cell_dof_index="2" />
    <dof index="370" value="-0.0038128260803463767" cell_index="1572" cell_dof_index="2" />
    <dof index="371" value="-0.0031463782444124642" cell_index="1638" cell_dof_index="2" />
    <dof index="372" value="-0.0024233262631097327" cell_index="1704" cell_dof_index="2" />
    <dof index="373" value="-0.0016501580942693316" cell_index="1770" cell_dof_index="2" />
    <dof index="374" value="-0.00083764954131557883" cell_index="1836" cell_dof_index="2" />
    <dof index="375" value="0" cell_index="1902" cell_dof_index="2" />
    <dof index="376" value="-0.0014412541157092719" cell_index="1968" cell_dof_index="2" />
    <dof index="377" value="-0.0013519323389262314" cell_index="2034" cell_dof_index="2" />
    <dof index="378" value="-0.0012675945524544697" cell_index="257" cell_dof_index="1" />
    <dof index="379" value="-0.0011853842020504274" cell_index="320" cell_dof_index="2" />
    <dof index="380" value="-0.0011022470829478226" cell_index="386" cell_dof_index="2" />
    <dof index="381" value="-0.0010151844722490896" cell_index="452" cell_dof_index="2" />
    <dof index="382" value="-0.00092150426969258995" cell_index="518" cell_dof_index="2" />
    <dof index="383" value="-0.00081904905800105434" cell_index="584" cell_dof_index="2" />
    <dof index="384" value="-0.00070638170844443849" cell_index="650" cell_dof_index="2" />
    <dof index="385" value="-0.00058291251498641201" cell_index="716" cell_dof_index="2" />
    <dof index="386" value="-0.00044895657703280861" cell_index="782" cell_dof_index="2" />
    <dof index="387" value="-0.00030571588351270838" cell_index="848" cell_dof_index="2" />
    <dof index="388" value="-0.0001551868093648913" cell_index="914" cell_dof_index="2" />
    <dof index="389" value="0" cell_index="980" cell_dof_index="2" />
    <dof index="390" value="-0.0016219744401564757" cell_index="1046" cell_dof_index="2" />
    <dof index="391" value="-0.0015214525146248657" cell_index="1112" cell_dof_index="2" />
    <dof index="392" value="-0.0014265395270360998" cell_index="1178" cell_dof_index="2" />
    <dof index="393" value="-0.0013340207368947488" cell_index="1244" cell_dof_index="2" />
    <dof index="394" value="-0.0012404589695819051" cell_index="1310" cell_dof_index="2" />
    <dof index="395" value="-0.001142479489275516" cell_index="1376" cell_dof_index="2" />
    <dof index="396" value="-0.0010370526305147015" cell_index="1442" cell_dof_index="2" />
    <dof index="397" value="-0.00092175045526803382" cell_index="1508" cell_dof_index="2" />
    <dof index="398" value="-0.0007949556317673398" cell_index="1574" cell_dof_index="2" />
    <dof index="399" value="-0.0006560045101345665" cell_index="1640" cell_dof_index="2" />
    <dof index="400" value="-0.00050525170041162146" cell_index="1706" cell_dof_index="2" />
    <dof index="401" value="-0.00034404991014609702" cell_index="1772" cell_dof_index="2" />
    <dof index="402" value="-0.00017464584176775648" cell_index="1838" cell_dof_index="2" />
    <dof index="403" value="0" cell_index="1904" cell_dof_index="2" />
    <dof index="404" value="-0.0089915555867287333" cell_index="1970" cell_dof_index="2" />
    <dof index="405" value="-0.00843430359882732" cell_index="2036" cell_dof_index="2" />
    <dof index="406" value="-0.0079081452435054243" cell_index="193" cell_dof_index="1" />
    <dof index="407" value="-0.007395259328797304" cell_index="256" cell_dof_index="2" />
    <dof index="408" value="-0.0068765915799363191" cell_index="322" cell_dof_index="2" />
    <dof index="409" value="-0.0063334338570262714" cell_index="388" cell_dof_index="2" />
    <dof index="410" value="-0.005748990947561798" cell_index="454" cell_dof_index="2" />
    <dof index="411" value="-0.0051098033670835671" cell_index="520" cell_dof_index="2" />
    <dof index="412" value="-0.0044069052970585158" cell_index="586" cell_dof_index="2" />
    <dof index="413" value="-0.0036366177369913828" cell_index="652" cell_dof_index="2" />
    <dof index="414" value="-0.0028009064983182063" cell_index="718" cell_dof_index="2" />
    <dof index="415" value="-0.0019072704323190295" cell_index="784" cell_dof_index="2" />
    <dof index="416" value="-0.00096816432822105318" cell_index="850" cell_dof_index="2" />
    <dof index="417" value="0" cell_index="916" cell_dof_index="2" />
    <dof index="418" value="-0.015586037766631535" cell_index="982" cell_dof_index="2" />
    <dof index="419" value="-0.014620092503302325" cell_index="1048" cell_dof_index="2" />
    <dof index="420" value="-0.013708045203124387" cell_index="1114" cell_dof_index="2" />
    <dof index="421" value="-0.012819004462675334" cell_index="1180" cell_dof_index="2" />
    <dof index="422" value="-0.011919941442477497" cell_index="1246" cell_dof_index="2" />
    <dof index="423" value="-0.010978427296136826" cell_index="1312" cell_dof_index="2" />
    <dof index="424" value="-0.0099653490616210833" cell_index="1378" cell_dof_index="2" />
    <dof index="425" value="-0.008857375955832832" cell_index="1444" cell_dof_index="2" />
    <dof index="426" value="-0.0076389665538298358" cell_index="1510" cell_dof_index="2" />
    <dof index="427" value="-0.0063037436453385731" cell_index="1576" cell_dof_index="2" />
    <dof index="428" value="-0.0048551147843677658" cell_index="1642" cell_dof_index="2" />
    <dof index="429" value="-0.0033060785425360548" cell_index="1708" cell_dof_index="2" />
    <dof index="430" value="-0.0016782241558102521" cell_index="1774" cell_dof_index="2" />
    <dof index="431" value="0" cell_index="1840" cell_dof_index="2" />
    <dof index="432" value="-0.019040120282420761" cell_index="1906" cell_dof_index="2" />
    <dof index="433" value="-0.017860108128247877" cell_index="1972" cell_dof_index="2" />
    <dof index="434" value="-0.016745938474699164" cell_index="2038" cell_dof_index="2" />
    <dof index="435" value="-0.015659873954159974" cell_index="129" cell_dof_index="1" />
    <dof index="436" value="-0.014561566077433785" cell_index="192" cell_dof_index="2" />
    <dof index="437" value="-0.013411399315211098" cell_index="258" cell_dof_index="2" />
    <dof index="438" value="-0.012173808868588501" cell_index="324" cell_dof_index="2" />
    <dof index="439" value="-0.010820293528784799" cell_index="390" cell_dof_index="2" />
    <dof index="440" value="-0.0093318676751636895" cell_index="456" cell_dof_index="2" />
    <dof index="441" value="-0.007700740819052412" cell_index="522" cell_dof_index="2" />
    <dof index="442" value="-0.0059310756757713278" cell_index="588" cell_dof_index="2" />
    <dof index="443" value="-0.00403875148100717" cell_index="654" cell_dof_index="2" />
    <dof index="444" value="-0.0020501419453699344" cell_index="720" cell_dof_index="2" />
    <dof index="445" value="0" cell_index="786" cell_dof_index="2" />
    <dof index="446" value="-0.019040120282420577" cell_index="852" cell_dof_index="2" />
    <dof index="447" value="-0.017860108128247704" cell_index="918" cell_dof_index="2" />
    <dof index="448" value="-0.016745938474699001" cell_index="984" cell_dof_index="2" />
    <dof index="449" value="-0.015659873954159818" cell_index="1050" cell_dof_index="2" />
    <dof index="450" value="-0.014561566077433641" cell_index="1116" cell_dof_index="2" />
    <dof index="451" value="-0.013411399315210966" cell_index="1182" cell_dof_index="2" />
    <dof index="452" value="-0.01217380886858838" cell_index="1248" cell_dof_index="2" />
    <dof index="453" value="-0.010820293528784691" cell_index="1314" cell_dof_index="2" />
    <dof index="454" value="-0.0093318676751635958" cell_index="1380" cell_dof_index="2" />
    <dof index="455" value="-0.0077007408190523357" cell_index="1446" cell_dof_index="2" />
    <dof index="456" value="-0.0059310756757712706" cell_index="1512" cell_dof_index="2" />
    <dof index="457" value="-0.004038751481007131" cell_index="1578" cell_dof_index="2" />
    <dof index="458" value="-0.0020501419453699144" cell_index="1644" cell_dof_index="2" />
    <dof index="459" value="0" cell_index="1710" cell_dof_index="2" />
    <dof index="460" value="-0.015586037766631285" cell_index="1776" cell_dof_index="2" />
    <dof index="461" value="-0.014620092503302089" cell_index="1842" cell_dof_index="2" />
    <dof index="462" value="-0.013708045203124165" cell_index="1908" cell_dof_index="2" />
    <dof index="463" value="-0.012819004462675126" cell_index="1974" cell_dof_index="2" />
    <dof index="464" value="-0.011919941442477303" cell_index="2040" cell_dof_index="2" />
    <dof index="465" value="-0.010978427296136645" cell_index="65" cell_dof_index="1" />
    <dof index="466" value="-0.009965349061620922" cell_index="128" cell_dof_index="2" />
    <dof index="467" value="-0.0088573759558326862" cell_index="194" cell_dof_index="2" />
    <dof index="468" value="-0.0076389665538297109" cell_index="260" cell_dof_index="2" />
    <dof index="469" value="-0.0063037436453384698" cell_index="326" cell_dof_index="2" />
    <dof index="470" value="-0.004855114784367686" cell_index="392" cell_dof_index="2" />
    <dof index="471" value="-0.003306078542536001" cell_index="458" cell_dof_index="2" />
    <dof index="472" value="-0.0016782241558102248" cell_index="524" cell_dof_index="2" />
    <dof index="473" value="0" cell_index="590" cell_dof_index="2" />
    <dof index="474" value="-0.0089915555867284939" cell_index="656" cell_dof_index="2" />
    <dof index="475" value="-0.0084343035988270962" cell_index="722" cell_dof_index="2" />
    <dof index="476" value="-0.0079081452435052144" cell_index="788" cell_dof_index="2" />
    <dof index="477" value="-0.0073952593287971071" cell_index="854" cell_dof_index="2" />
    <dof index="478" value="-0.006876591579936136" cell_index="920" cell_dof_index="2" />
    <dof index="479" value="-0.0063334338570261023" cell_index="986" cell_dof_index="2" />
    <dof index="480" value="-0.0057489909475616444" cell_index="1052" cell_dof_index="2" />
    <dof index="481" value="-0.0051098033670834301" cell_index="1118" cell_dof_index="2" />
    <dof index="482" value="-0.0044069052970583987" cell_index="1184" cell_dof_index="2" />
    <dof index="483" value="-0.0036366177369912861" cell_index="1250" cell_dof_index="2" />
    <dof index="484" value="-0.0028009064983181313" cell_index="1316" cell_dof_index="2" />
    <dof index="485" value="-0.0019072704323189788" cell_index="1382" cell_dof_index="2" />
    <dof index="486" value="-0.00096816432822102749" cell_index="1448" cell_dof_index="2" />
    <dof index="487" value="0" cell_index="1514" cell_dof_index="2" />
    <dof index="488" value="-0.0016219744401564243" cell_index="1580" cell_dof_index="2" />
    <dof index="489" value="-0.0015214525146248175" cell_index="1646" cell_dof_index="2" />
    <dof index="490" value="-0.0014265395270360544" cell_index="1712" cell_dof_index="2" />
    <dof index="491" value="-0.0013340207368947067" cell_index="1778" cell_dof_index="2" />
    <dof index="492" value="-0.0012404589695818658" cell_index="1844" cell_dof_index="2" />
    <dof index="493" value="-0.0011424794892754796" cell_index="1910" cell_dof_index="2" />
    <dof index="494" value="-0.0010370526305146686" cell_index="1976" cell_dof_index="2" />
    <dof index="495" value="-0.00092175045526800444" cell_index="2042" cell_dof_index="2" />
    <dof index="496" value="-0.00079495563176731454" cell_index="1" cell_dof_index="1" />
    <dof index="497" value="-0.00065600451013454568" cell_index="64" cell_dof_index="2" />
    <dof index="498" value="-0.00050525170041160541" cell_index="130" cell_dof_index="2" />
    <dof index="499" value="-0.00034404991014608613" cell_index="196" cell_dof_index="2" />
    <dof index="500" value="-0.00017464584176775093" cell_index="262" cell_dof_index="2" />
    <dof index="501" value="0" cell_index="328" cell_dof_index="2" />
    <dof index="502" value="-0.0017663243732226842" cell_index="394" cell_dof_index="2" />
    <dof index="503" value="-0.0016568563552848497" cell_index="460" cell_dof_index="2" />
    <dof index="504" value="-0.0015534964507371268" cell_index="526" cell_dof_index="2" />
    <dof index="505" value="-0.0014527438186599055" cell_index="592" cell_dof_index="2" />
    <dof index="506" value="-0.0013508553881674233" cell_index="658" cell_dof_index="2" />
    <dof index="507" value="-0.0012441560840007243" cell_index="724" cell_dof_index="2" />
    <dof index="508" value="-0.0011293466112919145" cell_index="790" cell_dof_index="2" />
    <dof index="509" value="-0.0010037829541949908" cell_index="856" cell_dof_index="2" />
    <dof index="510" value="-0.00086570384418994148" cell_index="922" cell_dof_index="2" />
    <dof index="511" value="-0.0007143865689294757" cell_index="988" cell_dof_index="2" />
    <dof index="512" value="-0.00055021729748291036" cell_index="1054" cell_dof_index="2" />
    <dof index="513" value="-0.00037466912353902379" cell_index="1120" cell_dof_index="2" />
    <dof index="514" value="-0.00019018869802080269" cell_index="1186" cell_dof_index="2" />
    <dof index="515" value="0" cell_index="1252" cell_dof_index="2" />
    <dof index="516" value="-0.0099990890387242903" cell_index="1318" cell_dof_index="2" />
    <dof index="517" value="-0.0093793951281114854" cell_index="1384" cell_dof_index="2" />
    <dof index="518" value="-0.0087942789941360035" cell_index="1450" cell_dof_index="2" />
    <dof index="519" value="-0.0082239225215092419" cell_index="1516" cell_dof_index="2" />
    <dof index="520" value="-0.0076471363411479308" cell_index="1582" cell_dof_index="2" />
    <dof index="521" value="-0.0070431160043928059" cell_index="1648" cell_dof_index="2" />
    <dof index="522" value="-0.0063931843397972195" cell_index="1714" cell_dof_index="2" />
    <dof index="523" value="-0.0056823736832872455" cell_index="1780" cell_dof_index="2" />
    <dof index="524" value="-0.0049007135667995536" cell_index="1846" cell_dof_index="2" />
    <dof index="525" value="-0.004044112745702353" cell_index="1912" cell_dof_index="2" />
    <dof index="526" value="-0.0031147573070851036" cell_index="1978" cell_dof_index="2" />
    <dof index="527" value="-0.002120986373240279" cell_index="2044" cell_dof_index="2" />
    <dof index="528" value="-0.0010766503335960589" cell_index="0" cell_dof_index="0" />
    <dof index="529" value="0" cell_index="0" cell_dof_index="2" />
    <dof index="530" value="-0.017942866858365141" cell_index="66" cell_dof_index="2" />
    <dof index="531" value="-0.016830857025469024" cell_index="132" cell_dof_index="2" />
    <dof index="532" value="-0.015780895289160407" cell_index="198" cell_dof_index="2" />
    <dof index="533" value="-0.014757419029421608" cell_index="264" cell_dof_index="2" />
    <dof index="534" value="-0.013722404979652892" cell_index="330" cell_dof_index="2" />
    <dof index="535" value="-0.012638520593768398" cell_index="396" cell_dof_index="2" />
    <dof index="536" value="-0.011472250618602534" cell_index="462" cell_dof_index="2" />
    <dof index="537" value="-0.010196736327063355" cell_index="528" cell_dof_index="2" />
    <dof index="538" value="-0.0087940862112061771" cell_index="594" cell_dof_index="2" />
    <dof index="539" value="-0.0072569587364743147" cell_index="660" cell_dof_index="2" />
    <dof index="540" value="-0.0055892767271805647" cell_index="726" cell_dof_index="2" />
    <dof index="541" value="-0.0038060043226010158" cell_index="792" cell_dof_index="2" />
    <dof index="542" value="-0.0019319953561682821" cell_index="858" cell_dof_index="2" />
    <dof index="543" value="0" cell_index="924" cell_dof_index="2" />
    <dof index="544" value="-0.023012998011628649" cell_index="990" cell_dof_index="2" />
    <dof index="545" value="-0.021586766614196236" cell_index="1056" cell_dof_index="2" />
    <dof index="546" value="-0.020240116296792166" cell_index="1122" cell_dof_index="2" />
    <dof index="547" value="-0.018927435479605067" cell_index="1188" cell_dof_index="2" />
    <dof index="548" value="-0.01759995662924339" cell_index="1254" cell_dof_index="2" />
    <dof index="549" value="-0.016209798110312711" cell_index="1320" cell_dof_index="2" />
    <dof index="550" value="-0.014713974236046964" cell_index="1386" cell_dof_index="2" />
    <dof index="551" value="-0.013078036785989466" cell_index="1452" cell_dof_index="2" />
    <dof index="552" value="-0.011279038633574205" cell_index="1518" cell_dof_index="2" />
    <dof index="553" value="-0.0093075637405789155" cell_index="1584" cell_dof_index="2" />
    <dof index="554" value="-0.0071686434071198523" cell_index="1650" cell_dof_index="2" />
    <dof index="555" value="-0.0048814702020392575" cell_index="1716" cell_dof_index="2" />
    <dof index="556" value="-0.0024779209276274759" cell_index="1782" cell_dof_index="2" />
    <dof index="557" value="0" cell_index="1848" cell_dof_index="2" />
    <dof index="558" value="-0.024755036391421653" cell_index="1914" cell_dof_index="2" />
    <dof index="559" value="-0.023220842101386651" cell_index="1980" cell_dof_index="2" />
    <dof index="560" value="-0.021772253021553934" cell_index="2046" cell_dof_index="2" />
    <dof index="561" value="-0.020360204865839168" cell_index="0" cell_dof_index="1" />
    <dof index="562" value="-0.018932238495141158" cell_index="2" cell_dof_index="2" />
    <dof index="563" value="-0.017436847729079979" cell_index="68" cell_dof_index="2" />
    <dof index="564" value="-0.015827792949520414" cell_index="134" cell_dof_index="2" />
    <dof index="565" value="-0.014068018273930595" cell_index="200" cell_dof_index="2" />
    <dof index="566" value="-0.012132839523702721" cell_index="266" cell_dof_index="2" />
    <dof index="567" value="-0.010012127885166469" cell_index="332" cell_dof_index="2" />
    <dof index="568" value="-0.0077112955178940575" cell_index="398" cell_dof_index="2" />
    <dof index="569" value="-0.0052509878301845048" cell_index="464" cell_dof_index="2" />
    <dof index="570" value="-0.0026654946351399918" cell_index="530" cell_dof_index="2" />
    <dof index="571" value="0" cell_index="596" cell_dof_index="2" />
    <dof index="572" value="-0.023012998011628316" cell_index="662" cell_dof_index="2" />
    <dof index="573" value="-0.021586766614195924" cell_index="728" cell_dof_index="2" />
    <dof index="574" value="-0.020240116296791875" cell_index="794" cell_dof_index="2" />
    <dof index="575" value="-0.018927435479604793" cell_index="860" cell_dof_index="2" />
    <dof index="576" value="-0.01759995662924314" cell_index="926" cell_dof_index="2" />
    <dof index="577" value="-0.016209798110312482" cell_index="992" cell_dof_index="2" />
    <dof index="578" value="-0.014713974236046756" cell_index="1058" cell_dof_index="2" />
    <dof index="579" value="-0.013078036785989282" cell_index="1124" cell_dof_index="2" />
    <dof index="580" value="-0.011279038633574047" cell_index="1190" cell_dof_index="2" />
    <dof index="581" value="-0.0093075637405787854" cell_index="1256" cell_dof_index="2" />
    <dof index="582" value="-0.0071686434071197526" cell_index="1322" cell_dof_index="2" />
    <dof index="583" value="-0.0048814702020391898" cell_index="1388" cell_dof_index="2" />
    <dof index="584" value="-0.0024779209276274412" cell_index="1454" cell_dof_index="2" />
    <dof index="585" value="0" cell_index="1520" cell_dof_index="2" />
    <dof index="586" value="-0.017942866858364707" cell_index="1586" cell_dof_index="2" />
    <dof index="587" value="-0.016830857025468618" cell_index="1652" cell_dof_index="2" />
    <dof index="588" value="-0.015780895289160025" cell_index="1718" cell_dof_index="2" />
    <dof index="589" value="-0.014757419029421253" cell_index="1784" cell_dof_index="2" />
    <dof index="590" value="-0.013722404979652563" cell_index="1850" cell_dof_index="2" />
    <dof index="591" value="-0.012638520593768092" cell_index="1916" cell_dof_index="2" />
    <dof index="592" value="-0.011472250618602256" cell_index="1982" cell_dof_index="2" />
    <dof index="593" value="-0.010196736327063107" cell_index="2" cell_dof_index="1" />
    <dof index="594" value="-0.0087940862112059655" cell_index="4" cell_dof_index="2" />
    <dof index="595" value="-0.0072569587364741395" cell_index="70" cell_dof_index="2" />
    <dof index="596" value="-0.0055892767271804294" cell_index="136" cell_dof_index="2" />
    <dof index="597" value="-0.0038060043226009234" cell_index="202" cell_dof_index="2" />
    <dof index="598" value="-0.001931995356168235" cell_index="268" cell_dof_index="2" />
    <dof index="599" value="0" cell_index="334" cell_dof_index="2" />
    <dof index="600" value="-0.0099990890387239295" cell_index="400" cell_dof_index="2" />
    <dof index="601" value="-0.0093793951281111471" cell_index="466" cell_dof_index="2" />
    <dof index="602" value="-0.0087942789941356861" cell_index="532" cell_dof_index="2" />
    <dof index="603" value="-0.0082239225215089452" cell_index="598" cell_dof_index="2" />
    <dof index="604" value="-0.007647136341147655" cell_index="664" cell_dof_index="2" />
    <dof index="605" value="-0.0070431160043925517" cell_index="730" cell_dof_index="2" />
    <dof index="606" value="-0.0063931843397969888" cell_index="796" cell_dof_index="2" />
    <dof index="607" value="-0.0056823736832870399" cell_index="862" cell_dof_index="2" />
    <dof index="608" value="-0.0049007135667993766" cell_index="928" cell_dof_index="2" />
    <dof index="609" value="-0.0040441127457022073" cell_index="994" cell_dof_index="2" />
    <dof index="610" value="-0.0031147573070849912" cell_index="1060" cell_dof_index="2" />
    <dof index="611" value="-0.0021209863732402027" cell_index="1126" cell_dof_index="2" />
    <dof index="612" value="-0.0010766503335960203" cell_index="1192" cell_dof_index="2" />
    <dof index="613" value="0" cell_index="1258" cell_dof_index="2" />
    <dof index="614" value="-0.001766324373222594" cell_index="1324" cell_dof_index="2" />
    <dof index="615" value="-0.0016568563552847649" cell_index="1390" cell_dof_index="2" />
    <dof index="616" value="-0.0015534964507370474" cell_index="1456" cell_dof_index="2" />
    <dof index="617" value="-0.0014527438186598312" cell_index="1522" cell_dof_index="2" />
    <dof index="618" value="-0.0013508553881673541" cell_index="1588" cell_dof_index="2" />
    <dof index="619" value="-0.0012441560840006605" cell_index="1654" cell_dof_index="2" />
    <dof index="620" value="-0.0011293466112918568" cell_index="1720" cell_dof_index="2" />
    <dof index="621" value="-0.0010037829541949396" cell_index="1786" cell_dof_index="2" />
    <dof index="622" value="-0.00086570384418989735" cell_index="1852" cell_dof_index="2" />
    <dof index="623" value="-0.00071438656892943927" cell_index="1918" cell_dof_index="2" />
    <dof index="624" value="-0.00055021729748288228" cell_index="4" cell_dof_index="1" />
    <dof index="625" value="-0.00037466912353900466" cell_index="6" cell_dof_index="2" />
    <dof index="626" value="-0.00019018869802079301" cell_index="72" cell_dof_index="2" />
    <dof index="627" value="0" cell_index="138" cell_dof_index="2" />
    <dof index="628" value="-0.0018720381984654909" cell_index="204" cell_dof_index="2" />
    <dof index="629" value="-0.001756018562323553" cell_index="270" cell_dof_index="2" />
    <dof index="630" value="-0.0016464726077772473" cell_index="336" cell_dof_index="2" />
    <dof index="631" value="-0.0015396899699425151" cell_index="402" cell_dof_index="2" />
    <dof index="632" value="-0.0014317035566000914" cell_index="468" cell_dof_index="2" />
    <dof index="633" value="-0.0013186183406692763" cell_index="534" cell_dof_index="2" />
    <dof index="634" value="-0.0011969375657703632" cell_index="600" cell_dof_index="2" />
    <dof index="635" value="-0.0010638589727395751" cell_index="666" cell_dof_index="2" />
    <dof index="636" value="-0.00091751588182250124" cell_index="732" cell_dof_index="2" />
    <dof index="637" value="-0.00075714232661957116" cell_index="798" cell_dof_index="2" />
    <dof index="638" value="-0.00058314758826837553" cell_index="864" cell_dof_index="2" />
    <dof index="639" value="-0.00039709292454077015" cell_index="930" cell_dof_index="2" />
    <dof index="640" value="-0.00020157141746380354" cell_index="996" cell_dof_index="2" />
    <dof index="641" value="0" cell_index="1062" cell_dof_index="2" />
    <dof index="642" value="-0.010783840001602218" cell_index="1128" cell_dof_index="2" />
    <dof index="643" value="-0.010115511121227702" cell_index="1194" cell_dof_index="2" />
    <dof index="644" value="-0.0094844737590528902" cell_index="1260" cell_dof_index="2" />
    <dof index="645" value="-0.0088693544295954628" cell_index="1326" cell_dof_index="2" />
    <dof index="646" value="-0.0082473007745011758" cell_index="1392" cell_dof_index="2" />
    <dof index="647" value="-0.0075958755652590967" cell_index="1458" cell_dof_index="2" />
    <dof index="648" value="-0.0068949358040638117" cell_index="1524" cell_dof_index="2" />
    <dof index="649" value="-0.0061283391309517425" cell_index="1590" cell_dof_index="2" />
    <dof index="650" value="-0.0052853325731351056" cell_index="1656" cell_dof_index="2" />
    <dof index="651" value="-0.0043615037959156338" cell_index="1722" cell_dof_index="2" />
    <dof index="652" value="-0.0033592104554068967" cell_index="1788" cell_dof_index="2" />
    <dof index="653" value="-0.0022874461469461864" cell_index="1854" cell_dof_index="2" />
    <dof index="654" value="-0.0011611482696280537" cell_index="6" cell_dof_index="1" />
    <dof index="655" value="0" cell_index="8" cell_dof_index="2" />
    <dof index="656" value="-0.019890227321765569" cell_index="74" cell_dof_index="2" />
    <dof index="657" value="-0.018657529752590291" cell_index="140" cell_dof_index="2" />
    <dof index="658" value="-0.017493614432971354" cell_index="206" cell_dof_index="2" />
    <dof index="659" value="-0.016359059089874423" cell_index="272" cell_dof_index="2" />
    <dof index="660" value="-0.015211713746812747" cell_index="338" cell_dof_index="2" />
    <dof index="661" value="-0.014010194112523982" cell_index="404" cell_dof_index="2" />
    <dof index="662" value="-0.012717347483960605" cell_index="470" cell_dof_index="2" />
    <dof index="663" value="-0.011303400124759912" cell_index="536" cell_dof_index="2" />
    <dof index="664" value="-0.0097485187405571827" cell_index="602" cell_dof_index="2" />
    <dof index="665" value="-0.0080445650114074636" cell_index="668" cell_dof_index="2" />
    <dof index="666" value="-0.0061958875103643668" cell_index="734" cell_dof_index="2" />
    <dof index="667" value="-0.0042190744523561696" cell_index="800" cell_dof_index="2" />
    <dof index="668" value="-0.002141677086617133" cell_index="866" cell_dof_index="2" />
    <dof index="669" value="0" cell_index="932" cell_dof_index="2" />
    <dof index="670" value="-0.026448169496988607" cell_index="998" cell_dof_index="2" />
    <dof index="671" value="-0.024809043220518304" cell_index="1064" cell_dof_index="2" />
    <dof index="672" value="-0.02326137716545329" cell_index="1130" cell_dof_index="2" />
    <dof index="673" value="-0.021752751269302487" cell_index="1196" cell_dof_index="2" />
    <dof index="674" value="-0.020227118423886511" cell_index="1262" cell_dof_index="2" />
    <dof index="675" value="-0.018629449657836014" cell_index="1328" cell_dof_index="2" />
    <dof index="676" value="-0.016910342771187359" cell_index="1394" cell_dof_index="2" />
    <dof index="677" value="-0.015030207425773927" cell_index="1460" cell_dof_index="2" />
    <dof index="678" value="-0.012962671156235926" cell_index="1526" cell_dof_index="2" />
    <dof index="679" value="-0.010696912383621894" cell_index="1592" cell_dof_index="2" />
    <dof index="680" value="-0.008238713434867144" cell_index="1658" cell_dof_index="2" />
    <dof index="681" value="-0.0056101317713057328" cell_index="1724" cell_dof_index="2" />
    <dof index="682" value="-0.0028478024749713461" cell_index="1790" cell_dof_index="2" />
    <dof index="683" value="0" cell_index="8" cell_dof_index="1" />
    <dof index="684" value="-0.029878478869095601" cell_index="10" cell_dof_index="2" />
    <dof index="685" value="-0.028026759043234928" cell_index="76" cell_dof_index="2" />
    <dof index="686" value="-0.026278361766518231" cell_index="142" cell_dof_index="2" />
    <dof index="687" value="-0.02457406813044468" cell_index="208" cell_dof_index="2" />
    <dof index="688" value="-0.022850561755496896" cell_index="274" cell_dof_index="2" />
    <dof index="689" value="-0.021045676450610715" cell_index="340" cell_dof_index="2" />
    <dof index="690" value="-0.019103602584504518" cell_index="406" cell_dof_index="2" />
    <dof index="691" value="-0.016979614979412562" cell_index="472" cell_dof_index="2" />
    <dof index="692" value="-0.014643920679377408" cell_index="538" cell_dof_index="2" />
    <dof index="693" value="-0.012084294554109103" cell_index="604" cell_dof_index="2" />
    <dof index="694" value="-0.0093072688943648778" cell_index="670" cell_dof_index="2" />
    <dof index="695" value="-0.0063377619990255185" cell_index="736" cell_dof_index="2" />
    <dof index="696" value="-0.0032171604950383308" cell_index="802" cell_dof_index="2" />
    <dof index="697" value="0" cell_index="868" cell_dof_index="2" />
    <dof index="698" value="-0.029878478869095438" cell_index="934" cell_dof_index="2" />
    <dof index="699" value="-0.028026759043234775" cell_index="1000" cell_dof_index="2" />
    <dof index="700" value="-0.026278361766518082" cell_index="1066" cell_dof_index="2" />
    <dof index="701" value="-0.024574068130444545" cell_index="1132" cell_dof_index="2" />
    <dof index="702" value="-0.022850561755496771" cell_index="1198" cell_dof_index="2" />
    <dof index="703" value="-0.021045676450610597" cell_index="1264" cell_dof_index="2" />
    <dof index="704" value="-0.019103602584504411" cell_index="1330" cell_dof_index="2" />
    <dof index="705" value="-0.016979614979412465" cell_index="1396" cell_dof_index="2" />
    <dof index="706" value="-0.014643920679377325" cell_index="1462" cell_dof_index="2" />
    <dof index="707" value="-0.012084294554109034" cell_index="1528" cell_dof_index="2" />
    <dof index="708" value="-0.0093072688943648257" cell_index="1594" cell_dof_index="2" />
    <dof index="709" value="-0.0063377619990254812" cell_index="1660" cell_dof_index="2" />
    <dof index="710" value="-0.0032171604950383117" cell_index="1726" cell_dof_index="2" />
    <dof index="711" value="0" cell_index="10" cell_dof_index="1" />
    <dof index="712" value="-0.026448169496988017" cell_index="12" cell_dof_index="2" />
    <dof index="713" value="-0.024809043220517753" cell_index="78" cell_dof_index="2" />
    <dof index="714" value="-0.023261377165452773" cell_index="144" cell_dof_index="2" />
    <dof index="715" value="-0.021752751269302002" cell_index="210" cell_dof_index="2" />
    <dof index="716" value="-0.02022711842388606" cell_index="276" cell_dof_index="2" />
    <dof index="717" value="-0.018629449657835601" cell_index="342" cell_dof_index="2" />
    <dof index="718" value="-0.016910342771186981" cell_index="408" cell_dof_index="2" />
    <dof index="719" value="-0.015030207425773594" cell_index="474" cell_dof_index="2" />
    <dof index="720" value="-0.012962671156235638" cell_index="540" cell_dof_index="2" />
    <dof index="721" value="-0.010696912383621656" cell_index="606" cell_dof_index="2" />
    <dof index="722" value="-0.0082387134348669601" cell_index="672" cell_dof_index="2" />
    <dof index="723" value="-0.0056101317713056079" cell_index="738" cell_dof_index="2" />
    <dof index="724" value="-0.0028478024749712828" cell_index="804" cell_dof_index="2" />
    <dof index="725" value="0" cell_index="870" cell_dof_index="2" />
    <dof index="726" value="-0.019890227321764854" cell_index="936" cell_dof_index="2" />
    <dof index="727" value="-0.018657529752589625" cell_index="1002" cell_dof_index="2" />
    <dof index="728" value="-0.017493614432970733" cell_index="1068" cell_dof_index="2" />
    <dof index="729" value="-0.016359059089873836" cell_index="1134" cell_dof_index="2" />
    <dof index="730" value="-0.015211713746812202" cell_index="1200" cell_dof_index="2" />
    <dof index="731" value="-0.01401019411252348" cell_index="1266" cell_dof_index="2" />
    <dof index="732" value="-0.01271734748396015" cell_index="1332" cell_dof_index="2" />
    <dof index="733" value="-0.011303400124759506" cell_index="1398" cell_dof_index="2" />
    <dof index="734" value="-0.0097485187405568358" cell_index="1464" cell_dof_index="2" />
    <dof index="735" value="-0.0080445650114071756" cell_index="1530" cell_dof_index="2" />
    <dof index="736" value="-0.0061958875103641457" cell_index="1596" cell_dof_index="2" />
    <dof index="737" value="-0.0042190744523560187" cell_index="1662" cell_dof_index="2" />
    <dof index="738" value="-0.0021416770866170562" cell_index="12" cell_dof_index="1" />
    <dof index="739" value="0" cell_index="14" cell_dof_index="2" />
    <dof index="740" value="-0.010783840001601659" cell_index="80" cell_dof_index="2" />
    <dof index="741" value="-0.01011551112122718" cell_index="146" cell_dof_index="2" />
    <dof index="742" value="-0.009484473759052401" cell_index="212" cell_dof_index="2" />
    <dof index="743" value="-0.0088693544295950048" cell_index="278" cell_dof_index="2" />
    <dof index="744" value="-0.0082473007745007508" cell_index="344" cell_dof_index="2" />
    <dof index="745" value="-0.0075958755652587055" cell_index="410" cell_dof_index="2" />
    <dof index="746" value="-0.006894935804063456" cell_index="476" cell_dof_index="2" />
    <dof index="747" value="-0.0061283391309514268" cell_index="542" cell_dof_index="2" />
    <dof index="748" value="-0.0052853325731348341" cell_index="608" cell_dof_index="2" />
    <dof index="749" value="-0.0043615037959154092" cell_index="674" cell_dof_index="2" />
    <dof index="750" value="-0.0033592104554067232" cell_index="740" cell_dof_index="2" />
    <dof index="751" value="-0.0022874461469460689" cell_index="806" cell_dof_index="2" />
    <dof index="752" value="-0.0011611482696279938" cell_index="872" cell_dof_index="2" />
    <dof index="753" value="0" cell_index="938" cell_dof_index="2" />
    <dof index="754" value="-0.0018720381984653801" cell_index="1004" cell_dof_index="2" />
    <dof index="755" value="-0.0017560185623234491" cell_index="1070" cell_dof_index="2" />
    <dof index="756" value="-0.00164647260777715" cell_index="1136" cell_dof_index="2" />
    <dof index="757" value="-0.0015396899699424245" cell_index="1202" cell_dof_index="2" />
    <dof index="758" value="-0.0014317035566000069" cell_index="1268" cell_dof_index="2" />
    <dof index="759" value="-0.0013186183406691987" cell_index="1334" cell_dof_index="2" />
    <dof index="760" value="-0.0011969375657702927" cell_index="1400" cell_dof_index="2" />
    <dof index="761" value="-0.0010638589727395124" cell_index="1466" cell_dof_index="2" />
    <dof index="762" value="-0.00091751588182244713" cell_index="1532" cell_dof_index="2" />
    <dof index="763" value="-0.0007571423266195266" cell_index="1598" cell_dof_index="2" />
    <dof index="764" value="-0.00058314758826834127" cell_index="14" cell_dof_index="1" />
    <dof index="765" value="-0.00039709292454074679" cell_index="16" cell_dof_index="2" />
    <dof index="766" value="-0.00020157141746379164" cell_index="82" cell_dof_index="2" />
    <dof index="767" value="0" cell_index="148" cell_dof_index="2" />
    <dof index="768" value="-0.0019380620383238935" cell_index="214" cell_dof_index="2" />
    <dof index="769" value="-0.0018179505722805444" cell_index="280" cell_dof_index="2" />
    <dof index="770" value="-0.0017045411043903177" cell_index="346" cell_dof_index="2" />
    <dof index="771" value="-0.001593992411041421" cell_index="412" cell_dof_index="2" />
    <dof index="772" value="-0.0014821974869179417" cell_index="478" cell_dof_index="2" />
    <dof index="773" value="-0.0013651239334665092" cell_index="544" cell_dof_index="2" />
    <dof index="774" value="-0.0012391516692153181" cell_index="610" cell_dof_index="2" />
    <dof index="775" value="-0.0011013796037318583" cell_index="676" cell_dof_index="2" />
    <dof index="776" value="-0.00094987522240574669" cell_index="742" cell_dof_index="2" />
    <dof index="777" value="-0.00078384554440846311" cell_index="808" cell_dof_index="2" />
    <dof index="778" value="-0.00060371428557893505" cell_index="874" cell_dof_index="2" />
    <dof index="779" value="-0.00041109776679253357" cell_index="940" cell_dof_index="2" />
    <dof index="780" value="-0.00020868052399676334" cell_index="1006" cell_dof_index="2" />
    <dof index="781" value="0" cell_index="1072" cell_dof_index="2" />
    <dof index="782" value="-0.01133468734373878" cell_index="1138" cell_dof_index="2" />
    <dof index="783" value="-0.010632219679093292" cell_index="1204" cell_dof_index="2" />
    <dof index="784" value="-0.0099689484138105675" cell_index="1270" cell_dof_index="2" />
    <dof index="785" value="-0.0093224082873385235" cell_index="1336" cell_dof_index="2" />
    <dof index="786" value="-0.0086685796242207402" cell_index="1402" cell_dof_index="2" />
    <dof index="787" value="-0.0079838790840150668" cell_index="1468" cell_dof_index="2" />
    <dof index="788" value="-0.0072471347481603944" cell_index="1534" cell_dof_index="2" />
    <dof index="789" value="-0.0064413796917811607" cell_index="16" cell_dof_index="1" />
    <dof index="790" value="-0.0055553116714699043" cell_index="18" cell_dof_index="2" />
    <dof index="791" value="-0.0045842929668734479" cell_index="84" cell_dof_index="2" />
    <dof index="792" value="-0.0035308016651024532" cell_index="150" cell_dof_index="2" />
    <dof index="793" value="-0.0024042907616788449" cell_index="216" cell_dof_index="2" />
    <dof index="794" value="-0.001220460670225249" cell_index="282" cell_dof_index="2" />
    <dof index="795" value="0" cell_index="348" cell_dof_index="2" />
    <dof index="796" value="-0.021393324835955269" cell_index="414" cell_dof_index="2" />
    <dof index="797" value="-0.020067472743103561" cell_index="480" cell_dof_index="2" />
    <dof index="798" value="-0.018815600750323219" cell_index="546" cell_dof_index="2" />
    <dof index="799" value="-0.017595307457210323" cell_index="612" cell_dof_index="2" />
    <dof index="800" value="-0.016361257628313742" cell_index="678" cell_dof_index="2" />
    <dof index="801" value="-0.015068939575971036" cell_index="744" cell_dof_index="2" />
    <dof index="802" value="-0.013678392980374319" cell_index="810" cell_dof_index="2" />
    <dof index="803" value="-0.012157594114329158" cell_index="876" cell_dof_index="2" />
    <dof index="804" value="-0.010485210888360276" cell_index="942" cell_dof_index="2" />
    <dof index="805" value="-0.0086524899725340838" cell_index="1008" cell_dof_index="2" />
    <dof index="806" value="-0.0066641085600472223" cell_index="1074" cell_dof_index="2" />
    <dof index="807" value="-0.0045379084314217692" cell_index="1140" cell_dof_index="2" />
    <dof index="808" value="-0.0023035228741496152" cell_index="1206" cell_dof_index="2" />
    <dof index="809" value="0" cell_index="1272" cell_dof_index="2" />
    <dof index="810" value="-0.029275391408150889" cell_index="1338" cell_dof_index="2" />
    <dof index="811" value="-0.027461047949843997" cell_index="1404" cell_dof_index="2" />
    <dof index="812" value="-0.025747941508345432" cell_index="1470" cell_dof_index="2" />
    <dof index="813" value="-0.024078048489725903" cell_index="18" cell_dof_index="1" />
    <dof index="814" value="-0.022389330535170712" cell_index="20" cell_dof_index="2" />
    <dof index="815" value="-0.02062087625813535" cell_index="86" cell_dof_index="2" />
    <dof index="816" value="-0.018718002526748483" cell_index="152" cell_dof_index="2" />
    <dof index="817" value="-0.016636886926534856" cell_index="218" cell_dof_index="2" />
    <dof index="818" value="-0.014348337862745588" cell_index="284" cell_dof_index="2" />
    <dof index="819" value="-0.011840376965403342" cell_index="350" cell_dof_index="2" />
    <dof index="820" value="-0.0091194046730829134" cell_index="416" cell_dof_index="2" />
    <dof index="821" value="-0.0062098363168376705" cell_index="482" cell_dof_index="2" />
    <dof index="822" value="-0.0031522231478960973" cell_index="548" cell_dof_index="2" />
    <dof index="823" value="0" cell_index="614" cell_dof_index="2" />
    <dof index="824" value="-0.034296154883523514" cell_index="680" cell_dof_index="2" />
    <dof index="825" value="-0.032170649424331739" cell_index="746" cell_dof_index="2" />
    <dof index="826" value="-0.030163743247383454" cell_index="812" cell_dof_index="2" />
    <dof index="827" value="-0.028207461645302311" cell_index="878" cell_dof_index="2" />
    <dof index="828" value="-0.026229126609006722" cell_index="944" cell_dof_index="2" />
    <dof index="829" value="-0.024157380378732659" cell_index="1010" cell_dof_index="2" />
    <dof index="830" value="-0.021928161602266967" cell_index="1076" cell_dof_index="2" />
    <dof index="831" value="-0.019490132270383417" cell_index="1142" cell_dof_index="2" />
    <dof index="832" value="-0.016809094396081706" cell_index="1208" cell_dof_index="2" />
    <dof index="833" value="-0.013871015305083717" cell_index="1274" cell_dof_index="2" />
    <dof index="834" value="-0.010683393118580155" cell_index="1340" cell_dof_index="2" />
    <dof index="835" value="-0.0072748304251296081" cell_index="1406" cell_dof_index="2" />
    <dof index="836" value="-0.003692833062432524" cell_index="20" cell_dof_index="1" />
    <dof index="837" value="0" cell_index="22" cell_dof_index="2" />
    <dof index="838" value="-0.036019619101815559" cell_index="88" cell_dof_index="2" />
    <dof index="839" value="-0.033787301884362762" cell_index="154" cell_dof_index="2" />
    <dof index="840" value="-0.031679543848155432" cell_index="220" cell_dof_index="2" />
    <dof index="841" value="-0.02962495439338525" cell_index="286" cell_dof_index="2" />
    <dof index="842" value="-0.027547203266322963" cell_index="352" cell_dof_index="2" />
    <dof index="843" value="-0.025371346808258487" cell_index="418" cell_dof_index="2" />
    <dof index="844" value="-0.023030104430049932" cell_index="484" cell_dof_index="2" />
    <dof index="845" value="-0.020469558264109677" cell_index="550" cell_dof_index="2" />
    <dof index="846" value="-0.017653791792391214" cell_index="616" cell_dof_index="2" />
    <dof index="847" value="-0.014568067165004549" cell_index="682" cell_dof_index="2" />
    <dof index="848" value="-0.011220259301752949" cell_index="748" cell_dof_index="2" />
    <dof index="849" value="-0.0076404081400202233" cell_index="814" cell_dof_index="2" />
    <dof index="850" value="-0.003878406800037898" cell_index="880" cell_dof_index="2" />
    <dof index="851" value="0" cell_index="946" cell_dof_index="2" />
    <dof index="852" value="-0.034296154883522945" cell_index="1012" cell_dof_index="2" />
    <dof index="853" value="-0.032170649424331205" cell_index="1078" cell_dof_index="2" />
    <dof index="854" value="-0.030163743247382954" cell_index="1144" cell_dof_index="2" />
    <dof index="855" value="-0.028207461645301846" cell_index="1210" cell_dof_index="2" />
    <dof index="856" value="-0.026229126609006288" cell_index="1276" cell_dof_index="2" />
    <dof index="857" value="-0.024157380378732256" cell_index="1342" cell_dof_index="2" />
    <dof index="858" value="-0.021928161602266599" cell_index="22" cell_dof_index="1" />
    <dof index="859" value="-0.019490132270383091" cell_index="24" cell_dof_index="2" />
    <dof index="860" value="-0.016809094396081421" cell_index="90" cell_dof_index="2" />
    <dof index="861" value="-0.013871015305083483" cell_index="156" cell_dof_index="2" />
    <dof index="862" value="-0.010683393118579975" cell_index="222" cell_dof_index="2" />
    <dof index="863" value="-0.0072748304251294858" cell_index="288" cell_dof_index="2" />
    <dof index="864" value="-0.0036928330624324619" cell_index="354" cell_dof_index="2" />
    <dof index="865" value="0" cell_index="420" cell_dof_index="2" />
    <dof index="866" value="-0.029275391408149852" cell_index="486" cell_dof_index="2" />
    <dof index="867" value="-0.027461047949843026" cell_index="552" cell_dof_index="2" />
    <dof index="868" value="-0.025747941508344516" cell_index="618" cell_dof_index="2" />
    <dof index="869" value="-0.024078048489725046" cell_index="684" cell_dof_index="2" />
    <dof index="870" value="-0.022389330535169921" cell_index="750" cell_dof_index="2" />
    <dof index="871" value="-0.020620876258134621" cell_index="816" cell_dof_index="2" />
    <dof index="872" value="-0.01871800252674782" cell_index="882" cell_dof_index="2" />
    <dof index="873" value="-0.016636886926534266" cell_index="948" cell_dof_index="2" />
    <dof index="874" value="-0.014348337862745079" cell_index="1014" cell_dof_index="2" />
    <dof index="875" value="-0.011840376965402924" cell_index="1080" cell_dof_index="2" />
    <dof index="876" value="-0.0091194046730825908" cell_index="1146" cell_dof_index="2" />
    <dof index="877" value="-0.0062098363168374519" cell_index="1212" cell_dof_index="2" />
    <dof index="878" value="-0.0031522231478959863" cell_index="1278" cell_dof_index="2" />
    <dof index="879" value="0" cell_index="24" cell_dof_index="1" />
    <dof index="880" value="-0.021393324835954162" cell_index="26" cell_dof_index="2" />
    <dof index="881" value="-0.020067472743102523" cell_index="92" cell_dof_index="2" />
    <dof index="882" value="-0.018815600750322251" cell_index="158" cell_dof_index="2" />
    <dof index="883" value="-0.017595307457209417" cell_index="224" cell_dof_index="2" />
    <dof index="884" value="-0.016361257628312895" cell_index="290" cell_dof_index="2" />
    <dof index="885" value="-0.015068939575970259" cell_index="356" cell_dof_index="2" />
    <dof index="886" value="-0.013678392980373613" cell_index="422" cell_dof_index="2" />
    <dof index="887" value="-0.01215759411432853" cell_index="488" cell_dof_index="2" />
    <dof index="888" value="-0.010485210888359735" cell_index="554" cell_dof_index="2" />
    <dof index="889" value="-0.0086524899725336363" cell_index="620" cell_dof_index="2" />
    <dof index="890" value="-0.006664108560046878" cell_index="686" cell_dof_index="2" />
    <dof index="891" value="-0.004537908431421535" cell_index="752" cell_dof_index="2" />
    <dof index="892" value="-0.0023035228741494964" cell_index="818" cell_dof_index="2" />
    <dof index="893" value="0" cell_index="884" cell_dof_index="2" />
    <dof index="894" value="-0.011334687343738012" cell_index="950" cell_dof_index="2" />
    <dof index="895" value="-0.010632219679092569" cell_index="1016" cell_dof_index="2" />
    <dof index="896" value="-0.0099689484138098926" cell_index="1082" cell_dof_index="2" />
    <dof index="897" value="-0.0093224082873378904" cell_index="1148" cell_dof_index="2" />
    <dof index="898" value="-0.0086685796242201522" cell_index="1214" cell_dof_index="2" />
    <dof index="899" value="-0.0079838790840145238" cell_index="26" cell_dof_index="1" />
    <dof index="900" value="-0.0072471347481599009" cell_index="28" cell_dof_index="2" />
    <dof index="901" value="-0.0064413796917807235" cell_index="94" cell_dof_index="2" />
    <dof index="902" value="-0.0055553116714695261" cell_index="160" cell_dof_index="2" />
    <dof index="903" value="-0.0045842929668731356" cell_index="226" cell_dof_index="2" />
    <dof index="904" value="-0.0035308016651022125" cell_index="292" cell_dof_index="2" />
    <dof index="905" value="-0.002404290761678681" cell_index="358" cell_dof_index="2" />
    <dof index="906" value="-0.0012204606702251658" cell_index="424" cell_dof_index="2" />
    <dof index="907" value="0" cell_index="490" cell_dof_index="2" />
    <dof index="908" value="-0.0019380620383237404" cell_index="556" cell_dof_index="2" />
    <dof index="909" value="-0.0018179505722804008" cell_index="622" cell_dof_index="2" />
    <dof index="910" value="-0.0017045411043901831" cell_index="688" cell_dof_index="2" />
    <dof index="911" value="-0.001593992411041295" cell_index="754" cell_dof_index="2" />
    <dof index="912" value="-0.0014821974869178244" cell_index="820" cell_dof_index="2" />
    <dof index="913" value="-0.0013651239334664014" cell_index="886" cell_dof_index="2" />
    <dof index="914" value="-0.0012391516692152203" cell_index="952" cell_dof_index="2" />
    <dof index="915" value="-0.0011013796037317716" cell_index="1018" cell_dof_index="2" />
    <dof index="916" value="-0.00094987522240567188" cell_index="1084" cell_dof_index="2" />
    <dof index="917" value="-0.00078384554440840153" cell_index="1150" cell_dof_index="2" />
    <dof index="918" value="-0.00060371428557888767" cell_index="28" cell_dof_index="1" />
    <dof index="919" value="-0.00041109776679250116" cell_index="30" cell_dof_index="2" />
    <dof index="920" value="-0.00020868052399674691" cell_index="96" cell_dof_index="2" />
    <dof index="921" value="0" cell_index="162" cell_dof_index="2" />
    <dof index="922" value="-0.0019645622292412653" cell_index="228" cell_dof_index="2" />
    <dof index="923" value="-0.0018428084128920058" cell_index="294" cell_dof_index="2" />
    <dof index="924" value="-0.0017278482348121675" cell_index="360" cell_dof_index="2" />
    <dof index="925" value="-0.0016157879482214231" cell_index="426" cell_dof_index="2" />
    <dof index="926" value="-0.001502464390455531" cell_index="492" cell_dof_index="2" />
    <dof index="927" value="-0.0013837900257521938" cell_index="558" cell_dof_index="2" />
    <dof index="928" value="-0.0012560952732694921" cell_index="624" cell_dof_index="2" />
    <dof index="929" value="-0.0011164393743657414" cell_index="690" cell_dof_index="2" />
    <dof index="930" value="-0.00096286339009268146" cell_index="756" cell_dof_index="2" />
    <dof index="931" value="-0.00079456349675766666" cell_index="822" cell_dof_index="2" />
    <dof index="932" value="-0.00061196920389993109" cell_index="888" cell_dof_index="2" />
    <dof index="933" value="-0.0004167189332414307" cell_index="954" cell_dof_index="2" />
    <dof index="934" value="-0.00021153392786996133" cell_index="1020" cell_dof_index="2" />
    <dof index="935" value="0" cell_index="1086" cell_dof_index="2" />
    <dof index="936" value="-0.011647803439591129" cell_index="30" cell_dof_index="1" />
    <dof index="937" value="-0.010925930393399071" cell_index="32" cell_dof_index="2" />
    <dof index="938" value="-0.010244336531049647" cell_index="98" cell_dof_index="2" />
    <dof index="939" value="-0.0095799359983684568" cell_index="164" cell_dof_index="2" />
    <dof index="940" value="-0.0089080455862016461" cell_index="230" cell_dof_index="2" />
    <dof index="941" value="-0.0082044304739856896" cell_index="296" cell_dof_index="2" />
    <dof index="942" value="-0.0074473338775799935" cell_index="362" cell_dof_index="2" />
    <dof index="943" value="-0.0066193201677579626" cell_index="428" cell_dof_index="2" />
    <dof index="944" value="-0.0057087748812667313" cell_index="494" cell_dof_index="2" />
    <dof index="945" value="-0.0047109321826277048" cell_index="560" cell_dof_index="2" />
    <dof index="946" value="-0.0036283386150930976" cell_index="626" cell_dof_index="2" />
    <dof index="947" value="-0.002470708309314739" cell_index="692" cell_dof_index="2" />
    <dof index="948" value="-0.0012541753964116188" cell_index="758" cell_dof_index="2" />
    <dof index="949" value="0" cell_index="824" cell_dof_index="2" />
    <dof index="950" value="-0.02243147137624622" cell_index="890" cell_dof_index="2" />
    <dof index="951" value="-0.021041280113411071" cell_index="956" cell_dof_index="2" />
    <dof index="952" value="-0.019728658957601723" cell_index="1022" cell_dof_index="2" />
    <dof index="953" value="-0.018449148910192819" cell_index="32" cell_dof_index="1" />
    <dof index="954" value="-0.017155214768304245" cell_index="34" cell_dof_index="2" />
    <dof index="955" value="-0.015800184840865799" cell_index="100" cell_dof_index="2" />
    <dof index="956" value="-0.014342159667329392" cell_index="166" cell_dof_index="2" />
    <dof index="957" value="-0.012747561516069351" cell_index="232" cell_dof_index="2" />
    <dof index="958" value="-0.010994023122617467" cell_index="298" cell_dof_index="2" />
    <dof index="959" value="-0.0090723663871992641" cell_index="364" cell_dof_index="2" />
    <dof index="960" value="-0.0069874954715622058" cell_index="430" cell_dof_index="2" />
    <dof index="961" value="-0.0047581179581952775" cell_index="496" cell_dof_index="2" />
    <dof index="962" value="-0.0024153051389736568" cell_index="562" cell_dof_index="2" />
    <dof index="963" value="0" cell_index="628" cell_dof_index="2" />
    <dof index="964" value="-0.031444068229614243" cell_index="694" cell_dof_index="2" />
    <dof index="965" value="-0.029495320945604503" cell_index="760" cell_dof_index="2" />
    <dof index="966" value="-0.027655310163850279" cell_index="826" cell_dof_index="2" />
    <dof index="967" value="-0.02586171399013663" cell_index="892" cell_dof_index="2" />
    <dof index="968" value="-0.02404789835763842" cell_index="958" cell_dof_index="2" />
    <dof index="969" value="-0.022148439656205967" cell_index="34" cell_dof_index="1" />
    <dof index="970" value="-0.020104603910071062" cell_index="36" cell_dof_index="2" />
    <dof index="971" value="-0.017869322406418399" cell_index="102" cell_dof_index="2" />
    <dof index="972" value="-0.015411241081207696" cell_index="168" cell_dof_index="2" />
    <dof index="973" value="-0.012717494224888033" cell_index="234" cell_dof_index="2" />
    <dof index="974" value="-0.009794956410866109" cell_index="300" cell_dof_index="2" />
    <dof index="975" value="-0.0066698516210790936" cell_index="366" cell_dof_index="2" />
    <dof index="976" value="-0.0033857350822581169" cell_index="432" cell_dof_index="2" />
    <dof index="977" value="0" cell_index="498" cell_dof_index="2" />
    <dof index="978" value="-0.037916957255460897" cell_index="564" cell_dof_index="2" />
    <dof index="979" value="-0.035567052436214185" cell_index="630" cell_dof_index="2" />
    <dof index="980" value="-0.033348267969398458" cell_index="696" cell_dof_index="2" />
    <dof index="981" value="-0.03118545274601052" cell_index="762" cell_dof_index="2" />
    <dof index="982" value="-0.028998255806209031" cell_index="828" cell_dof_index="2" />
    <dof index="983" value="-0.026707785824246037" cell_index="894" cell_dof_index="2" />
    <dof index="984" value="-0.024243218197134934" cell_index="36" cell_dof_index="1" />
    <dof index="985" value="-0.021547794926551338" cell_index="38" cell_dof_index="2" />
    <dof index="986" value="-0.018583707587156696" cell_index="104" cell_dof_index="2" />
    <dof index="987" value="-0.015335442010887851" cell_index="170" cell_dof_index="2" />
    <dof index="988" value="-0.011811287929980081" cell_index="236" cell_dof_index="2" />
    <dof index="989" value="-0.0080428676394531887" cell_index="302" cell_dof_index="2" />
    <dof index="990" value="-0.0040827023861813539" cell_index="368" cell_dof_index="2" />
    <dof index="991" value="0" cell_index="434" cell_dof_index="2" />
    <dof index="992" value="-0.041297714365105605" cell_index="500" cell_dof_index="2" />
    <dof index="993" value="-0.038738286999755532" cell_index="566" cell_dof_index="2" />
    <dof index="994" value="-0.036321670958258889" cell_index="632" cell_dof_index="2" />
    <dof index="995" value="-0.033966014497794531" cell_index="698" cell_dof_index="2" />
    <dof index="996" value="-0.031583802394866738" cell_index="764" cell_dof_index="2" />
    <dof index="997" value="-0.029089109204174783" cell_index="830" cell_dof_index="2" />
    <dof index="998" value="-0.026404795449455926" cell_index="38" cell_dof_index="1" />
    <dof index="999" value="-0.023469042467705571" cell_index="40" cell_dof_index="2" />
    <dof index="1000" value="-0.020240670753413653" cell_index="106" cell_dof_index="2" />
    <dof index="1001" value="-0.01670278286206826" cell_index="172" cell_dof_index="2" />
    <dof index="1002" value="-0.012864407656183581" cell_index="238" cell_dof_index="2" />
    <dof index="1003" value="-0.0087599869423238465" cell_index="304" cell_dof_index="2" />
    <dof index="1004" value="-0.004446724874210984" cell_index="370" cell_dof_index="2" />
    <dof index="1005" value="0" cell_index="436" cell_dof_index="2" />
    <dof index="1006" value="-0.041297714365105292" cell_index="502" cell_dof_index="2" />
    <dof index="1007" value="-0.038738286999755234" cell_index="568" cell_dof_index="2" />
    <dof index="1008" value="-0.036321670958258612" cell_index="634" cell_dof_index="2" />
    <dof index="1009" value="-0.033966014497794281" cell_index="700" cell_dof_index="2" />
    <dof index="1010" value="-0.031583802394866502" cell_index="766" cell_dof_index="2" />
    <dof index="1011" value="-0.029089109204174568" cell_index="40" cell_dof_index="1" />
    <dof index="1012" value="-0.026404795449455731" cell_index="42" cell_dof_index="2" />
    <dof index="1013" value="-0.023469042467705398" cell_index="108" cell_dof_index="2" />
    <dof index="1014" value="-0.020240670753413504" cell_index="174" cell_dof_index="2" />
    <dof index="1015" value="-0.016702782862068138" cell_index="240" cell_dof_index="2" />
    <dof index="1016" value="-0.012864407656183487" cell_index="306" cell_dof_index="2" />
    <dof index="1017" value="-0.0087599869423237824" cell_index="372" cell_dof_index="2" />
    <dof index="1018" value="-0.004446724874210951" cell_index="438" cell_dof_index="2" />
    <dof index="1019" value="0" cell_index="504" cell_dof_index="2" />
    <dof index="1020" value="-0.037916957255459793" cell_index="570" cell_dof_index="2" />
    <dof index="1021" value="-0.035567052436213158" cell_index="636" cell_dof_index="2" />
    <dof index="1022" value="-0.033348267969397494" cell_index="702" cell_dof_index="2" />
    <dof index="1023" value="-0.031185452746009614" cell_index="42" cell_dof_index="1" />
    <dof index="1024" value="-0.028998255806208184" cell_index="44" cell_dof_index="2" />
    <dof index="1025" value="-0.02670778582424526" cell_index="110" cell_dof_index="2" />
    <dof index="1026" value="-0.024243218197134226" cell_index="176" cell_dof_index="2" />
    <dof index="1027" value="-0.02154779492655071" cell_index="242" cell_dof_index="2" />
    <dof index="1028" value="-0.018583707587156155" cell_index="308" cell_dof_index="2" />
    <dof index="1029" value="-0.015335442010887403" cell_index="374" cell_dof_index="2" />
    <dof index="1030" value="-0.011811287929979737" cell_index="440" cell_dof_index="2" />
    <dof index="1031" value="-0.0080428676394529545" cell_index="506" cell_dof_index="2" />
    <dof index="1032" value="-0.0040827023861812351" cell_index="572" cell_dof_index="2" />
    <dof index="1033" value="0" cell_index="638" cell_dof_index="2" />
    <dof index="1034" value="-0.031444068229612696" cell_index="44" cell_dof_index="1" />
    <dof index="1035" value="-0.029495320945603053" cell_index="46" cell_dof_index="2" />
    <dof index="1036" value="-0.027655310163848919" cell_index="112" cell_dof_index="2" />
    <dof index="1037" value="-0.025861713990135357" cell_index="178" cell_dof_index="2" />
    <dof index="1038" value="-0.024047898357637234" cell_index="244" cell_dof_index="2" />
    <dof index="1039" value="-0.022148439656204874" cell_index="310" cell_dof_index="2" />
    <dof index="1040" value="-0.020104603910070074" cell_index="376" cell_dof_index="2" />
    <dof index="1041" value="-0.017869322406417518" cell_index="442" cell_dof_index="2" />
    <dof index="1042" value="-0.01541124108120694" cell_index="508" cell_dof_index="2" />
    <dof index="1043" value="-0.012717494224887408" cell_index="574" cell_dof_index="2" />
    <dof index="1044" value="-0.0097949564108656285" cell_index="46" cell_dof_index="1" />
    <dof index="1045" value="-0.0066698516210787666" cell_index="48" cell_dof_index="2" />
    <dof index="1046" value="-0.0033857350822579504" cell_index="114" cell_dof_index="2" />
    <dof index="1047" value="0" cell_index="180" cell_dof_index="2" />
    <dof index="1048" value="-0.022431471376244769" cell_index="246" cell_dof_index="2" />
    <dof index="1049" value="-0.021041280113409708" cell_index="312" cell_dof_index="2" />
    <dof index="1050" value="-0.019728658957600446" cell_index="378" cell_dof_index="2" />
    <dof index="1051" value="-0.018449148910191625" cell_index="444" cell_dof_index="2" />
    <dof index="1052" value="-0.017155214768303135" cell_index="510" cell_dof_index="2" />
    <dof index="1053" value="-0.015800184840864775" cell_index="48" cell_dof_index="1" />
    <dof index="1054" value="-0.014342159667328463" cell_index="50" cell_dof_index="2" />
    <dof index="1055" value="-0.012747561516068527" cell_index="116" cell_dof_index="2" />
    <dof index="1056" value="-0.010994023122616754" cell_index="182" cell_dof_index="2" />
    <dof index="1057" value="-0.009072366387198676" cell_index="248" cell_dof_index="2" />
    <dof index="1058" value="-0.006987495471561753" cell_index="314" cell_dof_index="2" />
    <dof index="1059" value="-0.0047581179581949705" cell_index="380" cell_dof_index="2" />
    <dof index="1060" value="-0.0024153051389735006" cell_index="446" cell_dof_index="2" />
    <dof index="1061" value="0" cell_index="50" cell_dof_index="1" />
    <dof index="1062" value="-0.011647803439590107" cell_index="52" cell_dof_index="2" />
    <dof index="1063" value="-0.010925930393398113" cell_index="118" cell_dof_index="2" />
    <dof index="1064" value="-0.010244336531048748" cell_index="184" cell_dof_index="2" />
    <dof index="1065" value="-0.009579935998367619" cell_index="250" cell_dof_index="2" />
    <dof index="1066" value="-0.0089080455862008672" cell_index="316" cell_dof_index="2" />
    <dof index="1067" value="-0.0082044304739849732" cell_index="382" cell_dof_index="2" />
    <dof index="1068" value="-0.007447333877579343" cell_index="52" cell_dof_index="1" />
    <dof index="1069" value="-0.006619320167757385" cell_index="54" cell_dof_index="2" />
    <dof index="1070" value="-0.0057087748812662325" cell_index="120" cell_dof_index="2" />
    <dof index="1071" value="-0.0047109321826272936" cell_index="186" cell_dof_index="2" />
    <dof index="1072" value="-0.003628338615092781" cell_index="252" cell_dof_index="2" />
    <dof index="1073" value="-0.0024707083093145239" cell_index="318" cell_dof_index="2" />
    <dof index="1074" value="-0.0012541753964115093" cell_index="54" cell_dof_index="1" />
    <dof index="1075" value="0" cell_index="56" cell_dof_index="2" />
    <dof index="1076" value="-0.0019645622292410736" cell_index="122" cell_dof_index="2" />
    <dof index="1077" value="-0.001842808412891826" cell_index="188" cell_dof_index="2" />
    <dof index="1078" value="-0.0017278482348119988" cell_index="254" cell_dof_index="2" />
    <dof index="1079" value="-0.0016157879482212654" cell_index="56" cell_dof_index="1" />
    <dof index="1080" value="-0.0015024643904553842" cell_index="58" cell_dof_index="2" />
    <dof index="1081" value="-0.0013837900257520584" cell_index="124" cell_dof_index="2" />
    <dof index="1082" value="-0.0012560952732693694" cell_index="190" cell_dof_index="2" />
    <dof index="1083" value="-0.0011164393743656323" cell_index="58" cell_dof_index="1" />
    <dof index="1084" value="-0.00096286339009258746" cell_index="60" cell_dof_index="2" />
    <dof index="1085" value="-0.00079456349675758903" cell_index="126" cell_dof_index="2" />
    <dof index="1086" value="-0.00061196920389987124" cell_index="60" cell_dof_index="1" />
    <dof index="1087" value="-0.00041671893324138993" cell_index="62" cell_dof_index="2" />
    <dof index="1088" value="-0.00021153392786994071" cell_index="62" cell_dof_index="1" />
  </function_data>
</dolfin>
